Workbook

Sheet Dashboard
A1: ARNALDO — Modelo financiero 2027–2031 · Dashboard ejecutivo
A2: Proyecto A (marca propia fabricada en Cuba). Condicionado a la confirmación jurídica de la Fase 0. Fecha de corte 10/10/2026.
A4: Escenario activo (cambiar en Assumptions!C4) | B4: =Assumptions!$D$4 -> Base
A6: Indicador | B6: Valor
A7: Unidades vendidas 2031 | B7: =INDEX(Engine!$C$14:$Y$14,1,(Assumptions!$C$4-1)*6+5) -> 6500
A8: Ingresos de la marca 2031 (antes de IEE) | B8: =INDEX(Engine!$C$33:$Y$33,1,(Assumptions!$C$4-1)*6+5) -> 107085.62
A9: EBITDA 2031 | B9: =INDEX(Engine!$C$41:$Y$41,1,(Assumptions!$C$4-1)*6+5) -> -13849.686
A10: EBITDA acumulado 2027–2031 | B10: =SUM(INDEX(Engine!$C$41:$Y$41,1,(Assumptions!$C$4-1)*6+1)+INDEX(Engine!$C$41:$Y$41,1,(Assumptions!$C$4-1)*6+2)+INDEX(Engine!$C$41:$Y$41,1,(Assumptions!$C$4-1)*6+3)+INDEX(Engine!$C$41:$Y$41,1,(Assumptions!$C$4-1)*6+4)+INDEX(Engine!$C$41:$Y$41,1,(Assumptions!$C$4-1)*6+5)) -> -94578.41
A11: Resultado neto acumulado | B11: =INDEX(Engine!$C$54:$Y$54,1,(Assumptions!$C$4-1)*6+1)+INDEX(Engine!$C$54:$Y$54,1,(Assumptions!$C$4-1)*6+2)+INDEX(Engine!$C$54:$Y$54,1,(Assumptions!$C$4-1)*6+3)+INDEX(Engine!$C$54:$Y$54,1,(Assumptions!$C$4-1)*6+4)+INDEX(Engine!$C$54:$Y$54,1,(Assumptions!$C$4-1)*6+5) -> -129034
A12: Necesidad máxima de financiación (capital + deuda) | B12: =INDEX(Scenarios!$B$16:$E$16,1,Assumptions!$C$4) -> 184160.48
A13: Capital aportado (Assumptions) | B13: =Assumptions!$C$9 -> 50000
A14: Financiación ajena máxima requerida | B14: =MAX(INDEX(Engine!$C$75:$Y$75,1,(Assumptions!$C$4-1)*6+1),INDEX(Engine!$C$75:$Y$75,1,(Assumptions!$C$4-1)*6+2),INDEX(Engine!$C$75:$Y$75,1,(Assumptions!$C$4-1)*6+3),INDEX(Engine!$C$75:$Y$75,1,(Assumptions!$C$4-1)*6+4),INDEX(Engine!$C$75:$Y$75,1,(Assumptions!$C$4-1)*6+5)) -> 153816.07
A15: VAN | B15: ='Investment Returns'!B21 -> -120972.97
A16: TIR del proyecto (con valor terminal) | B16: ='Investment Returns'!B22 -> no calculable
A17: Payback | B17: ='Investment Returns'!B24 -> no se recupera en 2027-2031
A18: Punto muerto EBITDA 2030 (unidades/año) | B18: =INDEX(Engine!$C$97:$Y$97,1,(Assumptions!$C$4-1)*6+4) -> 14298.461
A19: Contribución unitaria 2030 (€/u) | B19: =INDEX(Engine!$C$26:$Y$26,1,(Assumptions!$C$4-1)*6+4) -> 1.7477406
A20: Necesidad de caja de un pedido piloto (Working Capital) | B20: ='Working Capital'!$B$38 -> 65779.42
A21: Control de balance (0 = cuadra) | B21: =SUMPRODUCT(ABS(Engine!$C$84:$Y$84)) -> 0
A23: Veredicto financiero automático | B23: =IF(B14>0,"El capital no cubre la necesidad: requiere financiación adicional",IF(B9<=0,"EBITDA 2031 negativo: modelo no sostenible","Autofinanciable con el capital indicado")) -> El capital no cubre la necesidad: requiere financiación adicional
A24: Veredicto jurídico (no calculable) | B24: BLOQUEADO hasta confirmar por escrito la vía legal de fabricación y exportación en Cuba (Fase 0)
A26: Comparativa | B26: Conservador | C26: Base | D26: Optimista | E26: Estrés
A27: Unidades vendidas 2031 | B27: =Scenarios!B6 -> 2500 | C27: =Scenarios!C6 -> 6500 | D27: =Scenarios!D6 -> 12000 | E27: =Scenarios!E6 -> 0
A28: EBITDA 2031 | B28: =Scenarios!B12 -> -35632.408 | C28: =Scenarios!C12 -> -13849.686 | D28: =Scenarios!D12 -> 42857.176 | E28: =Scenarios!E12 -> -29172
A29: EBITDA acumulado 2027–2031 | B29: =Scenarios!B13 -> -161231.04 | C29: =Scenarios!C13 -> -94578.41 | D29: =Scenarios!D13 -> 42913.864 | E29: =Scenarios!E13 -> -154215.78
A30: Necesidad máxima de financiación (capital + deuda) | B30: =Scenarios!B16 -> 209452.12 | C30: =Scenarios!C16 -> 184160.48 | D30: =Scenarios!D16 -> 132822.63 | E30: =Scenarios!E16 -> 172818.08
A31: VAN (tasa de 'Assumptions') | B31: =Scenarios!B18 -> -131046.35 | C31: =Scenarios!C18 -> -120972.97 | D31: =Scenarios!D18 -> 10753.631 | E31: =Scenarios!E18 -> -116081
A32: TIR del proyecto (con valor terminal) | B32: =Scenarios!B19 -> n/c | C32: =Scenarios!C19 -> n/c | D32: =Scenarios!D19 -> 0.21640347 | E32: =Scenarios!E19 -> n/c
A33: Payback (año) | B33: =Scenarios!B20 -> > 2031 | C33: =Scenarios!C20 -> > 2031 | D33: =Scenarios!D20 -> > 2031 | E33: =Scenarios!E20 -> > 2031
A34: Punto muerto EBITDA 2030 (unidades) | B34: =Scenarios!B21 -> n/a | C34: =Scenarios!C21 -> 14298.461 | D34: =Scenarios!D21 -> 4663.7802 | E34: =Scenarios!E21 -> n/a
B36: 2027 | C36: 2028 | D36: 2029 | E36: 2030 | F36: 2031
A37: Serie gráfica: EBITDA escenario activo | B37: =INDEX(Engine!$C$41:$Y$41,1,(Assumptions!$C$4-1)*6+1) -> -27190 | C37: =INDEX(Engine!$C$41:$Y$41,1,(Assumptions!$C$4-1)*6+2) -> -20174.519 | D37: =INDEX(Engine!$C$41:$Y$41,1,(Assumptions!$C$4-1)*6+3) -> -17112.908 | E37: =INDEX(Engine!$C$41:$Y$41,1,(Assumptions!$C$4-1)*6+4) -> -16251.297 | F37: =INDEX(Engine!$C$41:$Y$41,1,(Assumptions!$C$4-1)*6+5) -> -13849.686

Sheet Assumptions
A1: Supuestos del modelo — Proyecto A (marca propia ARNALDO)
A2: Todos los valores en azul son editables. Estados: VERIFICADO / PROBABLE / HIPÓTESIS / BLOQUEADO. Fuentes en 'Sources & Validation'. Fecha de corte: 10/10/2026.
C3: Supuesto editable (input) | D3: Fórmula | E3: Resultado clave | F3: Alerta / bloqueo
A4: Escenario seleccionado (1=Conservador, 2=Base, 3=Optimista, 4=Estrés) | C4: 2 | D4: =INDEX({"Conservador","Base","Optimista","Estrés"},C4) -> Base
A6: 1. Parámetros generales
A7: Parámetro | B7: Unidad | C7: Valor | D7: Estado | E7: Fuente / nota
A8: Primer año del modelo | B8: año | C8: 2027 | D8: HIPÓTESIS | E8: Calendario del promotor
A9: Capital aportado por el promotor (año 1) | B9: € | C9: 50000 | D9: HIPÓTESIS | E9: Comparar 15k–100k en 'Scenarios'
A10: IVA tipo general | B10: % | C10: 0.21 | D10: VERIFICADO | E10: Ley 37/1992
A11: Impuesto especial cigarros: tipo ad valorem sobre PVP | B11: % | C11: 0.158 | D11: VERIFICADO | E11: S14
A12: Impuesto especial cigarros: mínimo | B12: €/1.000 u | C12: 47 | D12: VERIFICADO | E12: S14
A13: Margen del expendedor sobre PVP (cigarros) | B13: % | C13: 0.09 | D13: PROBABLE | E13: S15 (confirmar texto consolidado)
A14: Derecho arancelario UE 2402 10 00 (origen Cuba, sin preferencia) | B14: % CIF | C14: 0.26 | D14: PROBABLE | E14: S32 (confirmar TARIC)
A15: Seguro de transporte | B15: % valor | C15: 0.005 | D15: HIPÓTESIS | E15: Cotizar con transitario
A16: Marcas fiscales + identificador único trazabilidad | B16: €/u | C16: 0.03 | D16: HIPÓTESIS | E16: S27, S28 (coste a confirmar con FNMT/emisor)
A17: Despacho aduanero + agente + inspección por envío | B17: €/envío | C17: 450 | D17: HIPÓTESIS | E17: Cotizar agente de aduanas
A18: Envíos (importaciones) por año con actividad | B18: nº | C18: 2 | D18: HIPÓTESIS | E18: Política de compras
A19: Tipo de cambio USD por EUR | B19: USD/€ | C19: 1.15 | D19: HIPÓTESIS | E19: Si la fábrica cotiza en EUR, poner 1,00
... A24: Cobro al distribuidor | B24: días | C24: 45 | D24: HIPÓTESIS | E24: Negociar con distribuidor habilitado
A25: Pago a proveedores de gastos generales | B25: días | C25: 30 | D25: HIPÓTESIS
A26: IEE pagado al importar (1) o diferido en depósito fiscal (0) | B26: 1/0 | C26: 1 | D26: HIPÓTESIS | E26: Conservador = 1
A27: Fracción anual de IVA pendiente a cierre (liquidación trimestral) | B27: fracción | C27: 0.25 | D27: HIPÓTESIS
A28: Royalty a Arnaldo por nombre/firma (% ingresos de la marca antes de IEE) | B28: % | C28: 0 | D28: HIPÓTESIS | E28: 0% = opción B (sólo equity, recomendada). Opción A: 2% → VAN Optimista −4.561 € y TIR 16,4% (cálculo 10/10/2026)
A29: Participación de Arnaldo en la SL (opción B, con vesting) | B29: % | C29: 0.1 | D29: HIPÓTESIS | E29: Acuerdo con Arnaldo; reparto de valor, no coste
A30: Impuesto sobre Sociedades (España) | B30: % | C30: 0.25 | D30: PROBABLE | E30: N04 (15% nueva creación no aplicado: conservador)
A31: Coste de la financiación ajena (déficit de caja) | B31: % | C31: 0.07 | D31: HIPÓTESIS | E31: Póliza / préstamo socio
A32: Caja mínima operativa | B32: € | C32: 5000 | D32: HIPÓTESIS
A33: Vida útil intangibles (marca, diseño) | B33: años | C33: 5 | D33: HIPÓTESIS
A34: Tasa de descuento (riesgo alto, no cotizada) | B34: % | C34: 0.18 | D34: HIPÓTESIS | E34: Prima por riesgo país/regulatorio
A35: Múltiplo EV/EBITDA en 2031 (valor terminal) | B35: x | C35: 5 | D35: HIPÓTESIS | E35: Conservador para marca pequeña
A37: 2. Parámetros por escenario
A38: Parámetro | B38: Unidad | C38: Conservador | D38: Base | E38: Optimista | F38: Estrés | G38: Seleccionado | H38: Estado | I38: Fuente / nota
A39: PVP por unidad (IVA e IEE incluidos) | B39: €/u | C39: 20 | D39: 24 | E39: 28 | F39: 24 | G39: =INDEX(C39:F39,Assumptions!$C$4) -> 24 | H39: HIPÓTESIS | I39: Benchmarks S37/S38: Partagás D4 ≈21,20 €; Montecristo No.2 21,80 €; Davidoff Puro Dominicano 15,50 €. Ver rejilla 12–35 € en Unit Economics
A40: Precio de fabricación FOB/FCA por unidad (sin cotización) | B40: USD/u | C40: 7 | D40: 6 | E40: 5 | F40: 7.5 | G40: =INDEX(C40:F40,Assumptions!$C$4) -> 6 | H40: BLOQUEADO | I40: Requiere cotización formal del fabricante/exportador
A41: Factor sobre coste de packaging base ('Product Cost') | B41: x | C41: 1.1 | D41: 1 | E41: 0.9 | F41: 1.2 | G41: =INDEX(C41:F41,Assumptions!$C$4) -> 1 | H41: HIPÓTESIS
A42: Control de calidad en origen (inspección, catas, laboratorio) | B42: €/u | C42: 0.3 | D42: 0.25 | E42: 0.2 | F42: 0.35 | G42: =INDEX(C42:F42,Assumptions!$C$4) -> 0.25 | H42: HIPÓTESIS
A43: Flete internacional + manipulación hasta almacén | B43: €/u | C43: 0.7 | D43: 0.55 | E43: 0.4 | F43: 0.9 | G43: =INDEX(C43:F43,Assumptions!$C$4) -> 0.55 | H43: HIPÓTESIS | I43: Aéreo en lotes pequeños
A44: Honorario técnico de Arnaldo (pagado vía entidad autorizada) | B44: €/u | C44: 0.4 | D44: 0.35 | E44: 0.3 | F44: 0.4 | G44: =INDEX(C44:F44,Assumptions!$C$4) -> 0.35 | H44: BLOQUEADO | I44: Forma legal de pago sin confirmar
A45: Tarifa del distribuidor mayorista habilitado | B45: % PVP | C45: 0.06 | D45: 0.05 | E45: 0.045 | F45: 0.06 | G45: =INDEX(C45:F45,Assumptions!$C$4) -> 0.05 | H45: HIPÓTESIS | I45: Negociable; no regulada
A46: Merma y rechazos post-importación | B46: % compras | C46: 0.05 | D46: 0.03 | E46: 0.02 | F46: 0.08 | G46: =INDEX(C46:F46,Assumptions!$C$4) -> 0.03 | H46: HIPÓTESIS
A47: Muestras profesionales (sujetas a impuestos) | B47: % ventas | C47: 0.04 | D47: 0.03 | E47: 0.025 | F47: 0.04 | G47: =INDEX(C47:F47,Assumptions!$C$4) -> 0.03 | H47: HIPÓTESIS | I47: Sólo B2B: sin promoción al consumidor
A48: Plazo pedido→llegada a España | B48: meses | C48: 6 | D48: 5 | E48: 4 | F48: 10 | G48: =INDEX(C48:F48,Assumptions!$C$4) -> 5 | H48: HIPÓTESIS
A49: Año a partir del cual se bloquea el suministro | B49: año | C49: 9999 | D49: 9999 | E49: 9999 | F49: 2029 | G49: =INDEX(C49:F49,Assumptions!$C$4) -> 9999 | H49: HIPÓTESIS | I49: 9999 = sin bloqueo
A50: Factor sobre gastos fijos base ('Operating Expenses') | B50: x | C50: 1.15 | D50: 1 | E50: 1.1 | F50: 1.2 | G50: =INDEX(C50:F50,Assumptions!$C$4) -> 1 | H50: HIPÓTESIS | I50: Optimista: más esfuerzo comercial

Sheet Product Cost
A1: Coste de producto — desglose de packaging y coste en destino
A2: Packaging base por unidad (escenario Base). Los escenarios aplican el factor de 'Assumptions'. Todos los importes sin IVA.
A4: Componente (caja de 10 u) | B4: Unidad | C4: Coste por caja (€) | D4: Coste por unidad (€) | E4: Estado | F4: Nota
A5: Caja de cedro español macizo con bisagra y cierre | B5: caja | C5: 11.5 | D5: =C5/Assumptions!$C$20 -> 1.15 | E5: HIPÓTESIS | F5: Cotizar en Cuba (fabricación local) y en España
A6: Anilla principal (papel algodón, stamping oro, relieve) | B6: caja | C6: 1.2 | D6: =C6/Assumptions!$C$20 -> 0.12 | E6: HIPÓTESIS | F6: 0,12 €/u en tiradas ≥10.000
A7: Pie de anilla / numeración de pliego | B7: caja | C7: 0.4 | D7: =C7/Assumptions!$C$20 -> 0.04 | E7: HIPÓTESIS
A8: Hoja de cedro interior + papel de seda | B8: caja | C8: 0.6 | D8: =C8/Assumptions!$C$20 -> 0.06 | E8: HIPÓTESIS
A9: Colofón impreso numerado (tarjeta interior) | B9: caja | C9: 0.8 | D9: =C9/Assumptions!$C$20 -> 0.08 | E9: HIPÓTESIS | F9: Elemento de trazabilidad de lote
A10: Etiquetado de advertencias sanitarias (laterales/tapa) | B10: caja | C10: 0.7 | D10: =C10/Assumptions!$C$20 -> 0.07 | E10: HIPÓTESIS | F10: Diseño conforme RD 579/2017
A11: Precinto de garantía de la marca (no fiscal) | B11: caja | C11: 0.5 | D11: =C11/Assumptions!$C$20 -> 0.05 | E11: HIPÓTESIS | F11: No imita sellos de Habanos
A12: Retractilado + cartón exterior de expedición (prorrata) | B12: caja | C12: 0.8 | D12: =C12/Assumptions!$C$20 -> 0.08 | E12: HIPÓTESIS
A13: TOTAL packaging base | C13: =SUM(C5:C12) -> 16.5 | D13: =SUM(D5:D12) -> 1.65
A15: Coste en destino por unidad — escenario seleccionado (lee del motor)
A16: Concepto (€/u) | B16: 2027 | C16: 2028 | D16: 2029 | E16: 2030 | F16: 2031
A17: Fabricación FOB (€) | B17: =INDEX(Engine!$C$20:$Y$20,1,(Assumptions!$C$4-1)*6+1) -> 5.2173913 | C17: =INDEX(Engine!$C$20:$Y$20,1,(Assumptions!$C$4-1)*6+2) -> 5.2173913 | D17: =INDEX(Engine!$C$20:$Y$20,1,(Assumptions!$C$4-1)*6+3) -> 5.2173913 | E17: =INDEX(Engine!$C$20:$Y$20,1,(Assumptions!$C$4-1)*6+4) -> 5.2173913 | F17: =INDEX(Engine!$C$20:$Y$20,1,(Assumptions!$C$4-1)*6+5) -> 5.2173913
A18: Packaging | B18: =INDEX(Engine!$C$21:$Y$21,1,(Assumptions!$C$4-1)*6+1) -> 1.65 | C18: =INDEX(Engine!$C$21:$Y$21,1,(Assumptions!$C$4-1)*6+2) -> 1.65 | D18: =INDEX(Engine!$C$21:$Y$21,1,(Assumptions!$C$4-1)*6+3) -> 1.65 | E18: =INDEX(Engine!$C$21:$Y$21,1,(Assumptions!$C$4-1)*6+4) -> 1.65 | F18: =INDEX(Engine!$C$21:$Y$21,1,(Assumptions!$C$4-1)*6+5) -> 1.65
A19: Valor CIF (incl. QC, flete, seguro) | B19: =INDEX(Engine!$C$22:$Y$22,1,(Assumptions!$C$4-1)*6+1) -> 7.7057283 | C19: =INDEX(Engine!$C$22:$Y$22,1,(Assumptions!$C$4-1)*6+2) -> 7.7057283 | D19: =INDEX(Engine!$C$22:$Y$22,1,(Assumptions!$C$4-1)*6+3) -> 7.7057283 | E19: =INDEX(Engine!$C$22:$Y$22,1,(Assumptions!$C$4-1)*6+4) -> 7.7057283 | F19: =INDEX(Engine!$C$22:$Y$22,1,(Assumptions!$C$4-1)*6+5) -> 7.7057283
A20: Arancel | B20: =INDEX(Engine!$C$23:$Y$23,1,(Assumptions!$C$4-1)*6+1) -> 2.0034893 | C20: =INDEX(Engine!$C$23:$Y$23,1,(Assumptions!$C$4-1)*6+2) -> 2.0034893 | D20: =INDEX(Engine!$C$23:$Y$23,1,(Assumptions!$C$4-1)*6+3) -> 2.0034893 | E20: =INDEX(Engine!$C$23:$Y$23,1,(Assumptions!$C$4-1)*6+4) -> 2.0034893 | F20: =INDEX(Engine!$C$23:$Y$23,1,(Assumptions!$C$4-1)*6+5) -> 2.0034893
A21: Coste en destino (incl. marcas fiscales y honorario técnico) | B21: =INDEX(Engine!$C$24:$Y$24,1,(Assumptions!$C$4-1)*6+1) -> 10.089218 | C21: =INDEX(Engine!$C$24:$Y$24,1,(Assumptions!$C$4-1)*6+2) -> 10.089218 | D21: =INDEX(Engine!$C$24:$Y$24,1,(Assumptions!$C$4-1)*6+3) -> 10.089218 | E21: =INDEX(Engine!$C$24:$Y$24,1,(Assumptions!$C$4-1)*6+4) -> 10.089218 | F21: =INDEX(Engine!$C$24:$Y$24,1,(Assumptions!$C$4-1)*6+5) -> 10.089218
A22: Impuesto especial por unidad | B22: =INDEX(Engine!$C$25:$Y$25,1,(Assumptions!$C$4-1)*6+1) -> 3.792 | C22: =INDEX(Engine!$C$25:$Y$25,1,(Assumptions!$C$4-1)*6+2) -> 3.792 | D22: =INDEX(Engine!$C$25:$Y$25,1,(Assumptions!$C$4-1)*6+3) -> 3.792 | E22: =INDEX(Engine!$C$25:$Y$25,1,(Assumptions!$C$4-1)*6+4) -> 3.792 | F22: =INDEX(Engine!$C$25:$Y$25,1,(Assumptions!$C$4-1)*6+5) -> 3.792
A23: Contribución por unidad vendida | B23: =INDEX(Engine!$C$26:$Y$26,1,(Assumptions!$C$4-1)*6+1) -> 1.7477406 | C23: =INDEX(Engine!$C$26:$Y$26,1,(Assumptions!$C$4-1)*6+2) -> 1.7477406 | D23: =INDEX(Engine!$C$26:$Y$26,1,(Assumptions!$C$4-1)*6+3) -> 1.7477406 | E23: =INDEX(Engine!$C$26:$Y$26,1,(Assumptions!$C$4-1)*6+4) -> 1.7477406 | F23: =INDEX(Engine!$C$26:$Y$26,1,(Assumptions!$C$4-1)*6+5) -> 1.7477406
A25: Coste en destino por caja de 10 (2028) | C25: =C21*Assumptions!$C$20 -> 100.89218

Sheet Import & Taxes
A1: Importación y fiscalidad — simulación de un envío (DUA) y reparto del PVP
A2: Escenario seleccionado. El IVA de importación es recuperable (impacto de caja, no de coste). Base IVA importación = valor en aduana + arancel + IEE.
A4: Unidades del envío | C4: 3000
A5: Valor en aduana (CIF) por unidad | C5: =INDEX(Engine!$C$22:$Y$22,1,(Assumptions!$C$4-1)*6+2) -> 7.7057283
A6: Valor en aduana del envío | C6: =C4*C5 -> 23117.185
A7: Derecho arancelario | C7: =C6*Assumptions!$C$14 -> 6010.468
A8: Impuesto especial (si se paga al importar) | C8: =C4*INDEX(Engine!$C$25:$Y$25,1,(Assumptions!$C$4-1)*6+2)*Assumptions!$C$26 -> 11376
A9: Base imponible IVA importación | C9: =C6+C7+C8 -> 40503.653
A10: IVA de importación (recuperable) | C10: =C9*Assumptions!$C$10 -> 8505.7671
A11: Despacho y agente de aduanas | C11: =Assumptions!$C$17 -> 450
A12: PAGO TOTAL EN FRONTERA | C12: =C7+C8+C10+C11 -> 26342.235
A13: de ello, coste definitivo (arancel + despacho) | C13: =C7+C11 -> 6460.468
A14: de ello, impuesto recuperable vía precio de venta (IEE) | C14: =C8 -> 11376
A15: de ello, IVA recuperable vía liquidación (≈1 trimestre) | C15: =C10 -> 8505.7671
A17: Reparto del PVP de una unidad (año 2028, escenario seleccionado)
A18: Destino del PVP | C18: €/u | D18: % PVP
A19: IVA (Hacienda) | C19: =INDEX(Engine!$C$19:$Y$19,1,(Assumptions!$C$4-1)*6+2)*Assumptions!$C$10/(1+Assumptions!$C$10) -> 4.1652893 | D19: =C19/INDEX(Engine!$C$19:$Y$19,1,(Assumptions!$C$4-1)*6+2) -> 0.17355372
A20: Impuesto especial (Hacienda) | C20: =INDEX(Engine!$C$25:$Y$25,1,(Assumptions!$C$4-1)*6+2) -> 3.792 | D20: =C20/INDEX(Engine!$C$19:$Y$19,1,(Assumptions!$C$4-1)*6+2) -> 0.158
A21: Margen expendedor | C21: =INDEX(Engine!$C$19:$Y$19,1,(Assumptions!$C$4-1)*6+2)*Assumptions!$C$13 -> 2.16 | D21: =C21/INDEX(Engine!$C$19:$Y$19,1,(Assumptions!$C$4-1)*6+2) -> 0.09
A22: Tarifa distribuidor | C22: =INDEX(Engine!$C$19:$Y$19,1,(Assumptions!$C$4-1)*6+2)*Assumptions!$G$45 -> 1.2 | D22: =C22/INDEX(Engine!$C$19:$Y$19,1,(Assumptions!$C$4-1)*6+2) -> 0.05
A23: Arancel (Hacienda UE) | C23: =INDEX(Engine!$C$23:$Y$23,1,(Assumptions!$C$4-1)*6+2) -> 2.0034893 | D23: =C23/INDEX(Engine!$C$19:$Y$19,1,(Assumptions!$C$4-1)*6+2) -> 0.083478723
A24: Fabricación, packaging, QC, flete, seguro | C24: =INDEX(Engine!$C$22:$Y$22,1,(Assumptions!$C$4-1)*6+2) -> 7.7057283 | D24: =C24/INDEX(Engine!$C$19:$Y$19,1,(Assumptions!$C$4-1)*6+2) -> 0.32107201
A25: Marcas fiscales + honorario técnico | C25: =INDEX(Engine!$C$24:$Y$24,1,(Assumptions!$C$4-1)*6+2)-INDEX(Engine!$C$22:$Y$22,1,(Assumptions!$C$4-1)*6+2)-INDEX(Engine!$C$23:$Y$23,1,(Assumptions!$C$4-1)*6+2) -> 0.38 | D25: =C25/INDEX(Engine!$C$19:$Y$19,1,(Assumptions!$C$4-1)*6+2) -> 0.015833333
A26: Merma y muestras (coste + IEE) | C26: =(INDEX(Engine!$C$10:$Y$10,1,(Assumptions!$C$4-1)*6+2)-1)*(INDEX(Engine!$C$25:$Y$25,1,(Assumptions!$C$4-1)*6+2)+INDEX(Engine!$C$24:$Y$24,1,(Assumptions!$C$4-1)*6+2)) -> 0.84575254 | D26: =C26/INDEX(Engine!$C$19:$Y$19,1,(Assumptions!$C$4-1)*6+2) -> 0.035239689
A27: Royalty de nombre a Arnaldo | C27: =(INDEX(Engine!$C$19:$Y$19,1,(Assumptions!$C$4-1)*6+2)/(1+Assumptions!$C$10)-INDEX(Engine!$C$19:$Y$19,1,(Assumptions!$C$4-1)*6+2)*(Assumptions!$C$13+Assumptions!$G$45))*Assumptions!$C$28 -> 0 | D27: =C27/INDEX(Engine!$C$19:$Y$19,1,(Assumptions!$C$4-1)*6+2) -> 0
A28: Contribución de la marca (antes de gastos fijos) | C28: =INDEX(Engine!$C$26:$Y$26,1,(Assumptions!$C$4-1)*6+2) -> 1.7477406 | D28: =C28/INDEX(Engine!$C$19:$Y$19,1,(Assumptions!$C$4-1)*6+2) -> 0.072822525
A29: Control: suma = PVP | C29: =SUM(C19:C28) -> 24 | D29: =SUM(D19:D28) -> 1

Sheet Unit Economics
A1: Economía unitaria por nivel de PVP (costes del escenario seleccionado, año 2028)
A2: Cada columna recalcula impuestos y márgenes para el PVP indicado. Las cifras del distribuidor, expendedor y marca se separan explícitamente.
A4: Concepto (€/u) | B4: PVP 12 € | C4: PVP 15 € | D4: PVP 18 € | E4: PVP 20 € | F4: PVP 25 € | G4: PVP 30 € | H4: PVP 35 €
A5: PVP (input) | B5: 12 | C5: 15 | D5: 18 | E5: 20 | F5: 25 | G5: 30 | H5: 35
A6: IVA incluido en PVP | B6: =B5*Assumptions!$C$10/(1+Assumptions!$C$10) -> 2.0826446 | C6: =C5*Assumptions!$C$10/(1+Assumptions!$C$10) -> 2.6033058 | D6: =D5*Assumptions!$C$10/(1+Assumptions!$C$10) -> 3.1239669 | E6: =E5*Assumptions!$C$10/(1+Assumptions!$C$10) -> 3.4710744 | F6: =F5*Assumptions!$C$10/(1+Assumptions!$C$10) -> 4.338843 | G6: =G5*Assumptions!$C$10/(1+Assumptions!$C$10) -> 5.2066116 | H6: =H5*Assumptions!$C$10/(1+Assumptions!$C$10) -> 6.0743802
A7: Impuesto especial (15,8% PVP, mín. 0,047 €) | B7: =MAX(Assumptions!$C$11*B5,Assumptions!$C$12/1000) -> 1.896 | C7: =MAX(Assumptions!$C$11*C5,Assumptions!$C$12/1000) -> 2.37 | D7: =MAX(Assumptions!$C$11*D5,Assumptions!$C$12/1000) -> 2.844 | E7: =MAX(Assumptions!$C$11*E5,Assumptions!$C$12/1000) -> 3.16 | F7: =MAX(Assumptions!$C$11*F5,Assumptions!$C$12/1000) -> 3.95 | G7: =MAX(Assumptions!$C$11*G5,Assumptions!$C$12/1000) -> 4.74 | H7: =MAX(Assumptions!$C$11*H5,Assumptions!$C$12/1000) -> 5.53
A8: Margen expendedor | B8: =B5*Assumptions!$C$13 -> 1.08 | C8: =C5*Assumptions!$C$13 -> 1.35 | D8: =D5*Assumptions!$C$13 -> 1.62 | E8: =E5*Assumptions!$C$13 -> 1.8 | F8: =F5*Assumptions!$C$13 -> 2.25 | G8: =G5*Assumptions!$C$13 -> 2.7 | H8: =H5*Assumptions!$C$13 -> 3.15
A9: Tarifa distribuidor | B9: =B5*Assumptions!$G$45 -> 0.6 | C9: =C5*Assumptions!$G$45 -> 0.75 | D9: =D5*Assumptions!$G$45 -> 0.9 | E9: =E5*Assumptions!$G$45 -> 1 | F9: =F5*Assumptions!$G$45 -> 1.25 | G9: =G5*Assumptions!$G$45 -> 1.5 | H9: =H5*Assumptions!$G$45 -> 1.75
A10: Ingreso de la marca antes de IEE | B10: =B5/(1+Assumptions!$C$10)-B8-B9 -> 8.2373554 | C10: =C5/(1+Assumptions!$C$10)-C8-C9 -> 10.296694 | D10: =D5/(1+Assumptions!$C$10)-D8-D9 -> 12.356033 | E10: =E5/(1+Assumptions!$C$10)-E8-E9 -> 13.728926 | F10: =F5/(1+Assumptions!$C$10)-F8-F9 -> 17.161157 | G10: =G5/(1+Assumptions!$C$10)-G8-G9 -> 20.593388 | H10: =H5/(1+Assumptions!$C$10)-H8-H9 -> 24.02562
A11: Ingreso de la marca neto de IEE | B11: =B10-B7 -> 6.3413554 | C11: =C10-C7 -> 7.9266942 | D11: =D10-D7 -> 9.5120331 | E11: =E10-E7 -> 10.568926 | F11: =F10-F7 -> 13.211157 | G11: =G10-G7 -> 15.853388 | H11: =H10-H7 -> 18.49562
A12: Coste en destino (sin IEE) | B12: =INDEX(Engine!$C$24:$Y$24,1,(Assumptions!$C$4-1)*6+2) -> 10.089218 | C12: =INDEX(Engine!$C$24:$Y$24,1,(Assumptions!$C$4-1)*6+2) -> 10.089218 | D12: =INDEX(Engine!$C$24:$Y$24,1,(Assumptions!$C$4-1)*6+2) -> 10.089218 | E12: =INDEX(Engine!$C$24:$Y$24,1,(Assumptions!$C$4-1)*6+2) -> 10.089218 | F12: =INDEX(Engine!$C$24:$Y$24,1,(Assumptions!$C$4-1)*6+2) -> 10.089218 | G12: =INDEX(Engine!$C$24:$Y$24,1,(Assumptions!$C$4-1)*6+2) -> 10.089218 | H12: =INDEX(Engine!$C$24:$Y$24,1,(Assumptions!$C$4-1)*6+2) -> 10.089218
A13: Merma y muestras (coste + IEE) | B13: =(INDEX(Engine!$C$10:$Y$10,1,(Assumptions!$C$4-1)*6+2)-1)*(B7+B12) -> 0.73023336 | C13: =(INDEX(Engine!$C$10:$Y$10,1,(Assumptions!$C$4-1)*6+2)-1)*(C7+C12) -> 0.75911316 | D13: =(INDEX(Engine!$C$10:$Y$10,1,(Assumptions!$C$4-1)*6+2)-1)*(D7+D12) -> 0.78799295 | E13: =(INDEX(Engine!$C$10:$Y$10,1,(Assumptions!$C$4-1)*6+2)-1)*(E7+E12) -> 0.80724615 | F13: =(INDEX(Engine!$C$10:$Y$10,1,(Assumptions!$C$4-1)*6+2)-1)*(F7+F12) -> 0.85537913 | G13: =(INDEX(Engine!$C$10:$Y$10,1,(Assumptions!$C$4-1)*6+2)-1)*(G7+G12) -> 0.90351212 | H13: =(INDEX(Engine!$C$10:$Y$10,1,(Assumptions!$C$4-1)*6+2)-1)*(H7+H12) -> 0.95164511
A14: CONTRIBUCIÓN por unidad (tras royalty Arnaldo) | B14: =B11-B12-B13-B10*Assumptions!$C$28 -> -4.4780956 | C14: =C11-C12-C13-C10*Assumptions!$C$28 -> -2.9216365 | D14: =D11-D12-D13-D10*Assumptions!$C$28 -> -1.3651775 | E14: =E11-E12-E13-E10*Assumptions!$C$28 -> -0.32753813 | F14: =F11-F12-F13-F10*Assumptions!$C$28 -> 2.2665603 | G14: =G11-G12-G13-G10*Assumptions!$C$28 -> 4.8606587 | H14: =H11-H12-H13-H10*Assumptions!$C$28 -> 7.4547571
A15: Margen de contribución sobre ingreso neto de IEE | B15: =IF(B11<>0,B14/B11,0) -> -0.70617326 | C15: =IF(C11<>0,C14/C11,0) -> -0.36858197 | D15: =IF(D11<>0,D14/D11,0) -> -0.14352111 | E15: =IF(E11<>0,E14/E11,0) -> -0.030990675 | F15: =IF(F11<>0,F14/F11,0) -> 0.1715641 | G15: =IF(G11<>0,G14/G11,0) -> 0.30660062 | H15: =IF(H11<>0,H14/H11,0) -> 0.40305527
A16: Contribución sobre PVP | B16: =B14/B5 -> -0.37317463 | C16: =C14/C5 -> -0.19477577 | D16: =D14/D5 -> -0.075843194 | E16: =E14/E5 -> -0.016376907 | F16: =F14/F5 -> 0.090662411 | G16: =G14/G5 -> 0.16202196 | H16: =H14/H5 -> 0.21299306
A17: Punto muerto EBITDA 2030 (unidades/año) | B17: =IF(B14>0,(INDEX(Engine!$C$40:$Y$40,1,(Assumptions!$C$4-1)*6+4)+Assumptions!$C$18*Assumptions!$C$17)/B14,"no viable") -> no viable | C17: =IF(C14>0,(INDEX(Engine!$C$40:$Y$40,1,(Assumptions!$C$4-1)*6+4)+Assumptions!$C$18*Assumptions!$C$17)/C14,"no viable") -> no viable | D17: =IF(D14>0,(INDEX(Engine!$C$40:$Y$40,1,(Assumptions!$C$4-1)*6+4)+Assumptions!$C$18*Assumptions!$C$17)/D14,"no viable") -> no viable | E17: =IF(E14>0,(INDEX(Engine!$C$40:$Y$40,1,(Assumptions!$C$4-1)*6+4)+Assumptions!$C$18*Assumptions!$C$17)/E14,"no viable") -> no viable | F17: =IF(F14>0,(INDEX(Engine!$C$40:$Y$40,1,(Assumptions!$C$4-1)*6+4)+Assumptions!$C$18*Assumptions!$C$17)/F14,"no viable") -> 11025.517 | G17: =IF(G14>0,(INDEX(Engine!$C$40:$Y$40,1,(Assumptions!$C$4-1)*6+4)+Assumptions!$C$18*Assumptions!$C$17)/G14,"no viable") -> 5141.2785 | H17: =IF(H14>0,(INDEX(Engine!$C$40:$Y$40,1,(Assumptions!$C$4-1)*6+4)+Assumptions!$C$18*Assumptions!$C$17)/H14,"no viable") -> 3352.2219
A18: FOB máximo (USD) para contribución ≥ 25% del ingreso neto | B18: =MAX(0,((B11*0.75-B10*Assumptions!$C$28-B7*(INDEX(Engine!$C$10:$Y$10,1,(Assumptions!$C$4-1)*6+2)-1))/INDEX(Engine!$C$10:$Y$10,1,(Assumptions!$C$4-1)*6+2)-(INDEX(Engine!$C$24:$Y$24,1,(Assumptions!$C$4-1)*6+2)-INDEX(Engine!$C$20:$Y$20,1,(Assumptions!$C$4-1)*6+2)*(1+Assumptions!$C$15)*(1+Assumptions!$C$14)))/((1+Assumptions!$C$15)*(1+Assumptions!$C$14))*Assumptions!$C$19) -> 0.8096807 | C18: =MAX(0,((C11*0.75-C10*Assumptions!$C$28-C7*(INDEX(Engine!$C$10:$Y$10,1,(Assumptions!$C$4-1)*6+2)-1))/INDEX(Engine!$C$10:$Y$10,1,(Assumptions!$C$4-1)*6+2)-(INDEX(Engine!$C$24:$Y$24,1,(Assumptions!$C$4-1)*6+2)-INDEX(Engine!$C$20:$Y$20,1,(Assumptions!$C$4-1)*6+2)*(1+Assumptions!$C$15)*(1+Assumptions!$C$14)))/((1+Assumptions!$C$15)*(1+Assumptions!$C$14))*Assumptions!$C$19) -> 1.8027508 | D18: =MAX(0,((D11*0.75-D10*Assumptions!$C$28-D7*(INDEX(Engine!$C$10:$Y$10,1,(Assumptions!$C$4-1)*6+2)-1))/INDEX(Engine!$C$10:$Y$10,1,(Assumptions!$C$4-1)*6+2)-(INDEX(Engine!$C$24:$Y$24,1,(Assumptions!$C$4-1)*6+2)-INDEX(Engine!$C$20:$Y$20,1,(Assumptions!$C$4-1)*6+2)*(1+Assumptions!$C$15)*(1+Assumptions!$C$14)))/((1+Assumptions!$C$15)*(1+Assumptions!$C$14))*Assumptions!$C$19) -> 2.795821 | E18: =MAX(0,((E11*0.75-E10*Assumptions!$C$28-E7*(INDEX(Engine!$C$10:$Y$10,1,(Assumptions!$C$4-1)*6+2)-1))/INDEX(Engine!$C$10:$Y$10,1,(Assumptions!$C$4-1)*6+2)-(INDEX(Engine!$C$24:$Y$24,1,(Assumptions!$C$4-1)*6+2)-INDEX(Engine!$C$20:$Y$20,1,(Assumptions!$C$4-1)*6+2)*(1+Assumptions!$C$15)*(1+Assumptions!$C$14)))/((1+Assumptions!$C$15)*(1+Assumptions!$C$14))*Assumptions!$C$19) -> 3.4578678 | F18: =MAX(0,((F11*0.75-F10*Assumptions!$C$28-F7*(INDEX(Engine!$C$10:$Y$10,1,(Assumptions!$C$4-1)*6+2)-1))/INDEX(Engine!$C$10:$Y$10,1,(Assumptions!$C$4-1)*6+2)-(INDEX(Engine!$C$24:$Y$24,1,(Assumptions!$C$4-1)*6+2)-INDEX(Engine!$C$20:$Y$20,1,(Assumptions!$C$4-1)*6+2)*(1+Assumptions!$C$15)*(1+Assumptions!$C$14)))/((1+Assumptions!$C$15)*(1+Assumptions!$C$14))*Assumptions!$C$19) -> 5.1129847 | G18: =MAX(0,((G11*0.75-G10*Assumptions!$C$28-G7*(INDEX(Engine!$C$10:$Y$10,1,(Assumptions!$C$4-1)*6+2)-1))/INDEX(Engine!$C$10:$Y$10,1,(Assumptions!$C$4-1)*6+2)-(INDEX(Engine!$C$24:$Y$24,1,(Assumptions!$C$4-1)*6+2)-INDEX(Engine!$C$20:$Y$20,1,(Assumptions!$C$4-1)*6+2)*(1+Assumptions!$C$15)*(1+Assumptions!$C$14)))/((1+Assumptions!$C$15)*(1+Assumptions!$C$14))*Assumptions!$C$19) -> 6.7681016 | H18: =MAX(0,((H11*0.75-H10*Assumptions!$C$28-H7*(INDEX(Engine!$C$10:$Y$10,1,(Assumptions!$C$4-1)*6+2)-1))/INDEX(Engine!$C$10:$Y$10,1,(Assumptions!$C$4-1)*6+2)-(INDEX(Engine!$C$24:$Y$24,1,(Assumptions!$C$4-1)*6+2)-INDEX(Engine!$C$20:$Y$20,1,(Assumptions!$C$4-1)*6+2)*(1+Assumptions!$C$15)*(1+Assumptions!$C$14)))/((1+Assumptions!$C$15)*(1+Assumptions!$C$14))*Assumptions!$C$19) -> 8.4232185
A21: Lectura: el Estado (IVA+IEE+arancel) captura ~35-40% del PVP; el canal (expendedor+distribuidor) ~14%. La marca debe pagar fábrica, logística y estructura con el resto.

Sheet Sales Forecast
A1: Previsión de demanda (unidades) por escenario
A2: Demanda B2B a través del canal legal (distribuidor habilitado → expendedurías). 2027 = año de habilitaciones, sin ventas.
A4: Escenario | B4: 2027 | C4: 2028 | D4: 2029 | E4: 2030 | F4: 2031 | G4: Total
A5: Conservador | B5: 0 | C5: 1000 | D5: 1500 | E5: 2000 | F5: 2500 | G5: =SUM(B5:F5) -> 7000
A6: Base | B6: 0 | C6: 2000 | D6: 3500 | E6: 5000 | F6: 6500 | G6: =SUM(B6:F6) -> 17000
A7: Optimista | B7: 0 | C7: 3500 | D7: 6000 | E7: 9000 | F7: 12000 | G7: =SUM(B7:F7) -> 30500
A8: Estrés (demanda; suministro bloqueado desde 2029) | B8: 0 | C8: 2000 | D8: 3500 | E8: 5000 | F8: 6500 | G8: =SUM(B8:F8) -> 17000
A11: Escenario seleccionado — volumen derivado y esfuerzo comercial
A12: Concepto | B12: 2027 | C12: 2028 | D12: 2029 | E12: 2030 | F12: 2031
A13: Unidades vendidas | B13: =INDEX(Engine!$C$14:$Y$14,1,(Assumptions!$C$4-1)*6+1) -> 0 | C13: =INDEX(Engine!$C$14:$Y$14,1,(Assumptions!$C$4-1)*6+2) -> 2000 | D13: =INDEX(Engine!$C$14:$Y$14,1,(Assumptions!$C$4-1)*6+3) -> 3500 | E13: =INDEX(Engine!$C$14:$Y$14,1,(Assumptions!$C$4-1)*6+4) -> 5000 | F13: =INDEX(Engine!$C$14:$Y$14,1,(Assumptions!$C$4-1)*6+5) -> 6500
A14: Unidades importadas | B14: =INDEX(Engine!$C$13:$Y$13,1,(Assumptions!$C$4-1)*6+1) -> 1000 | C14: =INDEX(Engine!$C$13:$Y$13,1,(Assumptions!$C$4-1)*6+2) -> 2871.8557 | D14: =INDEX(Engine!$C$13:$Y$13,1,(Assumptions!$C$4-1)*6+3) -> 4463.2474 | E14: =INDEX(Engine!$C$13:$Y$13,1,(Assumptions!$C$4-1)*6+4) -> 6054.6392 | F14: =INDEX(Engine!$C$13:$Y$13,1,(Assumptions!$C$4-1)*6+5) -> 6896.0309
A15: Stock final (unidades) | B15: =INDEX(Engine!$C$16:$Y$16,1,(Assumptions!$C$4-1)*6+1) -> 1000 | C15: =INDEX(Engine!$C$16:$Y$16,1,(Assumptions!$C$4-1)*6+2) -> 1750 | D15: =INDEX(Engine!$C$16:$Y$16,1,(Assumptions!$C$4-1)*6+3) -> 2500 | E15: =INDEX(Engine!$C$16:$Y$16,1,(Assumptions!$C$4-1)*6+4) -> 3250 | F15: =INDEX(Engine!$C$16:$Y$16,1,(Assumptions!$C$4-1)*6+5) -> 3250
A16: Cajas vendidas | B16: =B13/Assumptions!$C$20 -> 0 | C16: =C13/Assumptions!$C$20 -> 200 | D16: =D13/Assumptions!$C$20 -> 350 | E16: =E13/Assumptions!$C$20 -> 500 | F16: =F13/Assumptions!$C$20 -> 650
A17: Puntos de venta activos necesarios | B17: =INDEX(Engine!$C$99:$Y$99,1,(Assumptions!$C$4-1)*6+1) -> 0 | C17: =INDEX(Engine!$C$99:$Y$99,1,(Assumptions!$C$4-1)*6+2) -> 50 | D17: =INDEX(Engine!$C$99:$Y$99,1,(Assumptions!$C$4-1)*6+3) -> 87.5 | E17: =INDEX(Engine!$C$99:$Y$99,1,(Assumptions!$C$4-1)*6+4) -> 125 | F17: =INDEX(Engine!$C$99:$Y$99,1,(Assumptions!$C$4-1)*6+5) -> 162.5
A18: Ventas a PVP (consumidor) | B18: =INDEX(Engine!$C$29:$Y$29,1,(Assumptions!$C$4-1)*6+1) -> 0 | C18: =INDEX(Engine!$C$29:$Y$29,1,(Assumptions!$C$4-1)*6+2) -> 48000 | D18: =INDEX(Engine!$C$29:$Y$29,1,(Assumptions!$C$4-1)*6+3) -> 84000 | E18: =INDEX(Engine!$C$29:$Y$29,1,(Assumptions!$C$4-1)*6+4) -> 120000 | F18: =INDEX(Engine!$C$29:$Y$29,1,(Assumptions!$C$4-1)*6+5) -> 156000

Sheet Operating Expenses
A1: Gastos operativos fijos y CAPEX (escenario Base, € sin IVA)
A2: El motor multiplica el total por el factor de escenario. 'Remuneración del promotor' = 0: el modelo muestra el resultado ANTES de retribuir al gestor.
A4: Partida | B4: Estado | C4: 2027 | D4: 2028 | E4: 2029 | F4: 2030 | G4: 2031
A5: Due diligence jurídica Cuba (Fase 0) — abogado cubano + español | B5: HIPÓTESIS | C5: 6000 | D5: 0 | E5: 0 | F5: 0 | G5: 0
A6: Asesoría jurídica España: contratos, sociedad, propiedad intelectual | B6: HIPÓTESIS | C6: 6000 | D6: 2500 | E6: 2500 | F6: 2500 | G6: 2500
A7: Habilitación CMT, notificación EU-CEG, gestión regulatoria | B7: HIPÓTESIS | C7: 3000 | D7: 800 | E7: 800 | F7: 1500 | G7: 800
A8: Gestoría, contabilidad, auditoría ligera | B8: HIPÓTESIS | C8: 1800 | D8: 3600 | E8: 3600 | F8: 3800 | G8: 4000
A9: Seguros (RC producto, mercancía en almacén) | B9: HIPÓTESIS | C9: 600 | D9: 1500 | E9: 1500 | F9: 1600 | G9: 1700
A10: Almacén climatizado / depósito (3PL) | B10: HIPÓTESIS | C10: 0 | D10: 1800 | E10: 2400 | F10: 3000 | G10: 3600
A11: Viajes a Cuba (negociación, control de calidad) | B11: HIPÓTESIS | C11: 5000 | D11: 3000 | E11: 3000 | F11: 3000 | G11: 3000
A12: Desarrollo comercial B2B (ferias profesionales, logística de muestras) | B12: HIPÓTESIS | C12: 1000 | D12: 6000 | E12: 5000 | F12: 5000 | G12: 5000
A13: Software, trazabilidad, registros | B13: HIPÓTESIS | C13: 500 | D13: 1200 | E13: 1200 | F13: 1200 | G13: 1200
A14: Renovaciones y vigilancia de marcas | B14: HIPÓTESIS | C14: 0 | D14: 300 | E14: 300 | F14: 300 | G14: 300
A15: Remuneración del promotor (no incluida) | B15: HIPÓTESIS | C15: 0 | D15: 0 | E15: 0 | F15: 0 | G15: 0
A16: Imprevistos (% sobre el subtotal) | B16: 0.1 | C16: =SUM(C5:C15)*$B$16 -> 2390 | D16: =SUM(D5:D15)*$B$16 -> 2070 | E16: =SUM(E5:E15)*$B$16 -> 2030 | F16: =SUM(F5:F15)*$B$16 -> 2190 | G16: =SUM(G5:G15)*$B$16 -> 2210
A17: TOTAL GASTOS FIJOS (base) | C17: =SUM(C5:C16) -> 26290 | D17: =SUM(D5:D16) -> 22770 | E17: =SUM(E5:E16) -> 22330 | F17: =SUM(F5:F16) -> 24090 | G17: =SUM(G5:G16) -> 24310
A19: CAPEX intangible (amortizable)
A20: Registro de marcas: EUIPO clase 34 + Cuba (OCPI vía agente) + vigilancia | B20: PROBABLE | C20: 4000 | D20: 0 | E20: 0 | F20: 0 | G20: 0
A21: Diseño de identidad, artes finales, troqueles y planchas | B21: HIPÓTESIS | C21: 9000 | D21: 0 | E21: 3000 | F21: 0 | G21: 0
A22: TOTAL CAPEX | C22: =SUM(C20:C21) -> 13000 | D22: =SUM(D20:D21) -> 0 | E22: =SUM(E20:E21) -> 3000 | F22: =SUM(F20:F21) -> 0 | G22: =SUM(G20:G21) -> 0

Sheet Working Capital
A1: Capital circulante y desajuste temporal de caja
A2: Parte 1: saldos anuales. Parte 2: ciclo de caja mensual de un pedido (anticipo a Cuba → producción → transporte → frontera → ventas → cobro).
A3: ="Escenario: "&Assumptions!$D$4 -> Escenario: Base
A5: Concepto | B5: 2027 | C5: 2028 | D5: 2029 | E5: 2030 | F5: 2031
A6: Existencias | B6: =INDEX(Engine!$C$57:$Y$57,1,(Assumptions!$C$4-1)*6+1) -> 10089.218 | C6: =INDEX(Engine!$C$57:$Y$57,1,(Assumptions!$C$4-1)*6+2) -> 17656.131 | D6: =INDEX(Engine!$C$57:$Y$57,1,(Assumptions!$C$4-1)*6+3) -> 25223.044 | E6: =INDEX(Engine!$C$57:$Y$57,1,(Assumptions!$C$4-1)*6+4) -> 32789.957 | F6: =INDEX(Engine!$C$57:$Y$57,1,(Assumptions!$C$4-1)*6+5) -> 32789.957
A7: IEE anticipado sobre existencias | B7: =INDEX(Engine!$C$59:$Y$59,1,(Assumptions!$C$4-1)*6+1) -> 3792 | C7: =INDEX(Engine!$C$59:$Y$59,1,(Assumptions!$C$4-1)*6+2) -> 6636 | D7: =INDEX(Engine!$C$59:$Y$59,1,(Assumptions!$C$4-1)*6+3) -> 9480 | E7: =INDEX(Engine!$C$59:$Y$59,1,(Assumptions!$C$4-1)*6+4) -> 12324 | F7: =INDEX(Engine!$C$59:$Y$59,1,(Assumptions!$C$4-1)*6+5) -> 12324
A8: Anticipos a fábrica | B8: =INDEX(Engine!$C$61:$Y$61,1,(Assumptions!$C$4-1)*6+1) -> 4258.3585 | C8: =INDEX(Engine!$C$61:$Y$61,1,(Assumptions!$C$4-1)*6+2) -> 6618.058 | D8: =INDEX(Engine!$C$61:$Y$61,1,(Assumptions!$C$4-1)*6+3) -> 8977.7575 | E8: =INDEX(Engine!$C$61:$Y$61,1,(Assumptions!$C$4-1)*6+4) -> 10225.365 | F8: =INDEX(Engine!$C$61:$Y$61,1,(Assumptions!$C$4-1)*6+5) -> 10225.365
A9: Clientes | B9: =INDEX(Engine!$C$60:$Y$60,1,(Assumptions!$C$4-1)*6+1) -> 0 | C9: =INDEX(Engine!$C$60:$Y$60,1,(Assumptions!$C$4-1)*6+2) -> 4915.3315 | D9: =INDEX(Engine!$C$60:$Y$60,1,(Assumptions!$C$4-1)*6+3) -> 8601.8301 | E9: =INDEX(Engine!$C$60:$Y$60,1,(Assumptions!$C$4-1)*6+4) -> 12288.329 | F9: =INDEX(Engine!$C$60:$Y$60,1,(Assumptions!$C$4-1)*6+5) -> 15974.827
A10: Hacienda deudora IVA | B10: =INDEX(Engine!$C$63:$Y$63,1,(Assumptions!$C$4-1)*6+1) -> 708.81392 | C10: =INDEX(Engine!$C$63:$Y$63,1,(Assumptions!$C$4-1)*6+2) -> 2035.6113 | D10: =INDEX(Engine!$C$63:$Y$63,1,(Assumptions!$C$4-1)*6+3) -> 3163.6119 | E10: =INDEX(Engine!$C$63:$Y$63,1,(Assumptions!$C$4-1)*6+4) -> 4291.6126 | F10: =INDEX(Engine!$C$63:$Y$63,1,(Assumptions!$C$4-1)*6+5) -> 4888.0027
A11: (-) Proveedores | B11: =INDEX(Engine!$C$64:$Y$64,1,(Assumptions!$C$4-1)*6+1) -> 2160.8219 | C11: =INDEX(Engine!$C$64:$Y$64,1,(Assumptions!$C$4-1)*6+2) -> 1871.5068 | D11: =INDEX(Engine!$C$64:$Y$64,1,(Assumptions!$C$4-1)*6+3) -> 1835.3425 | E11: =INDEX(Engine!$C$64:$Y$64,1,(Assumptions!$C$4-1)*6+4) -> 1980 | F11: =INDEX(Engine!$C$64:$Y$64,1,(Assumptions!$C$4-1)*6+5) -> 1998.0822
A12: (-) Hacienda acreedora IVA | B12: =INDEX(Engine!$C$66:$Y$66,1,(Assumptions!$C$4-1)*6+1) -> 0 | C12: =INDEX(Engine!$C$66:$Y$66,1,(Assumptions!$C$4-1)*6+2) -> 1729.8446 | D12: =INDEX(Engine!$C$66:$Y$66,1,(Assumptions!$C$4-1)*6+3) -> 3027.2281 | E12: =INDEX(Engine!$C$66:$Y$66,1,(Assumptions!$C$4-1)*6+4) -> 4324.6116 | F12: =INDEX(Engine!$C$66:$Y$66,1,(Assumptions!$C$4-1)*6+5) -> 5621.995
A13: CAPITAL CIRCULANTE NETO | B13: =INDEX(Engine!$C$67:$Y$67,1,(Assumptions!$C$4-1)*6+1) -> 16687.568 | C13: =INDEX(Engine!$C$67:$Y$67,1,(Assumptions!$C$4-1)*6+2) -> 34259.78 | D13: =INDEX(Engine!$C$67:$Y$67,1,(Assumptions!$C$4-1)*6+3) -> 50583.673 | E13: =INDEX(Engine!$C$67:$Y$67,1,(Assumptions!$C$4-1)*6+4) -> 65614.652 | F13: =INDEX(Engine!$C$67:$Y$67,1,(Assumptions!$C$4-1)*6+5) -> 68582.075
A14: Variación | B14: =INDEX(Engine!$C$68:$Y$68,1,(Assumptions!$C$4-1)*6+1) -> 16687.568 | C14: =INDEX(Engine!$C$68:$Y$68,1,(Assumptions!$C$4-1)*6+2) -> 17572.212 | D14: =INDEX(Engine!$C$68:$Y$68,1,(Assumptions!$C$4-1)*6+3) -> 16323.893 | E14: =INDEX(Engine!$C$68:$Y$68,1,(Assumptions!$C$4-1)*6+4) -> 15030.979 | F14: =INDEX(Engine!$C$68:$Y$68,1,(Assumptions!$C$4-1)*6+5) -> 2967.4232
A18: Parte 2 — Ciclo de caja de un pedido (meses desde el pedido)
A19: Unidades del pedido | B19: 3000
A20: Meses de venta del lote tras llegada (incl. 1 mes de publicación de PVP en BOE) | B20: 12
A21: Incluir gastos fijos mensuales (1=sí) | B21: 1
A22: Plazo pedido→llegada (meses, escenario) | B22: =Assumptions!$G$48 -> 5
A23: Retraso de cobro (meses) = DSO/30 | B23: =ROUND(Assumptions!$C$24/30,0) -> 2
A25: Mes | B25: 0 | C25: 1 | D25: 2 | E25: 3 | F25: 4 | G25: 5 | H25: 6 | I25: 7 | J25: 8 | K25: 9 | L25: 10 | M25: 11 | N25: 12 | O25: 13 | P25: 14 | Q25: 15 | R25: 16 | S25: 17 | T25: 18 | U25: 19 | V25: 20 | W25: 21 | X25: 22 | Y25: 23 | Z25: 24
A26: Anticipo a fábrica | B26: =IF(B$25=0,-Assumptions!$C$23*$B$19*(INDEX(Engine!$C$20:$Y$20,1,(Assumptions!$C$4-1)*6+2)+INDEX(Engine!$C$21:$Y$21,1,(Assumptions!$C$4-1)*6+2)+Assumptions!$G$42),0) -> -10676.087 | C26: =IF(C$25=0,-Assumptions!$C$23*$B$19*(INDEX(Engine!$C$20:$Y$20,1,(Assumptions!$C$4-1)*6+2)+INDEX(Engine!$C$21:$Y$21,1,(Assumptions!$C$4-1)*6+2)+Assumptions!$G$42),0) -> 0 | D26: =IF(D$25=0,-Assumptions!$C$23*$B$19*(INDEX(Engine!$C$20:$Y$20,1,(Assumptions!$C$4-1)*6+2)+INDEX(Engine!$C$21:$Y$21,1,(Assumptions!$C$4-1)*6+2)+Assumptions!$G$42),0) -> 0 | E26: =IF(E$25=0,-Assumptions!$C$23*$B$19*(INDEX(Engine!$C$20:$Y$20,1,(Assumptions!$C$4-1)*6+2)+INDEX(Engine!$C$21:$Y$21,1,(Assumptions!$C$4-1)*6+2)+Assumptions!$G$42),0) -> 0 | F26: =IF(F$25=0,-Assumptions!$C$23*$B$19*(INDEX(Engine!$C$20:$Y$20,1,(Assumptions!$C$4-1)*6+2)+INDEX(Engine!$C$21:$Y$21,1,(Assumptions!$C$4-1)*6+2)+Assumptions!$G$42),0) -> 0 | G26: =IF(G$25=0,-Assumptions!$C$23*$B$19*(INDEX(Engine!$C$20:$Y$20,1,(Assumptions!$C$4-1)*6+2)+INDEX(Engine!$C$21:$Y$21,1,(Assumptions!$C$4-1)*6+2)+Assumptions!$G$42),0) -> 0 | H26: =IF(H$25=0,-Assumptions!$C$23*$B$19*(INDEX(Engine!$C$20:$Y$20,1,(Assumptions!$C$4-1)*6+2)+INDEX(Engine!$C$21:$Y$21,1,(Assumptions!$C$4-1)*6+2)+Assumptions!$G$42),0) -> 0 | I26: =IF(I$25=0,-Assumptions!$C$23*$B$19*(INDEX(Engine!$C$20:$Y$20,1,(Assumptions!$C$4-1)*6+2)+INDEX(Engine!$C$21:$Y$21,1,(Assumptions!$C$4-1)*6+2)+Assumptions!$G$42),0) -> 0 | ... Z26: =IF(Z$25=0,-Assumptions!$C$23*$B$19*(INDEX(Engine!$C$20:$Y$20,1,(Assumptions!$C$4-1)*6+2)+INDEX(Engine!$C$21:$Y$21,1,(Assumptions!$C$4-1)*6+2)+Assumptions!$G$42),0) -> 0
A27: Saldo a fábrica antes de embarque | B27: =IF(B$25=$B$22-1,-(1-Assumptions!$C$23)*$B$19*(INDEX(Engine!$C$20:$Y$20,1,(Assumptions!$C$4-1)*6+2)+INDEX(Engine!$C$21:$Y$21,1,(Assumptions!$C$4-1)*6+2)+Assumptions!$G$42),0) -> 0 | C27: =IF(C$25=$B$22-1,-(1-Assumptions!$C$23)*$B$19*(INDEX(Engine!$C$20:$Y$20,1,(Assumptions!$C$4-1)*6+2)+INDEX(Engine!$C$21:$Y$21,1,(Assumptions!$C$4-1)*6+2)+Assumptions!$G$42),0) -> 0 | D27: =IF(D$25=$B$22-1,-(1-Assumptions!$C$23)*$B$19*(INDEX(Engine!$C$20:$Y$20,1,(Assumptions!$C$4-1)*6+2)+INDEX(Engine!$C$21:$Y$21,1,(Assumptions!$C$4-1)*6+2)+Assumptions!$G$42),0) -> 0 | E27: =IF(E$25=$B$22-1,-(1-Assumptions!$C$23)*$B$19*(INDEX(Engine!$C$20:$Y$20,1,(Assumptions!$C$4-1)*6+2)+INDEX(Engine!$C$21:$Y$21,1,(Assumptions!$C$4-1)*6+2)+Assumptions!$G$42),0) -> 0 | F27: =IF(F$25=$B$22-1,-(1-Assumptions!$C$23)*$B$19*(INDEX(Engine!$C$20:$Y$20,1,(Assumptions!$C$4-1)*6+2)+INDEX(Engine!$C$21:$Y$21,1,(Assumptions!$C$4-1)*6+2)+Assumptions!$G$42),0) -> -10676.087 | G27: =IF(G$25=$B$22-1,-(1-Assumptions!$C$23)*$B$19*(INDEX(Engine!$C$20:$Y$20,1,(Assumptions!$C$4-1)*6+2)+INDEX(Engine!$C$21:$Y$21,1,(Assumptions!$C$4-1)*6+2)+Assumptions!$G$42),0) -> 0 | H27: =IF(H$25=$B$22-1,-(1-Assumptions!$C$23)*$B$19*(INDEX(Engine!$C$20:$Y$20,1,(Assumptions!$C$4-1)*6+2)+INDEX(Engine!$C$21:$Y$21,1,(Assumptions!$C$4-1)*6+2)+Assumptions!$G$42),0) -> 0 | I27: =IF(I$25=$B$22-1,-(1-Assumptions!$C$23)*$B$19*(INDEX(Engine!$C$20:$Y$20,1,(Assumptions!$C$4-1)*6+2)+INDEX(Engine!$C$21:$Y$21,1,(Assumptions!$C$4-1)*6+2)+Assumptions!$G$42),0) -> 0 | ... Z27: =IF(Z$25=$B$22-1,-(1-Assumptions!$C$23)*$B$19*(INDEX(Engine!$C$20:$Y$20,1,(Assumptions!$C$4-1)*6+2)+INDEX(Engine!$C$21:$Y$21,1,(Assumptions!$C$4-1)*6+2)+Assumptions!$G$42),0) -> 0
A28: Flete y seguro | B28: =IF(B$25=$B$22-1,-$B$19*(INDEX(Engine!$C$22:$Y$22,1,(Assumptions!$C$4-1)*6+2)-(INDEX(Engine!$C$20:$Y$20,1,(Assumptions!$C$4-1)*6+2)+INDEX(Engine!$C$21:$Y$21,1,(Assumptions!$C$4-1)*6+2)+Assumptions!$G$42)),0) -> 0 | C28: =IF(C$25=$B$22-1,-$B$19*(INDEX(Engine!$C$22:$Y$22,1,(Assumptions!$C$4-1)*6+2)-(INDEX(Engine!$C$20:$Y$20,1,(Assumptions!$C$4-1)*6+2)+INDEX(Engine!$C$21:$Y$21,1,(Assumptions!$C$4-1)*6+2)+Assumptions!$G$42)),0) -> 0 | D28: =IF(D$25=$B$22-1,-$B$19*(INDEX(Engine!$C$22:$Y$22,1,(Assumptions!$C$4-1)*6+2)-(INDEX(Engine!$C$20:$Y$20,1,(Assumptions!$C$4-1)*6+2)+INDEX(Engine!$C$21:$Y$21,1,(Assumptions!$C$4-1)*6+2)+Assumptions!$G$42)),0) -> 0 | E28: =IF(E$25=$B$22-1,-$B$19*(INDEX(Engine!$C$22:$Y$22,1,(Assumptions!$C$4-1)*6+2)-(INDEX(Engine!$C$20:$Y$20,1,(Assumptions!$C$4-1)*6+2)+INDEX(Engine!$C$21:$Y$21,1,(Assumptions!$C$4-1)*6+2)+Assumptions!$G$42)),0) -> 0 | F28: =IF(F$25=$B$22-1,-$B$19*(INDEX(Engine!$C$22:$Y$22,1,(Assumptions!$C$4-1)*6+2)-(INDEX(Engine!$C$20:$Y$20,1,(Assumptions!$C$4-1)*6+2)+INDEX(Engine!$C$21:$Y$21,1,(Assumptions!$C$4-1)*6+2)+Assumptions!$G$42)),0) -> -1765.0109 | G28: =IF(G$25=$B$22-1,-$B$19*(INDEX(Engine!$C$22:$Y$22,1,(Assumptions!$C$4-1)*6+2)-(INDEX(Engine!$C$20:$Y$20,1,(Assumptions!$C$4-1)*6+2)+INDEX(Engine!$C$21:$Y$21,1,(Assumptions!$C$4-1)*6+2)+Assumptions!$G$42)),0) -> 0 | H28: =IF(H$25=$B$22-1,-$B$19*(INDEX(Engine!$C$22:$Y$22,1,(Assumptions!$C$4-1)*6+2)-(INDEX(Engine!$C$20:$Y$20,1,(Assumptions!$C$4-1)*6+2)+INDEX(Engine!$C$21:$Y$21,1,(Assumptions!$C$4-1)*6+2)+Assumptions!$G$42)),0) -> 0 | I28: =IF(I$25=$B$22-1,-$B$19*(INDEX(Engine!$C$22:$Y$22,1,(Assumptions!$C$4-1)*6+2)-(INDEX(Engine!$C$20:$Y$20,1,(Assumptions!$C$4-1)*6+2)+INDEX(Engine!$C$21:$Y$21,1,(Assumptions!$C$4-1)*6+2)+Assumptions!$G$42)),0) -> 0 | ... Z28: =IF(Z$25=$B$22-1,-$B$19*(INDEX(Engine!$C$22:$Y$22,1,(Assumptions!$C$4-1)*6+2)-(INDEX(Engine!$C$20:$Y$20,1,(Assumptions!$C$4-1)*6+2)+INDEX(Engine!$C$21:$Y$21,1,(Assumptions!$C$4-1)*6+2)+Assumptions!$G$42)),0) -> 0
A29: Arancel + despacho en frontera | B29: =IF(B$25=$B$22,-($B$19*INDEX(Engine!$C$23:$Y$23,1,(Assumptions!$C$4-1)*6+2)+Assumptions!$C$17+$B$19*(Assumptions!$C$16+Assumptions!$G$44)),0) -> 0 | C29: =IF(C$25=$B$22,-($B$19*INDEX(Engine!$C$23:$Y$23,1,(Assumptions!$C$4-1)*6+2)+Assumptions!$C$17+$B$19*(Assumptions!$C$16+Assumptions!$G$44)),0) -> 0 | D29: =IF(D$25=$B$22,-($B$19*INDEX(Engine!$C$23:$Y$23,1,(Assumptions!$C$4-1)*6+2)+Assumptions!$C$17+$B$19*(Assumptions!$C$16+Assumptions!$G$44)),0) -> 0 | E29: =IF(E$25=$B$22,-($B$19*INDEX(Engine!$C$23:$Y$23,1,(Assumptions!$C$4-1)*6+2)+Assumptions!$C$17+$B$19*(Assumptions!$C$16+Assumptions!$G$44)),0) -> 0 | F29: =IF(F$25=$B$22,-($B$19*INDEX(Engine!$C$23:$Y$23,1,(Assumptions!$C$4-1)*6+2)+Assumptions!$C$17+$B$19*(Assumptions!$C$16+Assumptions!$G$44)),0) -> 0 | G29: =IF(G$25=$B$22,-($B$19*INDEX(Engine!$C$23:$Y$23,1,(Assumptions!$C$4-1)*6+2)+Assumptions!$C$17+$B$19*(Assumptions!$C$16+Assumptions!$G$44)),0) -> -7600.468 | H29: =IF(H$25=$B$22,-($B$19*INDEX(Engine!$C$23:$Y$23,1,(Assumptions!$C$4-1)*6+2)+Assumptions!$C$17+$B$19*(Assumptions!$C$16+Assumptions!$G$44)),0) -> 0 | I29: =IF(I$25=$B$22,-($B$19*INDEX(Engine!$C$23:$Y$23,1,(Assumptions!$C$4-1)*6+2)+Assumptions!$C$17+$B$19*(Assumptions!$C$16+Assumptions!$G$44)),0) -> 0 | ... Z29: =IF(Z$25=$B$22,-($B$19*INDEX(Engine!$C$23:$Y$23,1,(Assumptions!$C$4-1)*6+2)+Assumptions!$C$17+$B$19*(Assumptions!$C$16+Assumptions!$G$44)),0) -> 0
A30: IEE (en frontera si se paga al importar; si no, al vender) | B30: =IF(Assumptions!$C$26=1,IF(B$25=$B$22,-$B$19*INDEX(Engine!$C$25:$Y$25,1,(Assumptions!$C$4-1)*6+2),0),IF(AND(B$25>$B$22,B$25<=$B$22+$B$20),-$B$19/$B$20*INDEX(Engine!$C$25:$Y$25,1,(Assumptions!$C$4-1)*6+2),0)) -> 0 | C30: =IF(Assumptions!$C$26=1,IF(C$25=$B$22,-$B$19*INDEX(Engine!$C$25:$Y$25,1,(Assumptions!$C$4-1)*6+2),0),IF(AND(C$25>$B$22,C$25<=$B$22+$B$20),-$B$19/$B$20*INDEX(Engine!$C$25:$Y$25,1,(Assumptions!$C$4-1)*6+2),0)) -> 0 | D30: =IF(Assumptions!$C$26=1,IF(D$25=$B$22,-$B$19*INDEX(Engine!$C$25:$Y$25,1,(Assumptions!$C$4-1)*6+2),0),IF(AND(D$25>$B$22,D$25<=$B$22+$B$20),-$B$19/$B$20*INDEX(Engine!$C$25:$Y$25,1,(Assumptions!$C$4-1)*6+2),0)) -> 0 | E30: =IF(Assumptions!$C$26=1,IF(E$25=$B$22,-$B$19*INDEX(Engine!$C$25:$Y$25,1,(Assumptions!$C$4-1)*6+2),0),IF(AND(E$25>$B$22,E$25<=$B$22+$B$20),-$B$19/$B$20*INDEX(Engine!$C$25:$Y$25,1,(Assumptions!$C$4-1)*6+2),0)) -> 0 | F30: =IF(Assumptions!$C$26=1,IF(F$25=$B$22,-$B$19*INDEX(Engine!$C$25:$Y$25,1,(Assumptions!$C$4-1)*6+2),0),IF(AND(F$25>$B$22,F$25<=$B$22+$B$20),-$B$19/$B$20*INDEX(Engine!$C$25:$Y$25,1,(Assumptions!$C$4-1)*6+2),0)) -> 0 | G30: =IF(Assumptions!$C$26=1,IF(G$25=$B$22,-$B$19*INDEX(Engine!$C$25:$Y$25,1,(Assumptions!$C$4-1)*6+2),0),IF(AND(G$25>$B$22,G$25<=$B$22+$B$20),-$B$19/$B$20*INDEX(Engine!$C$25:$Y$25,1,(Assumptions!$C$4-1)*6+2),0)) -> -11376 | H30: =IF(Assumptions!$C$26=1,IF(H$25=$B$22,-$B$19*INDEX(Engine!$C$25:$Y$25,1,(Assumptions!$C$4-1)*6+2),0),IF(AND(H$25>$B$22,H$25<=$B$22+$B$20),-$B$19/$B$20*INDEX(Engine!$C$25:$Y$25,1,(Assumptions!$C$4-1)*6+2),0)) -> 0 | I30: =IF(Assumptions!$C$26=1,IF(I$25=$B$22,-$B$19*INDEX(Engine!$C$25:$Y$25,1,(Assumptions!$C$4-1)*6+2),0),IF(AND(I$25>$B$22,I$25<=$B$22+$B$20),-$B$19/$B$20*INDEX(Engine!$C$25:$Y$25,1,(Assumptions!$C$4-1)*6+2),0)) -> 0 | ... Z30: =IF(Assumptions!$C$26=1,IF(Z$25=$B$22,-$B$19*INDEX(Engine!$C$25:$Y$25,1,(Assumptions!$C$4-1)*6+2),0),IF(AND(Z$25>$B$22,Z$25<=$B$22+$B$20),-$B$19/$B$20*INDEX(Engine!$C$25:$Y$25,1,(Assumptions!$C$4-1)*6+2),0)) -> 0
A31: IVA de importación pagado | B31: =IF(B$25=$B$22,-$B$19*(INDEX(Engine!$C$22:$Y$22,1,(Assumptions!$C$4-1)*6+2)+INDEX(Engine!$C$23:$Y$23,1,(Assumptions!$C$4-1)*6+2)+Assumptions!$C$26*INDEX(Engine!$C$25:$Y$25,1,(Assumptions!$C$4-1)*6+2))*Assumptions!$C$10,0) -> 0 | C31: =IF(C$25=$B$22,-$B$19*(INDEX(Engine!$C$22:$Y$22,1,(Assumptions!$C$4-1)*6+2)+INDEX(Engine!$C$23:$Y$23,1,(Assumptions!$C$4-1)*6+2)+Assumptions!$C$26*INDEX(Engine!$C$25:$Y$25,1,(Assumptions!$C$4-1)*6+2))*Assumptions!$C$10,0) -> 0 | D31: =IF(D$25=$B$22,-$B$19*(INDEX(Engine!$C$22:$Y$22,1,(Assumptions!$C$4-1)*6+2)+INDEX(Engine!$C$23:$Y$23,1,(Assumptions!$C$4-1)*6+2)+Assumptions!$C$26*INDEX(Engine!$C$25:$Y$25,1,(Assumptions!$C$4-1)*6+2))*Assumptions!$C$10,0) -> 0 | E31: =IF(E$25=$B$22,-$B$19*(INDEX(Engine!$C$22:$Y$22,1,(Assumptions!$C$4-1)*6+2)+INDEX(Engine!$C$23:$Y$23,1,(Assumptions!$C$4-1)*6+2)+Assumptions!$C$26*INDEX(Engine!$C$25:$Y$25,1,(Assumptions!$C$4-1)*6+2))*Assumptions!$C$10,0) -> 0 | F31: =IF(F$25=$B$22,-$B$19*(INDEX(Engine!$C$22:$Y$22,1,(Assumptions!$C$4-1)*6+2)+INDEX(Engine!$C$23:$Y$23,1,(Assumptions!$C$4-1)*6+2)+Assumptions!$C$26*INDEX(Engine!$C$25:$Y$25,1,(Assumptions!$C$4-1)*6+2))*Assumptions!$C$10,0) -> 0 | G31: =IF(G$25=$B$22,-$B$19*(INDEX(Engine!$C$22:$Y$22,1,(Assumptions!$C$4-1)*6+2)+INDEX(Engine!$C$23:$Y$23,1,(Assumptions!$C$4-1)*6+2)+Assumptions!$C$26*INDEX(Engine!$C$25:$Y$25,1,(Assumptions!$C$4-1)*6+2))*Assumptions!$C$10,0) -> -8505.7671 | H31: =IF(H$25=$B$22,-$B$19*(INDEX(Engine!$C$22:$Y$22,1,(Assumptions!$C$4-1)*6+2)+INDEX(Engine!$C$23:$Y$23,1,(Assumptions!$C$4-1)*6+2)+Assumptions!$C$26*INDEX(Engine!$C$25:$Y$25,1,(Assumptions!$C$4-1)*6+2))*Assumptions!$C$10,0) -> 0 | I31: =IF(I$25=$B$22,-$B$19*(INDEX(Engine!$C$22:$Y$22,1,(Assumptions!$C$4-1)*6+2)+INDEX(Engine!$C$23:$Y$23,1,(Assumptions!$C$4-1)*6+2)+Assumptions!$C$26*INDEX(Engine!$C$25:$Y$25,1,(Assumptions!$C$4-1)*6+2))*Assumptions!$C$10,0) -> 0 | ... Z31: =IF(Z$25=$B$22,-$B$19*(INDEX(Engine!$C$22:$Y$22,1,(Assumptions!$C$4-1)*6+2)+INDEX(Engine!$C$23:$Y$23,1,(Assumptions!$C$4-1)*6+2)+Assumptions!$C$26*INDEX(Engine!$C$25:$Y$25,1,(Assumptions!$C$4-1)*6+2))*Assumptions!$C$10,0) -> 0
A32: Devolución/compensación IVA importación (+3 meses) | B32: =IF(B$25=$B$22+3,$B$19*(INDEX(Engine!$C$22:$Y$22,1,(Assumptions!$C$4-1)*6+2)+INDEX(Engine!$C$23:$Y$23,1,(Assumptions!$C$4-1)*6+2)+Assumptions!$C$26*INDEX(Engine!$C$25:$Y$25,1,(Assumptions!$C$4-1)*6+2))*Assumptions!$C$10,0) -> 0 | C32: =IF(C$25=$B$22+3,$B$19*(INDEX(Engine!$C$22:$Y$22,1,(Assumptions!$C$4-1)*6+2)+INDEX(Engine!$C$23:$Y$23,1,(Assumptions!$C$4-1)*6+2)+Assumptions!$C$26*INDEX(Engine!$C$25:$Y$25,1,(Assumptions!$C$4-1)*6+2))*Assumptions!$C$10,0) -> 0 | D32: =IF(D$25=$B$22+3,$B$19*(INDEX(Engine!$C$22:$Y$22,1,(Assumptions!$C$4-1)*6+2)+INDEX(Engine!$C$23:$Y$23,1,(Assumptions!$C$4-1)*6+2)+Assumptions!$C$26*INDEX(Engine!$C$25:$Y$25,1,(Assumptions!$C$4-1)*6+2))*Assumptions!$C$10,0) -> 0 | E32: =IF(E$25=$B$22+3,$B$19*(INDEX(Engine!$C$22:$Y$22,1,(Assumptions!$C$4-1)*6+2)+INDEX(Engine!$C$23:$Y$23,1,(Assumptions!$C$4-1)*6+2)+Assumptions!$C$26*INDEX(Engine!$C$25:$Y$25,1,(Assumptions!$C$4-1)*6+2))*Assumptions!$C$10,0) -> 0 | F32: =IF(F$25=$B$22+3,$B$19*(INDEX(Engine!$C$22:$Y$22,1,(Assumptions!$C$4-1)*6+2)+INDEX(Engine!$C$23:$Y$23,1,(Assumptions!$C$4-1)*6+2)+Assumptions!$C$26*INDEX(Engine!$C$25:$Y$25,1,(Assumptions!$C$4-1)*6+2))*Assumptions!$C$10,0) -> 0 | G32: =IF(G$25=$B$22+3,$B$19*(INDEX(Engine!$C$22:$Y$22,1,(Assumptions!$C$4-1)*6+2)+INDEX(Engine!$C$23:$Y$23,1,(Assumptions!$C$4-1)*6+2)+Assumptions!$C$26*INDEX(Engine!$C$25:$Y$25,1,(Assumptions!$C$4-1)*6+2))*Assumptions!$C$10,0) -> 0 | H32: =IF(H$25=$B$22+3,$B$19*(INDEX(Engine!$C$22:$Y$22,1,(Assumptions!$C$4-1)*6+2)+INDEX(Engine!$C$23:$Y$23,1,(Assumptions!$C$4-1)*6+2)+Assumptions!$C$26*INDEX(Engine!$C$25:$Y$25,1,(Assumptions!$C$4-1)*6+2))*Assumptions!$C$10,0) -> 0 | I32: =IF(I$25=$B$22+3,$B$19*(INDEX(Engine!$C$22:$Y$22,1,(Assumptions!$C$4-1)*6+2)+INDEX(Engine!$C$23:$Y$23,1,(Assumptions!$C$4-1)*6+2)+Assumptions!$C$26*INDEX(Engine!$C$25:$Y$25,1,(Assumptions!$C$4-1)*6+2))*Assumptions!$C$10,0) -> 0 | ... Z32: =IF(Z$25=$B$22+3,$B$19*(INDEX(Engine!$C$22:$Y$22,1,(Assumptions!$C$4-1)*6+2)+INDEX(Engine!$C$23:$Y$23,1,(Assumptions!$C$4-1)*6+2)+Assumptions!$C$26*INDEX(Engine!$C$25:$Y$25,1,(Assumptions!$C$4-1)*6+2))*Assumptions!$C$10,0) -> 0
A33: Cobros del distribuidor (netos de IVA repercutido) | B33: =IF(AND(B$25>$B$22+1+$B$23,B$25<=$B$22+1+$B$23+$B$20-1),$B$19/$B$20/INDEX(Engine!$C$10:$Y$10,1,(Assumptions!$C$4-1)*6+2)*(INDEX(Engine!$C$33:$Y$33,1,(Assumptions!$C$4-1)*6+3)/MAX(1,INDEX(Engine!$C$14:$Y$14,1,(Assumptions!$C$4-1)*6+3))),0) -> 0 | C33: =IF(AND(C$25>$B$22+1+$B$23,C$25<=$B$22+1+$B$23+$B$20-1),$B$19/$B$20/INDEX(Engine!$C$10:$Y$10,1,(Assumptions!$C$4-1)*6+2)*(INDEX(Engine!$C$33:$Y$33,1,(Assumptions!$C$4-1)*6+3)/MAX(1,INDEX(Engine!$C$14:$Y$14,1,(Assumptions!$C$4-1)*6+3))),0) -> 0 | D33: =IF(AND(D$25>$B$22+1+$B$23,D$25<=$B$22+1+$B$23+$B$20-1),$B$19/$B$20/INDEX(Engine!$C$10:$Y$10,1,(Assumptions!$C$4-1)*6+2)*(INDEX(Engine!$C$33:$Y$33,1,(Assumptions!$C$4-1)*6+3)/MAX(1,INDEX(Engine!$C$14:$Y$14,1,(Assumptions!$C$4-1)*6+3))),0) -> 0 | E33: =IF(AND(E$25>$B$22+1+$B$23,E$25<=$B$22+1+$B$23+$B$20-1),$B$19/$B$20/INDEX(Engine!$C$10:$Y$10,1,(Assumptions!$C$4-1)*6+2)*(INDEX(Engine!$C$33:$Y$33,1,(Assumptions!$C$4-1)*6+3)/MAX(1,INDEX(Engine!$C$14:$Y$14,1,(Assumptions!$C$4-1)*6+3))),0) -> 0 | F33: =IF(AND(F$25>$B$22+1+$B$23,F$25<=$B$22+1+$B$23+$B$20-1),$B$19/$B$20/INDEX(Engine!$C$10:$Y$10,1,(Assumptions!$C$4-1)*6+2)*(INDEX(Engine!$C$33:$Y$33,1,(Assumptions!$C$4-1)*6+3)/MAX(1,INDEX(Engine!$C$14:$Y$14,1,(Assumptions!$C$4-1)*6+3))),0) -> 0 | G33: =IF(AND(G$25>$B$22+1+$B$23,G$25<=$B$22+1+$B$23+$B$20-1),$B$19/$B$20/INDEX(Engine!$C$10:$Y$10,1,(Assumptions!$C$4-1)*6+2)*(INDEX(Engine!$C$33:$Y$33,1,(Assumptions!$C$4-1)*6+3)/MAX(1,INDEX(Engine!$C$14:$Y$14,1,(Assumptions!$C$4-1)*6+3))),0) -> 0 | H33: =IF(AND(H$25>$B$22+1+$B$23,H$25<=$B$22+1+$B$23+$B$20-1),$B$19/$B$20/INDEX(Engine!$C$10:$Y$10,1,(Assumptions!$C$4-1)*6+2)*(INDEX(Engine!$C$33:$Y$33,1,(Assumptions!$C$4-1)*6+3)/MAX(1,INDEX(Engine!$C$14:$Y$14,1,(Assumptions!$C$4-1)*6+3))),0) -> 0 | I33: =IF(AND(I$25>$B$22+1+$B$23,I$25<=$B$22+1+$B$23+$B$20-1),$B$19/$B$20/INDEX(Engine!$C$10:$Y$10,1,(Assumptions!$C$4-1)*6+2)*(INDEX(Engine!$C$33:$Y$33,1,(Assumptions!$C$4-1)*6+3)/MAX(1,INDEX(Engine!$C$14:$Y$14,1,(Assumptions!$C$4-1)*6+3))),0) -> 0 | ... Z33: =IF(AND(Z$25>$B$22+1+$B$23,Z$25<=$B$22+1+$B$23+$B$20-1),$B$19/$B$20/INDEX(Engine!$C$10:$Y$10,1,(Assumptions!$C$4-1)*6+2)*(INDEX(Engine!$C$33:$Y$33,1,(Assumptions!$C$4-1)*6+3)/MAX(1,INDEX(Engine!$C$14:$Y$14,1,(Assumptions!$C$4-1)*6+3))),0) -> 0
A34: Gastos fijos mensuales | B34: =IF($B$21=1,-INDEX(Engine!$C$40:$Y$40,1,(Assumptions!$C$4-1)*6+2)/12,0) -> -1897.5 | C34: =IF($B$21=1,-INDEX(Engine!$C$40:$Y$40,1,(Assumptions!$C$4-1)*6+2)/12,0) -> -1897.5 | D34: =IF($B$21=1,-INDEX(Engine!$C$40:$Y$40,1,(Assumptions!$C$4-1)*6+2)/12,0) -> -1897.5 | E34: =IF($B$21=1,-INDEX(Engine!$C$40:$Y$40,1,(Assumptions!$C$4-1)*6+2)/12,0) -> -1897.5 | F34: =IF($B$21=1,-INDEX(Engine!$C$40:$Y$40,1,(Assumptions!$C$4-1)*6+2)/12,0) -> -1897.5 | G34: =IF($B$21=1,-INDEX(Engine!$C$40:$Y$40,1,(Assumptions!$C$4-1)*6+2)/12,0) -> -1897.5 | H34: =IF($B$21=1,-INDEX(Engine!$C$40:$Y$40,1,(Assumptions!$C$4-1)*6+2)/12,0) -> -1897.5 | I34: =IF($B$21=1,-INDEX(Engine!$C$40:$Y$40,1,(Assumptions!$C$4-1)*6+2)/12,0) -> -1897.5 | ... Z34: =IF($B$21=1,-INDEX(Engine!$C$40:$Y$40,1,(Assumptions!$C$4-1)*6+2)/12,0) -> -1897.5
A35: Flujo neto del mes | B35: =SUM(B26:B34) -> -12573.587 | C35: =SUM(C26:C34) -> -1897.5 | D35: =SUM(D26:D34) -> -1897.5 | E35: =SUM(E26:E34) -> -1897.5 | F35: =SUM(F26:F34) -> -14338.598 | G35: =SUM(G26:G34) -> -29379.735 | H35: =SUM(H26:H34) -> -1897.5 | I35: =SUM(I26:I34) -> -1897.5 | ... Z35: =SUM(Z26:Z34) -> -1897.5
A36: Caja acumulada del pedido | B36: =B35 -> -12573.587 | C36: =B36+C35 -> -14471.087 | D36: =C36+D35 -> -16368.587 | E36: =D36+E35 -> -18266.087 | F36: =E36+F35 -> -32604.685 | G36: =F36+G35 -> -61984.42 | H36: =G36+H35 -> -63881.92 | I36: =H36+I35 -> -65779.42 | J36: =I36+J35 -> -59171.153 | ... Z36: =Y36+Z35 -> -46827.537
A38: Necesidad máxima de caja del ciclo (−mínimo acumulado) | B38: =-MIN(0,MIN(B36:Z36)) -> 65779.42
A39: Mes en que se alcanza | B39: =MATCH(MIN(B36:Z36),B36:Z36,0)-1 -> 7
A40: Meses entre el primer pago a Cuba y el primer cobro | B40: =$B$22+2+$B$23 -> 9
A41: Nota: los cobros usan el ingreso neto unitario de 2029 del escenario; el ciclo ilustra el desajuste anticipo→cobro, no sustituye al modelo anual.

Sheet Profit & Loss
A1: Cuenta de resultados 2027–2031 (escenario seleccionado)
A2: € sin IVA. Los importes del consumidor y del canal se muestran para separar ingresos de marca, distribuidor y detallista.
A3: ="Escenario: "&Assumptions!$D$4 -> Escenario: Base
A5: Concepto | B5: 2027 | C5: 2028 | D5: 2029 | E5: 2030 | F5: 2031
A6: Unidades vendidas | B6: =INDEX(Engine!$C$14:$Y$14,1,(Assumptions!$C$4-1)*6+1) -> 0 | C6: =INDEX(Engine!$C$14:$Y$14,1,(Assumptions!$C$4-1)*6+2) -> 2000 | D6: =INDEX(Engine!$C$14:$Y$14,1,(Assumptions!$C$4-1)*6+3) -> 3500 | E6: =INDEX(Engine!$C$14:$Y$14,1,(Assumptions!$C$4-1)*6+4) -> 5000 | F6: =INDEX(Engine!$C$14:$Y$14,1,(Assumptions!$C$4-1)*6+5) -> 6500
A7: Ventas a PVP con IVA (gasto del consumidor, informativo) | B7: =INDEX(Engine!$C$29:$Y$29,1,(Assumptions!$C$4-1)*6+1) -> 0 | C7: =INDEX(Engine!$C$29:$Y$29,1,(Assumptions!$C$4-1)*6+2) -> 48000 | D7: =INDEX(Engine!$C$29:$Y$29,1,(Assumptions!$C$4-1)*6+3) -> 84000 | E7: =INDEX(Engine!$C$29:$Y$29,1,(Assumptions!$C$4-1)*6+4) -> 120000 | F7: =INDEX(Engine!$C$29:$Y$29,1,(Assumptions!$C$4-1)*6+5) -> 156000
A8: Ventas a PVP sin IVA | B8: =INDEX(Engine!$C$30:$Y$30,1,(Assumptions!$C$4-1)*6+1) -> 0 | C8: =INDEX(Engine!$C$30:$Y$30,1,(Assumptions!$C$4-1)*6+2) -> 39669.421 | D8: =INDEX(Engine!$C$30:$Y$30,1,(Assumptions!$C$4-1)*6+3) -> 69421.488 | E8: =INDEX(Engine!$C$30:$Y$30,1,(Assumptions!$C$4-1)*6+4) -> 99173.554 | F8: =INDEX(Engine!$C$30:$Y$30,1,(Assumptions!$C$4-1)*6+5) -> 128925.62
A9: (-) Margen del expendedor (ingreso del detallista) | B9: =INDEX(Engine!$C$31:$Y$31,1,(Assumptions!$C$4-1)*6+1) -> 0 | C9: =INDEX(Engine!$C$31:$Y$31,1,(Assumptions!$C$4-1)*6+2) -> 4320 | D9: =INDEX(Engine!$C$31:$Y$31,1,(Assumptions!$C$4-1)*6+3) -> 7560 | E9: =INDEX(Engine!$C$31:$Y$31,1,(Assumptions!$C$4-1)*6+4) -> 10800 | F9: =INDEX(Engine!$C$31:$Y$31,1,(Assumptions!$C$4-1)*6+5) -> 14040
A10: (-) Tarifa del distribuidor (ingreso del mayorista) | B10: =INDEX(Engine!$C$32:$Y$32,1,(Assumptions!$C$4-1)*6+1) -> 0 | C10: =INDEX(Engine!$C$32:$Y$32,1,(Assumptions!$C$4-1)*6+2) -> 2400 | D10: =INDEX(Engine!$C$32:$Y$32,1,(Assumptions!$C$4-1)*6+3) -> 4200 | E10: =INDEX(Engine!$C$32:$Y$32,1,(Assumptions!$C$4-1)*6+4) -> 6000 | F10: =INDEX(Engine!$C$32:$Y$32,1,(Assumptions!$C$4-1)*6+5) -> 7800
A11: INGRESOS DE LA MARCA (antes de IEE) | B11: =INDEX(Engine!$C$33:$Y$33,1,(Assumptions!$C$4-1)*6+1) -> 0 | C11: =INDEX(Engine!$C$33:$Y$33,1,(Assumptions!$C$4-1)*6+2) -> 32949.421 | D11: =INDEX(Engine!$C$33:$Y$33,1,(Assumptions!$C$4-1)*6+3) -> 57661.488 | E11: =INDEX(Engine!$C$33:$Y$33,1,(Assumptions!$C$4-1)*6+4) -> 82373.554 | F11: =INDEX(Engine!$C$33:$Y$33,1,(Assumptions!$C$4-1)*6+5) -> 107085.62
A12: (-) Impuesto especial | B12: =INDEX(Engine!$C$34:$Y$34,1,(Assumptions!$C$4-1)*6+1) -> 0 | C12: =INDEX(Engine!$C$34:$Y$34,1,(Assumptions!$C$4-1)*6+2) -> 8046.0767 | D12: =INDEX(Engine!$C$34:$Y$34,1,(Assumptions!$C$4-1)*6+3) -> 14080.634 | E12: =INDEX(Engine!$C$34:$Y$34,1,(Assumptions!$C$4-1)*6+4) -> 20115.192 | F12: =INDEX(Engine!$C$34:$Y$34,1,(Assumptions!$C$4-1)*6+5) -> 26149.749
A13: Ingresos netos de impuestos | B13: =INDEX(Engine!$C$35:$Y$35,1,(Assumptions!$C$4-1)*6+1) -> 0 | C13: =INDEX(Engine!$C$35:$Y$35,1,(Assumptions!$C$4-1)*6+2) -> 24903.345 | D13: =INDEX(Engine!$C$35:$Y$35,1,(Assumptions!$C$4-1)*6+3) -> 43580.853 | E13: =INDEX(Engine!$C$35:$Y$35,1,(Assumptions!$C$4-1)*6+4) -> 62258.362 | F13: =INDEX(Engine!$C$35:$Y$35,1,(Assumptions!$C$4-1)*6+5) -> 80935.871
A14: (-) Coste de ventas | B14: =INDEX(Engine!$C$36:$Y$36,1,(Assumptions!$C$4-1)*6+1) -> 0 | C14: =INDEX(Engine!$C$36:$Y$36,1,(Assumptions!$C$4-1)*6+2) -> 21407.864 | D14: =INDEX(Engine!$C$36:$Y$36,1,(Assumptions!$C$4-1)*6+3) -> 37463.761 | E14: =INDEX(Engine!$C$36:$Y$36,1,(Assumptions!$C$4-1)*6+4) -> 53519.659 | F14: =INDEX(Engine!$C$36:$Y$36,1,(Assumptions!$C$4-1)*6+5) -> 69575.557
A15: (-) Despachos aduaneros | B15: =INDEX(Engine!$C$37:$Y$37,1,(Assumptions!$C$4-1)*6+1) -> 900 | C15: =INDEX(Engine!$C$37:$Y$37,1,(Assumptions!$C$4-1)*6+2) -> 900 | D15: =INDEX(Engine!$C$37:$Y$37,1,(Assumptions!$C$4-1)*6+3) -> 900 | E15: =INDEX(Engine!$C$37:$Y$37,1,(Assumptions!$C$4-1)*6+4) -> 900 | F15: =INDEX(Engine!$C$37:$Y$37,1,(Assumptions!$C$4-1)*6+5) -> 900
A16: (-) Royalty de nombre a Arnaldo | B16: =INDEX(Engine!$C$38:$Y$38,1,(Assumptions!$C$4-1)*6+1) -> 0 | C16: =INDEX(Engine!$C$38:$Y$38,1,(Assumptions!$C$4-1)*6+2) -> 0 | D16: =INDEX(Engine!$C$38:$Y$38,1,(Assumptions!$C$4-1)*6+3) -> 0 | E16: =INDEX(Engine!$C$38:$Y$38,1,(Assumptions!$C$4-1)*6+4) -> 0 | F16: =INDEX(Engine!$C$38:$Y$38,1,(Assumptions!$C$4-1)*6+5) -> 0
A17: MARGEN BRUTO | B17: =INDEX(Engine!$C$39:$Y$39,1,(Assumptions!$C$4-1)*6+1) -> -900 | C17: =INDEX(Engine!$C$39:$Y$39,1,(Assumptions!$C$4-1)*6+2) -> 2595.4812 | D17: =INDEX(Engine!$C$39:$Y$39,1,(Assumptions!$C$4-1)*6+3) -> 5217.0921 | E17: =INDEX(Engine!$C$39:$Y$39,1,(Assumptions!$C$4-1)*6+4) -> 7838.703 | F17: =INDEX(Engine!$C$39:$Y$39,1,(Assumptions!$C$4-1)*6+5) -> 10460.314
A18: (-) Gastos fijos | B18: =INDEX(Engine!$C$40:$Y$40,1,(Assumptions!$C$4-1)*6+1) -> 26290 | C18: =INDEX(Engine!$C$40:$Y$40,1,(Assumptions!$C$4-1)*6+2) -> 22770 | D18: =INDEX(Engine!$C$40:$Y$40,1,(Assumptions!$C$4-1)*6+3) -> 22330 | E18: =INDEX(Engine!$C$40:$Y$40,1,(Assumptions!$C$4-1)*6+4) -> 24090 | F18: =INDEX(Engine!$C$40:$Y$40,1,(Assumptions!$C$4-1)*6+5) -> 24310
A19: EBITDA | B19: =INDEX(Engine!$C$41:$Y$41,1,(Assumptions!$C$4-1)*6+1) -> -27190 | C19: =INDEX(Engine!$C$41:$Y$41,1,(Assumptions!$C$4-1)*6+2) -> -20174.519 | D19: =INDEX(Engine!$C$41:$Y$41,1,(Assumptions!$C$4-1)*6+3) -> -17112.908 | E19: =INDEX(Engine!$C$41:$Y$41,1,(Assumptions!$C$4-1)*6+4) -> -16251.297 | F19: =INDEX(Engine!$C$41:$Y$41,1,(Assumptions!$C$4-1)*6+5) -> -13849.686
A20: (-) Amortización | B20: =INDEX(Engine!$C$44:$Y$44,1,(Assumptions!$C$4-1)*6+1) -> 2600 | C20: =INDEX(Engine!$C$44:$Y$44,1,(Assumptions!$C$4-1)*6+2) -> 2600 | D20: =INDEX(Engine!$C$44:$Y$44,1,(Assumptions!$C$4-1)*6+3) -> 3200 | E20: =INDEX(Engine!$C$44:$Y$44,1,(Assumptions!$C$4-1)*6+4) -> 3200 | F20: =INDEX(Engine!$C$44:$Y$44,1,(Assumptions!$C$4-1)*6+5) -> 3200
A21: EBIT | B21: =INDEX(Engine!$C$47:$Y$47,1,(Assumptions!$C$4-1)*6+1) -> -29790 | C21: =INDEX(Engine!$C$47:$Y$47,1,(Assumptions!$C$4-1)*6+2) -> -22774.519 | D21: =INDEX(Engine!$C$47:$Y$47,1,(Assumptions!$C$4-1)*6+3) -> -20312.908 | E21: =INDEX(Engine!$C$47:$Y$47,1,(Assumptions!$C$4-1)*6+4) -> -19451.297 | F21: =INDEX(Engine!$C$47:$Y$47,1,(Assumptions!$C$4-1)*6+5) -> -17049.686
A22: (-) Gastos financieros | B22: =INDEX(Engine!$C$48:$Y$48,1,(Assumptions!$C$4-1)*6+1) -> 0 | C22: =INDEX(Engine!$C$48:$Y$48,1,(Assumptions!$C$4-1)*6+2) -> 831.42976 | D22: =INDEX(Engine!$C$48:$Y$48,1,(Assumptions!$C$4-1)*6+3) -> 3531.901 | E22: =INDEX(Engine!$C$48:$Y$48,1,(Assumptions!$C$4-1)*6+4) -> 6329.7101 | F22: =INDEX(Engine!$C$48:$Y$48,1,(Assumptions!$C$4-1)*6+5) -> 8962.5491
A23: Resultado antes de impuestos | B23: =INDEX(Engine!$C$49:$Y$49,1,(Assumptions!$C$4-1)*6+1) -> -29790 | C23: =INDEX(Engine!$C$49:$Y$49,1,(Assumptions!$C$4-1)*6+2) -> -23605.949 | D23: =INDEX(Engine!$C$49:$Y$49,1,(Assumptions!$C$4-1)*6+3) -> -23844.809 | E23: =INDEX(Engine!$C$49:$Y$49,1,(Assumptions!$C$4-1)*6+4) -> -25781.007 | F23: =INDEX(Engine!$C$49:$Y$49,1,(Assumptions!$C$4-1)*6+5) -> -26012.235
A24: (-) Impuesto sobre Sociedades | B24: =INDEX(Engine!$C$53:$Y$53,1,(Assumptions!$C$4-1)*6+1) -> 0 | C24: =INDEX(Engine!$C$53:$Y$53,1,(Assumptions!$C$4-1)*6+2) -> 0 | D24: =INDEX(Engine!$C$53:$Y$53,1,(Assumptions!$C$4-1)*6+3) -> 0 | E24: =INDEX(Engine!$C$53:$Y$53,1,(Assumptions!$C$4-1)*6+4) -> 0 | F24: =INDEX(Engine!$C$53:$Y$53,1,(Assumptions!$C$4-1)*6+5) -> 0
A25: RESULTADO NETO | B25: =INDEX(Engine!$C$54:$Y$54,1,(Assumptions!$C$4-1)*6+1) -> -29790 | C25: =INDEX(Engine!$C$54:$Y$54,1,(Assumptions!$C$4-1)*6+2) -> -23605.949 | D25: =INDEX(Engine!$C$54:$Y$54,1,(Assumptions!$C$4-1)*6+3) -> -23844.809 | E25: =INDEX(Engine!$C$54:$Y$54,1,(Assumptions!$C$4-1)*6+4) -> -25781.007 | F25: =INDEX(Engine!$C$54:$Y$54,1,(Assumptions!$C$4-1)*6+5) -> -26012.235
A26: Margen bruto / ingresos netos de impuestos | B26: =IF(B13<>0,B17/B13,0) -> 0 | C26: =IF(C13<>0,C17/C13,0) -> 0.10422219 | D26: =IF(D13<>0,D17/D13,0) -> 0.11971065 | E26: =IF(E13<>0,E17/E13,0) -> 0.12590603 | F26: =IF(F13<>0,F17/F13,0) -> 0.129242
A27: Margen EBITDA / ingresos de la marca | B27: =IF(B11<>0,B19/B11,0) -> 0 | C27: =IF(C11<>0,C19/C11,0) -> -0.6122875 | D27: =IF(D11<>0,D19/D11,0) -> -0.29678228 | E27: =IF(E11<>0,E19/E11,0) -> -0.1972878 | F27: =IF(F11<>0,F19/F11,0) -> -0.12933283

Sheet Cash Flow
A1: Estado de flujos de caja 2027–2031 (escenario seleccionado)
A2: Método indirecto. La financiación ajena se dimensiona automáticamente para mantener la caja mínima (no circular).
A3: ="Escenario: "&Assumptions!$D$4 -> Escenario: Base
A5: Concepto | B5: 2027 | C5: 2028 | D5: 2029 | E5: 2030 | F5: 2031
A6: Resultado neto | B6: =INDEX(Engine!$C$54:$Y$54,1,(Assumptions!$C$4-1)*6+1) -> -29790 | C6: =INDEX(Engine!$C$54:$Y$54,1,(Assumptions!$C$4-1)*6+2) -> -23605.949 | D6: =INDEX(Engine!$C$54:$Y$54,1,(Assumptions!$C$4-1)*6+3) -> -23844.809 | E6: =INDEX(Engine!$C$54:$Y$54,1,(Assumptions!$C$4-1)*6+4) -> -25781.007 | F6: =INDEX(Engine!$C$54:$Y$54,1,(Assumptions!$C$4-1)*6+5) -> -26012.235
A7: (+) Amortización | B7: =INDEX(Engine!$C$44:$Y$44,1,(Assumptions!$C$4-1)*6+1) -> 2600 | C7: =INDEX(Engine!$C$44:$Y$44,1,(Assumptions!$C$4-1)*6+2) -> 2600 | D7: =INDEX(Engine!$C$44:$Y$44,1,(Assumptions!$C$4-1)*6+3) -> 3200 | E7: =INDEX(Engine!$C$44:$Y$44,1,(Assumptions!$C$4-1)*6+4) -> 3200 | F7: =INDEX(Engine!$C$44:$Y$44,1,(Assumptions!$C$4-1)*6+5) -> 3200
A8: Variación del circulante (aumento = consumo de caja; se resta) | B8: =INDEX(Engine!$C$68:$Y$68,1,(Assumptions!$C$4-1)*6+1) -> 16687.568 | C8: =INDEX(Engine!$C$68:$Y$68,1,(Assumptions!$C$4-1)*6+2) -> 17572.212 | D8: =INDEX(Engine!$C$68:$Y$68,1,(Assumptions!$C$4-1)*6+3) -> 16323.893 | E8: =INDEX(Engine!$C$68:$Y$68,1,(Assumptions!$C$4-1)*6+4) -> 15030.979 | F8: =INDEX(Engine!$C$68:$Y$68,1,(Assumptions!$C$4-1)*6+5) -> 2967.4232
A9: FLUJO DE EXPLOTACIÓN | B9: =INDEX(Engine!$C$71:$Y$71,1,(Assumptions!$C$4-1)*6+1) -> -43877.568 | C9: =INDEX(Engine!$C$71:$Y$71,1,(Assumptions!$C$4-1)*6+2) -> -38578.161 | D9: =INDEX(Engine!$C$71:$Y$71,1,(Assumptions!$C$4-1)*6+3) -> -36968.702 | E9: =INDEX(Engine!$C$71:$Y$71,1,(Assumptions!$C$4-1)*6+4) -> -37611.986 | F9: =INDEX(Engine!$C$71:$Y$71,1,(Assumptions!$C$4-1)*6+5) -> -25779.658
A10: FLUJO DE INVERSIÓN | B10: =INDEX(Engine!$C$72:$Y$72,1,(Assumptions!$C$4-1)*6+1) -> -13000 | C10: =INDEX(Engine!$C$72:$Y$72,1,(Assumptions!$C$4-1)*6+2) -> 0 | D10: =INDEX(Engine!$C$72:$Y$72,1,(Assumptions!$C$4-1)*6+3) -> -3000 | E10: =INDEX(Engine!$C$72:$Y$72,1,(Assumptions!$C$4-1)*6+4) -> 0 | F10: =INDEX(Engine!$C$72:$Y$72,1,(Assumptions!$C$4-1)*6+5) -> 0
A11: Aportación de capital | B11: =INDEX(Engine!$C$73:$Y$73,1,(Assumptions!$C$4-1)*6+1) -> 50000 | C11: =INDEX(Engine!$C$73:$Y$73,1,(Assumptions!$C$4-1)*6+2) -> 0 | D11: =INDEX(Engine!$C$73:$Y$73,1,(Assumptions!$C$4-1)*6+3) -> 0 | E11: =INDEX(Engine!$C$73:$Y$73,1,(Assumptions!$C$4-1)*6+4) -> 0 | F11: =INDEX(Engine!$C$73:$Y$73,1,(Assumptions!$C$4-1)*6+5) -> 0
A12: Disposición / (devolución) de financiación ajena | B12: =INDEX(Engine!$C$76:$Y$76,1,(Assumptions!$C$4-1)*6+1) -> 11877.568 | C12: =INDEX(Engine!$C$76:$Y$76,1,(Assumptions!$C$4-1)*6+2) -> 38578.161 | D12: =INDEX(Engine!$C$76:$Y$76,1,(Assumptions!$C$4-1)*6+3) -> 39968.702 | E12: =INDEX(Engine!$C$76:$Y$76,1,(Assumptions!$C$4-1)*6+4) -> 37611.986 | F12: =INDEX(Engine!$C$76:$Y$76,1,(Assumptions!$C$4-1)*6+5) -> 25779.658
A13: VARIACIÓN NETA DE CAJA | B13: =SUM(B9:B12) -> 5000 | C13: =SUM(C9:C12) -> 0 | D13: =SUM(D9:D12) -> 0 | E13: =SUM(E9:E12) -> 0 | F13: =SUM(F9:F12) -> 0
A14: Caja final | B14: =INDEX(Engine!$C$77:$Y$77,1,(Assumptions!$C$4-1)*6+1) -> 5000 | C14: =INDEX(Engine!$C$77:$Y$77,1,(Assumptions!$C$4-1)*6+2) -> 5000 | D14: =INDEX(Engine!$C$77:$Y$77,1,(Assumptions!$C$4-1)*6+3) -> 5000 | E14: =INDEX(Engine!$C$77:$Y$77,1,(Assumptions!$C$4-1)*6+4) -> 5000 | F14: =INDEX(Engine!$C$77:$Y$77,1,(Assumptions!$C$4-1)*6+5) -> 5000
A15: Saldo de financiación ajena necesaria | B15: =INDEX(Engine!$C$75:$Y$75,1,(Assumptions!$C$4-1)*6+1) -> 11877.568 | C15: =INDEX(Engine!$C$75:$Y$75,1,(Assumptions!$C$4-1)*6+2) -> 50455.729 | D15: =INDEX(Engine!$C$75:$Y$75,1,(Assumptions!$C$4-1)*6+3) -> 90424.431 | E15: =INDEX(Engine!$C$75:$Y$75,1,(Assumptions!$C$4-1)*6+4) -> 128036.42 | F15: =INDEX(Engine!$C$75:$Y$75,1,(Assumptions!$C$4-1)*6+5) -> 153816.07
A16: Flujo de caja libre del proyecto | B16: =INDEX(Engine!$C$87:$Y$87,1,(Assumptions!$C$4-1)*6+1) -> -56877.568 | C16: =INDEX(Engine!$C$87:$Y$87,1,(Assumptions!$C$4-1)*6+2) -> -37746.731 | D16: =INDEX(Engine!$C$87:$Y$87,1,(Assumptions!$C$4-1)*6+3) -> -36436.801 | E16: =INDEX(Engine!$C$87:$Y$87,1,(Assumptions!$C$4-1)*6+4) -> -31282.276 | F16: =INDEX(Engine!$C$87:$Y$87,1,(Assumptions!$C$4-1)*6+5) -> -16817.109
A17: FCF acumulado | B17: =INDEX(Engine!$C$88:$Y$88,1,(Assumptions!$C$4-1)*6+1) -> -56877.568 | C17: =INDEX(Engine!$C$88:$Y$88,1,(Assumptions!$C$4-1)*6+2) -> -94624.299 | D17: =INDEX(Engine!$C$88:$Y$88,1,(Assumptions!$C$4-1)*6+3) -> -131061.1 | E17: =INDEX(Engine!$C$88:$Y$88,1,(Assumptions!$C$4-1)*6+4) -> -162343.38 | F17: =INDEX(Engine!$C$88:$Y$88,1,(Assumptions!$C$4-1)*6+5) -> -179160.48
A19: Control: caja final − caja inicial − variación neta | B19: =ROUND(B14-0-B13,2) -> 0 | C19: =ROUND(C14-B14-C13,2) -> 0 | D19: =ROUND(D14-C14-D13,2) -> 0 | E19: =ROUND(E14-D14-E13,2) -> 0 | F19: =ROUND(F14-E14-F13,2) -> 0

Sheet Balance Sheet
A1: Balance simplificado a 31/12 (escenario seleccionado)
A3: ="Escenario: "&Assumptions!$D$4 -> Escenario: Base
A5: Concepto | B5: 2027 | C5: 2028 | D5: 2029 | E5: 2030 | F5: 2031
A6: ACTIVO
A7: Intangible neto (marcas, diseño) | B7: =INDEX(Engine!$C$46:$Y$46,1,(Assumptions!$C$4-1)*6+1) -> 10400 | C7: =INDEX(Engine!$C$46:$Y$46,1,(Assumptions!$C$4-1)*6+2) -> 7800 | D7: =INDEX(Engine!$C$46:$Y$46,1,(Assumptions!$C$4-1)*6+3) -> 7600 | E7: =INDEX(Engine!$C$46:$Y$46,1,(Assumptions!$C$4-1)*6+4) -> 4400 | F7: =INDEX(Engine!$C$46:$Y$46,1,(Assumptions!$C$4-1)*6+5) -> 1200
A8: Existencias | B8: =INDEX(Engine!$C$57:$Y$57,1,(Assumptions!$C$4-1)*6+1) -> 10089.218 | C8: =INDEX(Engine!$C$57:$Y$57,1,(Assumptions!$C$4-1)*6+2) -> 17656.131 | D8: =INDEX(Engine!$C$57:$Y$57,1,(Assumptions!$C$4-1)*6+3) -> 25223.044 | E8: =INDEX(Engine!$C$57:$Y$57,1,(Assumptions!$C$4-1)*6+4) -> 32789.957 | F8: =INDEX(Engine!$C$57:$Y$57,1,(Assumptions!$C$4-1)*6+5) -> 32789.957
A9: IEE anticipado sobre existencias | B9: =INDEX(Engine!$C$59:$Y$59,1,(Assumptions!$C$4-1)*6+1) -> 3792 | C9: =INDEX(Engine!$C$59:$Y$59,1,(Assumptions!$C$4-1)*6+2) -> 6636 | D9: =INDEX(Engine!$C$59:$Y$59,1,(Assumptions!$C$4-1)*6+3) -> 9480 | E9: =INDEX(Engine!$C$59:$Y$59,1,(Assumptions!$C$4-1)*6+4) -> 12324 | F9: =INDEX(Engine!$C$59:$Y$59,1,(Assumptions!$C$4-1)*6+5) -> 12324
A10: Anticipos a fábrica | B10: =INDEX(Engine!$C$61:$Y$61,1,(Assumptions!$C$4-1)*6+1) -> 4258.3585 | C10: =INDEX(Engine!$C$61:$Y$61,1,(Assumptions!$C$4-1)*6+2) -> 6618.058 | D10: =INDEX(Engine!$C$61:$Y$61,1,(Assumptions!$C$4-1)*6+3) -> 8977.7575 | E10: =INDEX(Engine!$C$61:$Y$61,1,(Assumptions!$C$4-1)*6+4) -> 10225.365 | F10: =INDEX(Engine!$C$61:$Y$61,1,(Assumptions!$C$4-1)*6+5) -> 10225.365
A11: Clientes | B11: =INDEX(Engine!$C$60:$Y$60,1,(Assumptions!$C$4-1)*6+1) -> 0 | C11: =INDEX(Engine!$C$60:$Y$60,1,(Assumptions!$C$4-1)*6+2) -> 4915.3315 | D11: =INDEX(Engine!$C$60:$Y$60,1,(Assumptions!$C$4-1)*6+3) -> 8601.8301 | E11: =INDEX(Engine!$C$60:$Y$60,1,(Assumptions!$C$4-1)*6+4) -> 12288.329 | F11: =INDEX(Engine!$C$60:$Y$60,1,(Assumptions!$C$4-1)*6+5) -> 15974.827
A12: Hacienda deudora IVA | B12: =INDEX(Engine!$C$63:$Y$63,1,(Assumptions!$C$4-1)*6+1) -> 708.81392 | C12: =INDEX(Engine!$C$63:$Y$63,1,(Assumptions!$C$4-1)*6+2) -> 2035.6113 | D12: =INDEX(Engine!$C$63:$Y$63,1,(Assumptions!$C$4-1)*6+3) -> 3163.6119 | E12: =INDEX(Engine!$C$63:$Y$63,1,(Assumptions!$C$4-1)*6+4) -> 4291.6126 | F12: =INDEX(Engine!$C$63:$Y$63,1,(Assumptions!$C$4-1)*6+5) -> 4888.0027
A13: Tesorería | B13: =INDEX(Engine!$C$77:$Y$77,1,(Assumptions!$C$4-1)*6+1) -> 5000 | C13: =INDEX(Engine!$C$77:$Y$77,1,(Assumptions!$C$4-1)*6+2) -> 5000 | D13: =INDEX(Engine!$C$77:$Y$77,1,(Assumptions!$C$4-1)*6+3) -> 5000 | E13: =INDEX(Engine!$C$77:$Y$77,1,(Assumptions!$C$4-1)*6+4) -> 5000 | F13: =INDEX(Engine!$C$77:$Y$77,1,(Assumptions!$C$4-1)*6+5) -> 5000
A14: TOTAL ACTIVO | B14: =INDEX(Engine!$C$80:$Y$80,1,(Assumptions!$C$4-1)*6+1) -> 34248.39 | C14: =INDEX(Engine!$C$80:$Y$80,1,(Assumptions!$C$4-1)*6+2) -> 50661.132 | D14: =INDEX(Engine!$C$80:$Y$80,1,(Assumptions!$C$4-1)*6+3) -> 68046.244 | E14: =INDEX(Engine!$C$80:$Y$80,1,(Assumptions!$C$4-1)*6+4) -> 81319.263 | F14: =INDEX(Engine!$C$80:$Y$80,1,(Assumptions!$C$4-1)*6+5) -> 82402.152
A15: PATRIMONIO NETO Y PASIVO
A16: Capital | B16: =Assumptions!$C$9 -> 50000 | C16: =Assumptions!$C$9 -> 50000 | D16: =Assumptions!$C$9 -> 50000 | E16: =Assumptions!$C$9 -> 50000 | F16: =Assumptions!$C$9 -> 50000
A17: Resultados acumulados | B17: =INDEX(Engine!$C$82:$Y$82,1,(Assumptions!$C$4-1)*6+1) -> -29790 | C17: =INDEX(Engine!$C$82:$Y$82,1,(Assumptions!$C$4-1)*6+2) -> -53395.949 | D17: =INDEX(Engine!$C$82:$Y$82,1,(Assumptions!$C$4-1)*6+3) -> -77240.757 | E17: =INDEX(Engine!$C$82:$Y$82,1,(Assumptions!$C$4-1)*6+4) -> -103021.76 | F17: =INDEX(Engine!$C$82:$Y$82,1,(Assumptions!$C$4-1)*6+5) -> -129034
A18: PATRIMONIO NETO | B18: =INDEX(Engine!$C$83:$Y$83,1,(Assumptions!$C$4-1)*6+1) -> 20210 | C18: =INDEX(Engine!$C$83:$Y$83,1,(Assumptions!$C$4-1)*6+2) -> -3395.9486 | D18: =INDEX(Engine!$C$83:$Y$83,1,(Assumptions!$C$4-1)*6+3) -> -27240.757 | E18: =INDEX(Engine!$C$83:$Y$83,1,(Assumptions!$C$4-1)*6+4) -> -53021.765 | F18: =INDEX(Engine!$C$83:$Y$83,1,(Assumptions!$C$4-1)*6+5) -> -79034
A19: Financiación ajena | B19: =INDEX(Engine!$C$75:$Y$75,1,(Assumptions!$C$4-1)*6+1) -> 11877.568 | C19: =INDEX(Engine!$C$75:$Y$75,1,(Assumptions!$C$4-1)*6+2) -> 50455.729 | D19: =INDEX(Engine!$C$75:$Y$75,1,(Assumptions!$C$4-1)*6+3) -> 90424.431 | E19: =INDEX(Engine!$C$75:$Y$75,1,(Assumptions!$C$4-1)*6+4) -> 128036.42 | F19: =INDEX(Engine!$C$75:$Y$75,1,(Assumptions!$C$4-1)*6+5) -> 153816.07
A20: Proveedores | B20: =INDEX(Engine!$C$64:$Y$64,1,(Assumptions!$C$4-1)*6+1) -> 2160.8219 | C20: =INDEX(Engine!$C$64:$Y$64,1,(Assumptions!$C$4-1)*6+2) -> 1871.5068 | D20: =INDEX(Engine!$C$64:$Y$64,1,(Assumptions!$C$4-1)*6+3) -> 1835.3425 | E20: =INDEX(Engine!$C$64:$Y$64,1,(Assumptions!$C$4-1)*6+4) -> 1980 | F20: =INDEX(Engine!$C$64:$Y$64,1,(Assumptions!$C$4-1)*6+5) -> 1998.0822
A21: Hacienda acreedora IVA | B21: =INDEX(Engine!$C$66:$Y$66,1,(Assumptions!$C$4-1)*6+1) -> 0 | C21: =INDEX(Engine!$C$66:$Y$66,1,(Assumptions!$C$4-1)*6+2) -> 1729.8446 | D21: =INDEX(Engine!$C$66:$Y$66,1,(Assumptions!$C$4-1)*6+3) -> 3027.2281 | E21: =INDEX(Engine!$C$66:$Y$66,1,(Assumptions!$C$4-1)*6+4) -> 4324.6116 | F21: =INDEX(Engine!$C$66:$Y$66,1,(Assumptions!$C$4-1)*6+5) -> 5621.995
A22: TOTAL PN + PASIVO | B22: =B18+B19+B20+B21 -> 34248.39 | C22: =C18+C19+C20+C21 -> 50661.132 | D22: =D18+D19+D20+D21 -> 68046.244 | E22: =E18+E19+E20+E21 -> 81319.263 | F22: =F18+F19+F20+F21 -> 82402.152
A23: CONTROL (debe ser 0) | B23: =INDEX(Engine!$C$84:$Y$84,1,(Assumptions!$C$4-1)*6+1) -> 0 | C23: =INDEX(Engine!$C$84:$Y$84,1,(Assumptions!$C$4-1)*6+2) -> 0 | D23: =INDEX(Engine!$C$84:$Y$84,1,(Assumptions!$C$4-1)*6+3) -> 0 | E23: =INDEX(Engine!$C$84:$Y$84,1,(Assumptions!$C$4-1)*6+4) -> 0 | F23: =INDEX(Engine!$C$84:$Y$84,1,(Assumptions!$C$4-1)*6+5) -> 0

Sheet Break-even
A1: Punto muerto (escenario seleccionado)
A2: Unidades/año necesarias para cubrir gastos fijos con la contribución unitaria del año.
A3: ="Escenario: "&Assumptions!$D$4 -> Escenario: Base
A5: Concepto | B5: 2027 | C5: 2028 | D5: 2029 | E5: 2030 | F5: 2031
A6: Contribución por unidad vendida (€) | B6: =INDEX(Engine!$C$26:$Y$26,1,(Assumptions!$C$4-1)*6+1) -> 1.7477406 | C6: =INDEX(Engine!$C$26:$Y$26,1,(Assumptions!$C$4-1)*6+2) -> 1.7477406 | D6: =INDEX(Engine!$C$26:$Y$26,1,(Assumptions!$C$4-1)*6+3) -> 1.7477406 | E6: =INDEX(Engine!$C$26:$Y$26,1,(Assumptions!$C$4-1)*6+4) -> 1.7477406 | F6: =INDEX(Engine!$C$26:$Y$26,1,(Assumptions!$C$4-1)*6+5) -> 1.7477406
A7: Gastos fijos + despachos (€) | B7: =INDEX(Engine!$C$40:$Y$40,1,(Assumptions!$C$4-1)*6+1)+Assumptions!$C$18*Assumptions!$C$17 -> 27190 | C7: =INDEX(Engine!$C$40:$Y$40,1,(Assumptions!$C$4-1)*6+2)+Assumptions!$C$18*Assumptions!$C$17 -> 23670 | D7: =INDEX(Engine!$C$40:$Y$40,1,(Assumptions!$C$4-1)*6+3)+Assumptions!$C$18*Assumptions!$C$17 -> 23230 | E7: =INDEX(Engine!$C$40:$Y$40,1,(Assumptions!$C$4-1)*6+4)+Assumptions!$C$18*Assumptions!$C$17 -> 24990 | F7: =INDEX(Engine!$C$40:$Y$40,1,(Assumptions!$C$4-1)*6+5)+Assumptions!$C$18*Assumptions!$C$17 -> 25210
A8: Punto muerto EBITDA (unidades) | B8: =INDEX(Engine!$C$97:$Y$97,1,(Assumptions!$C$4-1)*6+1) -> 15557.229 | C8: =INDEX(Engine!$C$97:$Y$97,1,(Assumptions!$C$4-1)*6+2) -> 13543.2 | D8: =INDEX(Engine!$C$97:$Y$97,1,(Assumptions!$C$4-1)*6+3) -> 13291.446 | E8: =INDEX(Engine!$C$97:$Y$97,1,(Assumptions!$C$4-1)*6+4) -> 14298.461 | F8: =INDEX(Engine!$C$97:$Y$97,1,(Assumptions!$C$4-1)*6+5) -> 14424.337
A9: Punto muerto EBIT (unidades) | B9: =INDEX(Engine!$C$98:$Y$98,1,(Assumptions!$C$4-1)*6+1) -> 17044.864 | C9: =INDEX(Engine!$C$98:$Y$98,1,(Assumptions!$C$4-1)*6+2) -> 15030.835 | D9: =INDEX(Engine!$C$98:$Y$98,1,(Assumptions!$C$4-1)*6+3) -> 15122.381 | E9: =INDEX(Engine!$C$98:$Y$98,1,(Assumptions!$C$4-1)*6+4) -> 16129.396 | F9: =INDEX(Engine!$C$98:$Y$98,1,(Assumptions!$C$4-1)*6+5) -> 16255.273
A10: Unidades vendidas | B10: =INDEX(Engine!$C$14:$Y$14,1,(Assumptions!$C$4-1)*6+1) -> 0 | C10: =INDEX(Engine!$C$14:$Y$14,1,(Assumptions!$C$4-1)*6+2) -> 2000 | D10: =INDEX(Engine!$C$14:$Y$14,1,(Assumptions!$C$4-1)*6+3) -> 3500 | E10: =INDEX(Engine!$C$14:$Y$14,1,(Assumptions!$C$4-1)*6+4) -> 5000 | F10: =INDEX(Engine!$C$14:$Y$14,1,(Assumptions!$C$4-1)*6+5) -> 6500
A11: Cobertura (ventas / punto muerto EBITDA) | B11: =IFERROR(B10/B8,0) -> 0 | C11: =IFERROR(C10/C8,0) -> 0.14767559 | D11: =IFERROR(D10/D8,0) -> 0.26332725 | E11: =IFERROR(E10/E8,0) -> 0.34968799 | F11: =IFERROR(F10/F8,0) -> 0.45062729
A12: Cajas/año para punto muerto EBITDA | B12: =IFERROR(B8/Assumptions!$C$20,"n/a") -> 1555.7229 | C12: =IFERROR(C8/Assumptions!$C$20,"n/a") -> 1354.32 | D12: =IFERROR(D8/Assumptions!$C$20,"n/a") -> 1329.1446 | E12: =IFERROR(E8/Assumptions!$C$20,"n/a") -> 1429.8461 | F12: =IFERROR(F8/Assumptions!$C$20,"n/a") -> 1442.4337
A13: Puntos de venta necesarios para el punto muerto | B13: =IFERROR(B12/Assumptions!$C$21,"n/a") -> 388.93071 | C13: =IFERROR(C12/Assumptions!$C$21,"n/a") -> 338.57999 | D13: =IFERROR(D12/Assumptions!$C$21,"n/a") -> 332.28615 | E13: =IFERROR(E12/Assumptions!$C$21,"n/a") -> 357.46151 | F13: =IFERROR(F12/Assumptions!$C$21,"n/a") -> 360.60843

Sheet Scenarios
A1: Comparativa de escenarios y adecuación del capital
A2: Todas las cifras leen directamente del motor (mismas fórmulas para los 4 escenarios).
A4: Métrica | B4: Conservador | C4: Base | D4: Optimista | E4: Estrés
A5: Unidades vendidas 2027–2031 | B5: =SUM(Engine!$C$14:$G$14) -> 7000 | C5: =SUM(Engine!$I$14:$M$14) -> 17000 | D5: =SUM(Engine!$O$14:$S$14) -> 30500 | E5: =SUM(Engine!$U$14:$Y$14) -> 3552.8549
A6: Unidades vendidas 2031 | B6: =Engine!$G$14 -> 2500 | C6: =Engine!$M$14 -> 6500 | D6: =Engine!$S$14 -> 12000 | E6: =Engine!$Y$14 -> 0
A7: Ingresos de la marca 2027–2031 (antes de IEE) | B7: =SUM(Engine!$C$33:$G$33) -> 94702.479 | C7: =SUM(Engine!$I$33:$M$33) -> 280070.08 | D7: =SUM(Engine!$O$33:$S$33) -> 590495.12 | E7: =SUM(Engine!$U$33:$Y$33) -> 57679.572
A8: Ingresos netos de impuestos 2031 | B8: =Engine!$G$35 -> 25190.525 | C8: =Engine!$M$35 -> 80935.871 | D8: =Engine!$S$35 -> 176827.32 | E8: =Engine!$Y$35 -> 0
A9: EBITDA 2028 | B9: =Engine!$D$41 -> -29795.863 | C9: =Engine!$J$41 -> -20174.519 | D9: =Engine!$P$41 -> -5385.032 | E9: =Engine!$V$41 -> -33103.331
A10: EBITDA 2029 | B10: =Engine!$E$41 -> -30645.045 | C10: =Engine!$K$41 -> -17112.908 | D10: =Engine!$Q$41 -> 9786.0879 | E10: =Engine!$W$41 -> -30584.447
A11: EBITDA 2030 | B11: =Engine!$F$41 -> -34024.226 | C11: =Engine!$L$41 -> -16251.297 | D11: =Engine!$R$41 -> 25474.632 | E11: =Engine!$X$41 -> -28908
A12: EBITDA 2031 | B12: =Engine!$G$41 -> -35632.408 | C12: =Engine!$M$41 -> -13849.686 | D12: =Engine!$S$41 -> 42857.176 | E12: =Engine!$Y$41 -> -29172
A13: EBITDA acumulado 2027–2031 | B13: =SUM(Engine!$C$41:$G$41) -> -161231.04 | C13: =SUM(Engine!$I$41:$M$41) -> -94578.41 | D13: =SUM(Engine!$O$41:$S$41) -> 42913.864 | E13: =SUM(Engine!$U$41:$Y$41) -> -154215.78
A14: Resultado neto acumulado | B14: =SUM(Engine!$C$54:$G$54) -> -195063.03 | C14: =SUM(Engine!$I$54:$M$54) -> -129034 | D14: =SUM(Engine!$O$54:$S$54) -> 7252.0965 | E14: =SUM(Engine!$U$54:$Y$54) -> -188166.89
A15: FCF acumulado 2027–2031 | B15: =Engine!$G$88 -> -204452.12 | C15: =Engine!$M$88 -> -179160.48 | D15: =Engine!$S$88 -> -94057.914 | E15: =Engine!$Y$88 -> -167818.08
A16: Necesidad máxima de financiación (capital + deuda) | B16: =MAX(0,Assumptions!$C$32-MIN(0,MIN(Engine!$C$88:$G$88))) -> 209452.12 | C16: =MAX(0,Assumptions!$C$32-MIN(0,MIN(Engine!$I$88:$M$88))) -> 184160.48 | D16: =MAX(0,Assumptions!$C$32-MIN(0,MIN(Engine!$O$88:$S$88))) -> 132822.63 | E16: =MAX(0,Assumptions!$C$32-MIN(0,MIN(Engine!$U$88:$Y$88))) -> 172818.08
A17: Financiación ajena máxima con el capital de 'Assumptions' | B17: =MAX(Engine!$C$75:$G$75) -> 178484.11 | C17: =MAX(Engine!$I$75:$M$75) -> 153816.07 | D17: =MAX(Engine!$O$75:$S$75) -> 94642.088 | E17: =MAX(Engine!$U$75:$Y$75) -> 141969.19
A18: VAN (tasa de 'Assumptions') | B18: =SUM(Engine!$C$92:$G$92) -> -131046.35 | C18: =SUM(Engine!$I$92:$M$92) -> -120972.97 | D18: =SUM(Engine!$O$92:$S$92) -> 10753.631 | E18: =SUM(Engine!$U$92:$Y$92) -> -116081
A19: TIR del proyecto (con valor terminal) | B19: =IFERROR(IRR(Engine!$C$90:$G$90),"n/c") -> n/c | C19: =IFERROR(IRR(Engine!$I$90:$M$90),"n/c") -> n/c | D19: =IFERROR(IRR(Engine!$O$90:$S$90),"n/c") -> 0.21640347 | E19: =IFERROR(IRR(Engine!$U$90:$Y$90),"n/c") -> n/c
A20: Payback (año) | B20: =IFERROR(1/(1/MIN(Engine!$C$93:$G$93)),"> 2031") -> > 2031 | C20: =IFERROR(1/(1/MIN(Engine!$I$93:$M$93)),"> 2031") -> > 2031 | D20: =IFERROR(1/(1/MIN(Engine!$O$93:$S$93)),"> 2031") -> > 2031 | E20: =IFERROR(1/(1/MIN(Engine!$U$93:$Y$93)),"> 2031") -> > 2031
A21: Punto muerto EBITDA 2030 (unidades) | B21: =Engine!$F$97 -> n/a | C21: =Engine!$L$97 -> 14298.461 | D21: =Engine!$R$97 -> 4663.7802 | E21: =Engine!$X$97 -> n/a
A22: Contribución unitaria 2030 (€/u) | B22: =Engine!$F$26 -> -2.7103632 | C22: =Engine!$L$26 -> 1.7477406 | D22: =Engine!$R$26 -> 5.874848 | E22: =Engine!$X$26 -> -2.4396657
A23: ROIC 2031 | B23: =Engine!$G$96 -> -0.98418762 | C23: =Engine!$M$96 -> -0.18294083 | D23: =Engine!$S$96 -> 0.2520223 | E23: =Engine!$Y$96 -> n/a
A24: Control de balance (suma de descuadres) | B24: =SUMPRODUCT(ABS(Engine!$C$84:$G$84)) -> 0 | C24: =SUMPRODUCT(ABS(Engine!$I$84:$M$84)) -> 0 | D24: =SUMPRODUCT(ABS(Engine!$O$84:$S$84)) -> 0 | E24: =SUMPRODUCT(ABS(Engine!$U$84:$Y$84)) -> 0
A27: Adecuación del capital inicial (margen de seguridad sobre la necesidad máxima)
A28: Colchón de seguridad exigido sobre la necesidad máxima | B28: 0.25
A29: Capital disponible | B29: Conservador | C29: Base | D29: Optimista | E29: Estrés
A30: 15000 | B30: =IF($A30>=B$16*(1+$B$28),"Viable",IF($A30>=B$16,"Ajustado","Insuficiente")) -> Insuficiente | C30: =IF($A30>=C$16*(1+$B$28),"Viable",IF($A30>=C$16,"Ajustado","Insuficiente")) -> Insuficiente | D30: =IF($A30>=D$16*(1+$B$28),"Viable",IF($A30>=D$16,"Ajustado","Insuficiente")) -> Insuficiente | E30: =IF($A30>=E$16*(1+$B$28),"Viable",IF($A30>=E$16,"Ajustado","Insuficiente")) -> Insuficiente
A31: 30000 | B31: =IF($A31>=B$16*(1+$B$28),"Viable",IF($A31>=B$16,"Ajustado","Insuficiente")) -> Insuficiente | C31: =IF($A31>=C$16*(1+$B$28),"Viable",IF($A31>=C$16,"Ajustado","Insuficiente")) -> Insuficiente | D31: =IF($A31>=D$16*(1+$B$28),"Viable",IF($A31>=D$16,"Ajustado","Insuficiente")) -> Insuficiente | E31: =IF($A31>=E$16*(1+$B$28),"Viable",IF($A31>=E$16,"Ajustado","Insuficiente")) -> Insuficiente
A32: 50000 | B32: =IF($A32>=B$16*(1+$B$28),"Viable",IF($A32>=B$16,"Ajustado","Insuficiente")) -> Insuficiente | C32: =IF($A32>=C$16*(1+$B$28),"Viable",IF($A32>=C$16,"Ajustado","Insuficiente")) -> Insuficiente | D32: =IF($A32>=D$16*(1+$B$28),"Viable",IF($A32>=D$16,"Ajustado","Insuficiente")) -> Insuficiente | E32: =IF($A32>=E$16*(1+$B$28),"Viable",IF($A32>=E$16,"Ajustado","Insuficiente")) -> Insuficiente
A33: 75000 | B33: =IF($A33>=B$16*(1+$B$28),"Viable",IF($A33>=B$16,"Ajustado","Insuficiente")) -> Insuficiente | C33: =IF($A33>=C$16*(1+$B$28),"Viable",IF($A33>=C$16,"Ajustado","Insuficiente")) -> Insuficiente | D33: =IF($A33>=D$16*(1+$B$28),"Viable",IF($A33>=D$16,"Ajustado","Insuficiente")) -> Insuficiente | E33: =IF($A33>=E$16*(1+$B$28),"Viable",IF($A33>=E$16,"Ajustado","Insuficiente")) -> Insuficiente
A34: 100000 | B34: =IF($A34>=B$16*(1+$B$28),"Viable",IF($A34>=B$16,"Ajustado","Insuficiente")) -> Insuficiente | C34: =IF($A34>=C$16*(1+$B$28),"Viable",IF($A34>=C$16,"Ajustado","Insuficiente")) -> Insuficiente | D34: =IF($A34>=D$16*(1+$B$28),"Viable",IF($A34>=D$16,"Ajustado","Insuficiente")) -> Insuficiente | E34: =IF($A34>=E$16*(1+$B$28),"Viable",IF($A34>=E$16,"Ajustado","Insuficiente")) -> Insuficiente
A36: Tamaño del lote inicial (escenario seleccionado, valores 2028)
A37: Unidades del lote | B37: Pago a fábrica (€) | C37: Coste en destino total (€) | D37: IEE si se paga al importar (€) | E37: Caja inmovilizada (€) | F37: Meses de venta a demanda 2029 | G37: Riesgo de envejecimiento
A38: 1000 | B38: =A38*(INDEX(Engine!$C$20:$Y$20,1,(Assumptions!$C$4-1)*6+2)+INDEX(Engine!$C$21:$Y$21,1,(Assumptions!$C$4-1)*6+2)+Assumptions!$G$42) -> 7117.3913 | C38: =A38*INDEX(Engine!$C$24:$Y$24,1,(Assumptions!$C$4-1)*6+2)+Assumptions!$C$17 -> 10539.218 | D38: =A38*INDEX(Engine!$C$25:$Y$25,1,(Assumptions!$C$4-1)*6+2)*Assumptions!$C$26 -> 3792 | E38: =C38+D38 -> 14331.218 | F38: =IFERROR(A38/(INDEX(Engine!$C$8:$Y$8,1,(Assumptions!$C$4-1)*6+3)/12),"n/a") -> 3.4285714 | G38: =IF(F38="n/a","n/a",IF(F38>24,"Alto",IF(F38>12,"Medio","Bajo"))) -> Bajo
A39: 3000 | B39: =A39*(INDEX(Engine!$C$20:$Y$20,1,(Assumptions!$C$4-1)*6+2)+INDEX(Engine!$C$21:$Y$21,1,(Assumptions!$C$4-1)*6+2)+Assumptions!$G$42) -> 21352.174 | C39: =A39*INDEX(Engine!$C$24:$Y$24,1,(Assumptions!$C$4-1)*6+2)+Assumptions!$C$17 -> 30717.653 | D39: =A39*INDEX(Engine!$C$25:$Y$25,1,(Assumptions!$C$4-1)*6+2)*Assumptions!$C$26 -> 11376 | E39: =C39+D39 -> 42093.653 | F39: =IFERROR(A39/(INDEX(Engine!$C$8:$Y$8,1,(Assumptions!$C$4-1)*6+3)/12),"n/a") -> 10.285714 | G39: =IF(F39="n/a","n/a",IF(F39>24,"Alto",IF(F39>12,"Medio","Bajo"))) -> Bajo
A40: 5000 | B40: =A40*(INDEX(Engine!$C$20:$Y$20,1,(Assumptions!$C$4-1)*6+2)+INDEX(Engine!$C$21:$Y$21,1,(Assumptions!$C$4-1)*6+2)+Assumptions!$G$42) -> 35586.957 | C40: =A40*INDEX(Engine!$C$24:$Y$24,1,(Assumptions!$C$4-1)*6+2)+Assumptions!$C$17 -> 50896.088 | D40: =A40*INDEX(Engine!$C$25:$Y$25,1,(Assumptions!$C$4-1)*6+2)*Assumptions!$C$26 -> 18960 | E40: =C40+D40 -> 69856.088 | F40: =IFERROR(A40/(INDEX(Engine!$C$8:$Y$8,1,(Assumptions!$C$4-1)*6+3)/12),"n/a") -> 17.142857 | G40: =IF(F40="n/a","n/a",IF(F40>24,"Alto",IF(F40>12,"Medio","Bajo"))) -> Medio
A41: 10000 | B41: =A41*(INDEX(Engine!$C$20:$Y$20,1,(Assumptions!$C$4-1)*6+2)+INDEX(Engine!$C$21:$Y$21,1,(Assumptions!$C$4-1)*6+2)+Assumptions!$G$42) -> 71173.913 | C41: =A41*INDEX(Engine!$C$24:$Y$24,1,(Assumptions!$C$4-1)*6+2)+Assumptions!$C$17 -> 101342.18 | D41: =A41*INDEX(Engine!$C$25:$Y$25,1,(Assumptions!$C$4-1)*6+2)*Assumptions!$C$26 -> 37920 | E41: =C41+D41 -> 139262.18 | F41: =IFERROR(A41/(INDEX(Engine!$C$8:$Y$8,1,(Assumptions!$C$4-1)*6+3)/12),"n/a") -> 34.285714 | G41: =IF(F41="n/a","n/a",IF(F41>24,"Alto",IF(F41>12,"Medio","Bajo"))) -> Alto
A42: 20000 | B42: =A42*(INDEX(Engine!$C$20:$Y$20,1,(Assumptions!$C$4-1)*6+2)+INDEX(Engine!$C$21:$Y$21,1,(Assumptions!$C$4-1)*6+2)+Assumptions!$G$42) -> 142347.83 | C42: =A42*INDEX(Engine!$C$24:$Y$24,1,(Assumptions!$C$4-1)*6+2)+Assumptions!$C$17 -> 202234.35 | D42: =A42*INDEX(Engine!$C$25:$Y$25,1,(Assumptions!$C$4-1)*6+2)*Assumptions!$C$26 -> 75840 | E42: =C42+D42 -> 278074.35 | F42: =IFERROR(A42/(INDEX(Engine!$C$8:$Y$8,1,(Assumptions!$C$4-1)*6+3)/12),"n/a") -> 68.571429 | G42: =IF(F42="n/a","n/a",IF(F42>24,"Alto",IF(F42>12,"Medio","Bajo"))) -> Alto

Sheet Sensitivity Analysis
A1: Análisis de sensibilidad — EBITDA 2030 (año estabilizado, escenario seleccionado)
A2: Forma cerrada equivalente al motor para 2030: EBITDA = U × contribución(PVP, FOB, FX, tarifa, merma) − gastos fijos − despachos.
A4: Base: unidades 2030 | B4: =INDEX(Engine!$C$14:$Y$14,1,(Assumptions!$C$4-1)*6+4) -> 5000
A5: Base: PVP | B5: =INDEX(Engine!$C$19:$Y$19,1,(Assumptions!$C$4-1)*6+4) -> 24
A6: Base: FOB USD/u | B6: =Assumptions!$G$40 -> 6
A7: Base: tipo de cambio USD/€ | B7: =Assumptions!$C$19 -> 1.15
A8: Base: tarifa distribuidor | B8: =Assumptions!$G$45 -> 0.05
A9: Base: merma | B9: =Assumptions!$G$46 -> 0.03
A10: Coste no-FOB en destino por unidad (excl. FOB y su arancel/seguro) | B10: =INDEX(Engine!$C$24:$Y$24,1,(Assumptions!$C$4-1)*6+4)-INDEX(Engine!$C$20:$Y$20,1,(Assumptions!$C$4-1)*6+4)*(1+Assumptions!$C$15)*(1+Assumptions!$C$14) -> 3.482435
A11: Gastos fijos 2030 + despachos (motor) | B11: =INDEX(Engine!$C$40:$Y$40,1,(Assumptions!$C$4-1)*6+4)+INDEX(Engine!$C$37:$Y$37,1,(Assumptions!$C$4-1)*6+4) -> 24990
A12: EBITDA 2030 (motor) | B12: =INDEX(Engine!$C$41:$Y$41,1,(Assumptions!$C$4-1)*6+4) -> -16251.297
A13: EBITDA 2030 (forma cerrada) — control | B13: =$B$4*(($B$5/(1+Assumptions!$C$10)-$B$5*(Assumptions!$C$13+$B$8))*(1-Assumptions!$C$28)-(1/(1-$B$9)+Assumptions!$G$47)*(MAX(Assumptions!$C$11*$B$5,Assumptions!$C$12/1000)+($B$6/$B$7*(1+Assumptions!$C$15)*(1+Assumptions!$C$14)+$B$10)))-$B$11 -> -16251.297 | C13: =ROUND(B13-B12,0) -> 0 | D13: ← diferencia (debe ser 0)
A15: Tornado: impacto en EBITDA 2030 de variaciones individuales
A16: Variable | B16: Caso desfavorable | C16: Caso favorable | D16: EBITDA desfavorable | E16: EBITDA favorable | F16: Rango
A17: Volumen (unidades) | B17: -0.2 | C17: 0.2 | D17: =($B$4*(1+$B17))*(($B$5/(1+Assumptions!$C$10)-$B$5*(Assumptions!$C$13+$B$8))*(1-Assumptions!$C$28)-(1/(1-$B$9)+Assumptions!$G$47)*(MAX(Assumptions!$C$11*$B$5,Assumptions!$C$12/1000)+($B$6/$B$7*(1+Assumptions!$C$15)*(1+Assumptions!$C$14)+$B$10)))-$B$11 -> -17999.038 | E17: =($B$4*(1+$C17))*(($B$5/(1+Assumptions!$C$10)-$B$5*(Assumptions!$C$13+$B$8))*(1-Assumptions!$C$28)-(1/(1-$B$9)+Assumptions!$G$47)*(MAX(Assumptions!$C$11*$B$5,Assumptions!$C$12/1000)+($B$6/$B$7*(1+Assumptions!$C$15)*(1+Assumptions!$C$14)+$B$10)))-$B$11 -> -14503.556 | F17: =ABS(E17-D17) -> 3495.4812
A18: PVP | B18: -0.1 | C18: 0.1 | D18: =$B$4*((($B$5*(1+$B18))/(1+Assumptions!$C$10)-($B$5*(1+$B18))*(Assumptions!$C$13+$B$8))*(1-Assumptions!$C$28)-(1/(1-$B$9)+Assumptions!$G$47)*(MAX(Assumptions!$C$11*($B$5*(1+$B18)),Assumptions!$C$12/1000)+($B$6/$B$7*(1+Assumptions!$C$15)*(1+Assumptions!$C$14)+$B$10)))-$B$11 -> -22477.133 | E18: =$B$4*((($B$5*(1+$C18))/(1+Assumptions!$C$10)-($B$5*(1+$C18))*(Assumptions!$C$13+$B$8))*(1-Assumptions!$C$28)-(1/(1-$B$9)+Assumptions!$G$47)*(MAX(Assumptions!$C$11*($B$5*(1+$C18)),Assumptions!$C$12/1000)+($B$6/$B$7*(1+Assumptions!$C$15)*(1+Assumptions!$C$14)+$B$10)))-$B$11 -> -10025.461 | F18: =ABS(E18-D18) -> 12451.672
A19: Coste FOB | B19: 0.2 | C19: -0.2 | D19: =$B$4*(($B$5/(1+Assumptions!$C$10)-$B$5*(Assumptions!$C$13+$B$8))*(1-Assumptions!$C$28)-(1/(1-$B$9)+Assumptions!$G$47)*(MAX(Assumptions!$C$11*$B$5,Assumptions!$C$12/1000)+(($B$6*(1+$B19))/$B$7*(1+Assumptions!$C$15)*(1+Assumptions!$C$14)+$B$10)))-$B$11 -> -23260.617 | E19: =$B$4*(($B$5/(1+Assumptions!$C$10)-$B$5*(Assumptions!$C$13+$B$8))*(1-Assumptions!$C$28)-(1/(1-$B$9)+Assumptions!$G$47)*(MAX(Assumptions!$C$11*$B$5,Assumptions!$C$12/1000)+(($B$6*(1+$C19))/$B$7*(1+Assumptions!$C$15)*(1+Assumptions!$C$14)+$B$10)))-$B$11 -> -9241.9774 | F19: =ABS(E19-D19) -> 14018.639
A20: Tipo de cambio USD/€ | B20: -0.1 | C20: 0.1 | D20: =$B$4*(($B$5/(1+Assumptions!$C$10)-$B$5*(Assumptions!$C$13+$B$8))*(1-Assumptions!$C$28)-(1/(1-$B$9)+Assumptions!$G$47)*(MAX(Assumptions!$C$11*$B$5,Assumptions!$C$12/1000)+($B$6/($B$7*(1+$B20))*(1+Assumptions!$C$15)*(1+Assumptions!$C$14)+$B$10)))-$B$11 -> -20145.363 | E20: =$B$4*(($B$5/(1+Assumptions!$C$10)-$B$5*(Assumptions!$C$13+$B$8))*(1-Assumptions!$C$28)-(1/(1-$B$9)+Assumptions!$G$47)*(MAX(Assumptions!$C$11*$B$5,Assumptions!$C$12/1000)+($B$6/($B$7*(1+$C20))*(1+Assumptions!$C$15)*(1+Assumptions!$C$14)+$B$10)))-$B$11 -> -13065.243 | F20: =ABS(E20-D20) -> 7080.1208
A21: Tarifa distribuidor (pp) | B21: 0.02 | C21: -0.02 | D21: =$B$4*(($B$5/(1+Assumptions!$C$10)-$B$5*(Assumptions!$C$13+($B$8+$B21)))*(1-Assumptions!$C$28)-(1/(1-$B$9)+Assumptions!$G$47)*(MAX(Assumptions!$C$11*$B$5,Assumptions!$C$12/1000)+($B$6/$B$7*(1+Assumptions!$C$15)*(1+Assumptions!$C$14)+$B$10)))-$B$11 -> -18651.297 | E21: =$B$4*(($B$5/(1+Assumptions!$C$10)-$B$5*(Assumptions!$C$13+($B$8+$C21)))*(1-Assumptions!$C$28)-(1/(1-$B$9)+Assumptions!$G$47)*(MAX(Assumptions!$C$11*$B$5,Assumptions!$C$12/1000)+($B$6/$B$7*(1+Assumptions!$C$15)*(1+Assumptions!$C$14)+$B$10)))-$B$11 -> -13851.297 | F21: =ABS(E21-D21) -> 4800
A22: Merma (pp) | B22: 0.03 | C22: -0.02 | D22: =$B$4*(($B$5/(1+Assumptions!$C$10)-$B$5*(Assumptions!$C$13+$B$8))*(1-Assumptions!$C$28)-(1/(1-($B$9+$B22))+Assumptions!$G$47)*(MAX(Assumptions!$C$11*$B$5,Assumptions!$C$12/1000)+($B$6/$B$7*(1+Assumptions!$C$15)*(1+Assumptions!$C$14)+$B$10)))-$B$11 -> -18534.893 | E22: =$B$4*(($B$5/(1+Assumptions!$C$10)-$B$5*(Assumptions!$C$13+$B$8))*(1-Assumptions!$C$28)-(1/(1-($B$9+$C22))+Assumptions!$G$47)*(MAX(Assumptions!$C$11*$B$5,Assumptions!$C$12/1000)+($B$6/$B$7*(1+Assumptions!$C$15)*(1+Assumptions!$C$14)+$B$10)))-$B$11 -> -14805.789 | F22: =ABS(E22-D22) -> 3729.1042
A24: Tabla bidimensional: EBITDA 2030 según PVP (filas) y FOB USD/u (columnas)
A25: PVP \ FOB | B25: 4 USD | C25: 5 USD | D25: 6 USD | E25: 7 USD | F25: 8 USD | G25: 9 USD | H25: 10 USD
A26: FOB (input) | B26: 4 | C26: 5 | D26: 6 | E26: 7 | F26: 8 | G26: 9 | H26: 10
A27: 12 | B27: =$B$4*(($A27/(1+Assumptions!$C$10)-$A27*(Assumptions!$C$13+$B$8))*(1-Assumptions!$C$28)-(1/(1-$B$9)+Assumptions!$G$47)*(MAX(Assumptions!$C$11*$A27,Assumptions!$C$12/1000)+(B$26/$B$7*(1+Assumptions!$C$15)*(1+Assumptions!$C$14)+$B$10)))-$B$11 -> -35698.279 | C27: =$B$4*(($A27/(1+Assumptions!$C$10)-$A27*(Assumptions!$C$13+$B$8))*(1-Assumptions!$C$28)-(1/(1-$B$9)+Assumptions!$G$47)*(MAX(Assumptions!$C$11*$A27,Assumptions!$C$12/1000)+(C$26/$B$7*(1+Assumptions!$C$15)*(1+Assumptions!$C$14)+$B$10)))-$B$11 -> -41539.378 | D27: =$B$4*(($A27/(1+Assumptions!$C$10)-$A27*(Assumptions!$C$13+$B$8))*(1-Assumptions!$C$28)-(1/(1-$B$9)+Assumptions!$G$47)*(MAX(Assumptions!$C$11*$A27,Assumptions!$C$12/1000)+(D$26/$B$7*(1+Assumptions!$C$15)*(1+Assumptions!$C$14)+$B$10)))-$B$11 -> -47380.478 | E27: =$B$4*(($A27/(1+Assumptions!$C$10)-$A27*(Assumptions!$C$13+$B$8))*(1-Assumptions!$C$28)-(1/(1-$B$9)+Assumptions!$G$47)*(MAX(Assumptions!$C$11*$A27,Assumptions!$C$12/1000)+(E$26/$B$7*(1+Assumptions!$C$15)*(1+Assumptions!$C$14)+$B$10)))-$B$11 -> -53221.578 | F27: =$B$4*(($A27/(1+Assumptions!$C$10)-$A27*(Assumptions!$C$13+$B$8))*(1-Assumptions!$C$28)-(1/(1-$B$9)+Assumptions!$G$47)*(MAX(Assumptions!$C$11*$A27,Assumptions!$C$12/1000)+(F$26/$B$7*(1+Assumptions!$C$15)*(1+Assumptions!$C$14)+$B$10)))-$B$11 -> -59062.677 | G27: =$B$4*(($A27/(1+Assumptions!$C$10)-$A27*(Assumptions!$C$13+$B$8))*(1-Assumptions!$C$28)-(1/(1-$B$9)+Assumptions!$G$47)*(MAX(Assumptions!$C$11*$A27,Assumptions!$C$12/1000)+(G$26/$B$7*(1+Assumptions!$C$15)*(1+Assumptions!$C$14)+$B$10)))-$B$11 -> -64903.777 | H27: =$B$4*(($A27/(1+Assumptions!$C$10)-$A27*(Assumptions!$C$13+$B$8))*(1-Assumptions!$C$28)-(1/(1-$B$9)+Assumptions!$G$47)*(MAX(Assumptions!$C$11*$A27,Assumptions!$C$12/1000)+(H$26/$B$7*(1+Assumptions!$C$15)*(1+Assumptions!$C$14)+$B$10)))-$B$11 -> -70744.877
A28: 15 | B28: =$B$4*(($A28/(1+Assumptions!$C$10)-$A28*(Assumptions!$C$13+$B$8))*(1-Assumptions!$C$28)-(1/(1-$B$9)+Assumptions!$G$47)*(MAX(Assumptions!$C$11*$A28,Assumptions!$C$12/1000)+(B$26/$B$7*(1+Assumptions!$C$15)*(1+Assumptions!$C$14)+$B$10)))-$B$11 -> -27915.983 | C28: =$B$4*(($A28/(1+Assumptions!$C$10)-$A28*(Assumptions!$C$13+$B$8))*(1-Assumptions!$C$28)-(1/(1-$B$9)+Assumptions!$G$47)*(MAX(Assumptions!$C$11*$A28,Assumptions!$C$12/1000)+(C$26/$B$7*(1+Assumptions!$C$15)*(1+Assumptions!$C$14)+$B$10)))-$B$11 -> -33757.083 | D28: =$B$4*(($A28/(1+Assumptions!$C$10)-$A28*(Assumptions!$C$13+$B$8))*(1-Assumptions!$C$28)-(1/(1-$B$9)+Assumptions!$G$47)*(MAX(Assumptions!$C$11*$A28,Assumptions!$C$12/1000)+(D$26/$B$7*(1+Assumptions!$C$15)*(1+Assumptions!$C$14)+$B$10)))-$B$11 -> -39598.183 | E28: =$B$4*(($A28/(1+Assumptions!$C$10)-$A28*(Assumptions!$C$13+$B$8))*(1-Assumptions!$C$28)-(1/(1-$B$9)+Assumptions!$G$47)*(MAX(Assumptions!$C$11*$A28,Assumptions!$C$12/1000)+(E$26/$B$7*(1+Assumptions!$C$15)*(1+Assumptions!$C$14)+$B$10)))-$B$11 -> -45439.282 | F28: =$B$4*(($A28/(1+Assumptions!$C$10)-$A28*(Assumptions!$C$13+$B$8))*(1-Assumptions!$C$28)-(1/(1-$B$9)+Assumptions!$G$47)*(MAX(Assumptions!$C$11*$A28,Assumptions!$C$12/1000)+(F$26/$B$7*(1+Assumptions!$C$15)*(1+Assumptions!$C$14)+$B$10)))-$B$11 -> -51280.382 | G28: =$B$4*(($A28/(1+Assumptions!$C$10)-$A28*(Assumptions!$C$13+$B$8))*(1-Assumptions!$C$28)-(1/(1-$B$9)+Assumptions!$G$47)*(MAX(Assumptions!$C$11*$A28,Assumptions!$C$12/1000)+(G$26/$B$7*(1+Assumptions!$C$15)*(1+Assumptions!$C$14)+$B$10)))-$B$11 -> -57121.482 | H28: =$B$4*(($A28/(1+Assumptions!$C$10)-$A28*(Assumptions!$C$13+$B$8))*(1-Assumptions!$C$28)-(1/(1-$B$9)+Assumptions!$G$47)*(MAX(Assumptions!$C$11*$A28,Assumptions!$C$12/1000)+(H$26/$B$7*(1+Assumptions!$C$15)*(1+Assumptions!$C$14)+$B$10)))-$B$11 -> -62962.581
A29: 18 | B29: =$B$4*(($A29/(1+Assumptions!$C$10)-$A29*(Assumptions!$C$13+$B$8))*(1-Assumptions!$C$28)-(1/(1-$B$9)+Assumptions!$G$47)*(MAX(Assumptions!$C$11*$A29,Assumptions!$C$12/1000)+(B$26/$B$7*(1+Assumptions!$C$15)*(1+Assumptions!$C$14)+$B$10)))-$B$11 -> -20133.688 | C29: =$B$4*(($A29/(1+Assumptions!$C$10)-$A29*(Assumptions!$C$13+$B$8))*(1-Assumptions!$C$28)-(1/(1-$B$9)+Assumptions!$G$47)*(MAX(Assumptions!$C$11*$A29,Assumptions!$C$12/1000)+(C$26/$B$7*(1+Assumptions!$C$15)*(1+Assumptions!$C$14)+$B$10)))-$B$11 -> -25974.788 | D29: =$B$4*(($A29/(1+Assumptions!$C$10)-$A29*(Assumptions!$C$13+$B$8))*(1-Assumptions!$C$28)-(1/(1-$B$9)+Assumptions!$G$47)*(MAX(Assumptions!$C$11*$A29,Assumptions!$C$12/1000)+(D$26/$B$7*(1+Assumptions!$C$15)*(1+Assumptions!$C$14)+$B$10)))-$B$11 -> -31815.887 | E29: =$B$4*(($A29/(1+Assumptions!$C$10)-$A29*(Assumptions!$C$13+$B$8))*(1-Assumptions!$C$28)-(1/(1-$B$9)+Assumptions!$G$47)*(MAX(Assumptions!$C$11*$A29,Assumptions!$C$12/1000)+(E$26/$B$7*(1+Assumptions!$C$15)*(1+Assumptions!$C$14)+$B$10)))-$B$11 -> -37656.987 | F29: =$B$4*(($A29/(1+Assumptions!$C$10)-$A29*(Assumptions!$C$13+$B$8))*(1-Assumptions!$C$28)-(1/(1-$B$9)+Assumptions!$G$47)*(MAX(Assumptions!$C$11*$A29,Assumptions!$C$12/1000)+(F$26/$B$7*(1+Assumptions!$C$15)*(1+Assumptions!$C$14)+$B$10)))-$B$11 -> -43498.087 | G29: =$B$4*(($A29/(1+Assumptions!$C$10)-$A29*(Assumptions!$C$13+$B$8))*(1-Assumptions!$C$28)-(1/(1-$B$9)+Assumptions!$G$47)*(MAX(Assumptions!$C$11*$A29,Assumptions!$C$12/1000)+(G$26/$B$7*(1+Assumptions!$C$15)*(1+Assumptions!$C$14)+$B$10)))-$B$11 -> -49339.186 | H29: =$B$4*(($A29/(1+Assumptions!$C$10)-$A29*(Assumptions!$C$13+$B$8))*(1-Assumptions!$C$28)-(1/(1-$B$9)+Assumptions!$G$47)*(MAX(Assumptions!$C$11*$A29,Assumptions!$C$12/1000)+(H$26/$B$7*(1+Assumptions!$C$15)*(1+Assumptions!$C$14)+$B$10)))-$B$11 -> -55180.286
A30: 20 | B30: =$B$4*(($A30/(1+Assumptions!$C$10)-$A30*(Assumptions!$C$13+$B$8))*(1-Assumptions!$C$28)-(1/(1-$B$9)+Assumptions!$G$47)*(MAX(Assumptions!$C$11*$A30,Assumptions!$C$12/1000)+(B$26/$B$7*(1+Assumptions!$C$15)*(1+Assumptions!$C$14)+$B$10)))-$B$11 -> -14945.491 | C30: =$B$4*(($A30/(1+Assumptions!$C$10)-$A30*(Assumptions!$C$13+$B$8))*(1-Assumptions!$C$28)-(1/(1-$B$9)+Assumptions!$G$47)*(MAX(Assumptions!$C$11*$A30,Assumptions!$C$12/1000)+(C$26/$B$7*(1+Assumptions!$C$15)*(1+Assumptions!$C$14)+$B$10)))-$B$11 -> -20786.591 | D30: =$B$4*(($A30/(1+Assumptions!$C$10)-$A30*(Assumptions!$C$13+$B$8))*(1-Assumptions!$C$28)-(1/(1-$B$9)+Assumptions!$G$47)*(MAX(Assumptions!$C$11*$A30,Assumptions!$C$12/1000)+(D$26/$B$7*(1+Assumptions!$C$15)*(1+Assumptions!$C$14)+$B$10)))-$B$11 -> -26627.691 | E30: =$B$4*(($A30/(1+Assumptions!$C$10)-$A30*(Assumptions!$C$13+$B$8))*(1-Assumptions!$C$28)-(1/(1-$B$9)+Assumptions!$G$47)*(MAX(Assumptions!$C$11*$A30,Assumptions!$C$12/1000)+(E$26/$B$7*(1+Assumptions!$C$15)*(1+Assumptions!$C$14)+$B$10)))-$B$11 -> -32468.79 | F30: =$B$4*(($A30/(1+Assumptions!$C$10)-$A30*(Assumptions!$C$13+$B$8))*(1-Assumptions!$C$28)-(1/(1-$B$9)+Assumptions!$G$47)*(MAX(Assumptions!$C$11*$A30,Assumptions!$C$12/1000)+(F$26/$B$7*(1+Assumptions!$C$15)*(1+Assumptions!$C$14)+$B$10)))-$B$11 -> -38309.89 | G30: =$B$4*(($A30/(1+Assumptions!$C$10)-$A30*(Assumptions!$C$13+$B$8))*(1-Assumptions!$C$28)-(1/(1-$B$9)+Assumptions!$G$47)*(MAX(Assumptions!$C$11*$A30,Assumptions!$C$12/1000)+(G$26/$B$7*(1+Assumptions!$C$15)*(1+Assumptions!$C$14)+$B$10)))-$B$11 -> -44150.99 | H30: =$B$4*(($A30/(1+Assumptions!$C$10)-$A30*(Assumptions!$C$13+$B$8))*(1-Assumptions!$C$28)-(1/(1-$B$9)+Assumptions!$G$47)*(MAX(Assumptions!$C$11*$A30,Assumptions!$C$12/1000)+(H$26/$B$7*(1+Assumptions!$C$15)*(1+Assumptions!$C$14)+$B$10)))-$B$11 -> -49992.089
A31: 25 | B31: =$B$4*(($A31/(1+Assumptions!$C$10)-$A31*(Assumptions!$C$13+$B$8))*(1-Assumptions!$C$28)-(1/(1-$B$9)+Assumptions!$G$47)*(MAX(Assumptions!$C$11*$A31,Assumptions!$C$12/1000)+(B$26/$B$7*(1+Assumptions!$C$15)*(1+Assumptions!$C$14)+$B$10)))-$B$11 -> -1974.9993 | C31: =$B$4*(($A31/(1+Assumptions!$C$10)-$A31*(Assumptions!$C$13+$B$8))*(1-Assumptions!$C$28)-(1/(1-$B$9)+Assumptions!$G$47)*(MAX(Assumptions!$C$11*$A31,Assumptions!$C$12/1000)+(C$26/$B$7*(1+Assumptions!$C$15)*(1+Assumptions!$C$14)+$B$10)))-$B$11 -> -7816.099 | D31: =$B$4*(($A31/(1+Assumptions!$C$10)-$A31*(Assumptions!$C$13+$B$8))*(1-Assumptions!$C$28)-(1/(1-$B$9)+Assumptions!$G$47)*(MAX(Assumptions!$C$11*$A31,Assumptions!$C$12/1000)+(D$26/$B$7*(1+Assumptions!$C$15)*(1+Assumptions!$C$14)+$B$10)))-$B$11 -> -13657.199 | E31: =$B$4*(($A31/(1+Assumptions!$C$10)-$A31*(Assumptions!$C$13+$B$8))*(1-Assumptions!$C$28)-(1/(1-$B$9)+Assumptions!$G$47)*(MAX(Assumptions!$C$11*$A31,Assumptions!$C$12/1000)+(E$26/$B$7*(1+Assumptions!$C$15)*(1+Assumptions!$C$14)+$B$10)))-$B$11 -> -19498.298 | F31: =$B$4*(($A31/(1+Assumptions!$C$10)-$A31*(Assumptions!$C$13+$B$8))*(1-Assumptions!$C$28)-(1/(1-$B$9)+Assumptions!$G$47)*(MAX(Assumptions!$C$11*$A31,Assumptions!$C$12/1000)+(F$26/$B$7*(1+Assumptions!$C$15)*(1+Assumptions!$C$14)+$B$10)))-$B$11 -> -25339.398 | G31: =$B$4*(($A31/(1+Assumptions!$C$10)-$A31*(Assumptions!$C$13+$B$8))*(1-Assumptions!$C$28)-(1/(1-$B$9)+Assumptions!$G$47)*(MAX(Assumptions!$C$11*$A31,Assumptions!$C$12/1000)+(G$26/$B$7*(1+Assumptions!$C$15)*(1+Assumptions!$C$14)+$B$10)))-$B$11 -> -31180.498 | H31: =$B$4*(($A31/(1+Assumptions!$C$10)-$A31*(Assumptions!$C$13+$B$8))*(1-Assumptions!$C$28)-(1/(1-$B$9)+Assumptions!$G$47)*(MAX(Assumptions!$C$11*$A31,Assumptions!$C$12/1000)+(H$26/$B$7*(1+Assumptions!$C$15)*(1+Assumptions!$C$14)+$B$10)))-$B$11 -> -37021.597
A32: 30 | B32: =$B$4*(($A32/(1+Assumptions!$C$10)-$A32*(Assumptions!$C$13+$B$8))*(1-Assumptions!$C$28)-(1/(1-$B$9)+Assumptions!$G$47)*(MAX(Assumptions!$C$11*$A32,Assumptions!$C$12/1000)+(B$26/$B$7*(1+Assumptions!$C$15)*(1+Assumptions!$C$14)+$B$10)))-$B$11 -> 10995.493 | C32: =$B$4*(($A32/(1+Assumptions!$C$10)-$A32*(Assumptions!$C$13+$B$8))*(1-Assumptions!$C$28)-(1/(1-$B$9)+Assumptions!$G$47)*(MAX(Assumptions!$C$11*$A32,Assumptions!$C$12/1000)+(C$26/$B$7*(1+Assumptions!$C$15)*(1+Assumptions!$C$14)+$B$10)))-$B$11 -> 5154.3931 | D32: =$B$4*(($A32/(1+Assumptions!$C$10)-$A32*(Assumptions!$C$13+$B$8))*(1-Assumptions!$C$28)-(1/(1-$B$9)+Assumptions!$G$47)*(MAX(Assumptions!$C$11*$A32,Assumptions!$C$12/1000)+(D$26/$B$7*(1+Assumptions!$C$15)*(1+Assumptions!$C$14)+$B$10)))-$B$11 -> -686.70652 | E32: =$B$4*(($A32/(1+Assumptions!$C$10)-$A32*(Assumptions!$C$13+$B$8))*(1-Assumptions!$C$28)-(1/(1-$B$9)+Assumptions!$G$47)*(MAX(Assumptions!$C$11*$A32,Assumptions!$C$12/1000)+(E$26/$B$7*(1+Assumptions!$C$15)*(1+Assumptions!$C$14)+$B$10)))-$B$11 -> -6527.8062 | F32: =$B$4*(($A32/(1+Assumptions!$C$10)-$A32*(Assumptions!$C$13+$B$8))*(1-Assumptions!$C$28)-(1/(1-$B$9)+Assumptions!$G$47)*(MAX(Assumptions!$C$11*$A32,Assumptions!$C$12/1000)+(F$26/$B$7*(1+Assumptions!$C$15)*(1+Assumptions!$C$14)+$B$10)))-$B$11 -> -12368.906 | G32: =$B$4*(($A32/(1+Assumptions!$C$10)-$A32*(Assumptions!$C$13+$B$8))*(1-Assumptions!$C$28)-(1/(1-$B$9)+Assumptions!$G$47)*(MAX(Assumptions!$C$11*$A32,Assumptions!$C$12/1000)+(G$26/$B$7*(1+Assumptions!$C$15)*(1+Assumptions!$C$14)+$B$10)))-$B$11 -> -18210.005 | H32: =$B$4*(($A32/(1+Assumptions!$C$10)-$A32*(Assumptions!$C$13+$B$8))*(1-Assumptions!$C$28)-(1/(1-$B$9)+Assumptions!$G$47)*(MAX(Assumptions!$C$11*$A32,Assumptions!$C$12/1000)+(H$26/$B$7*(1+Assumptions!$C$15)*(1+Assumptions!$C$14)+$B$10)))-$B$11 -> -24051.105
A33: 35 | B33: =$B$4*(($A33/(1+Assumptions!$C$10)-$A33*(Assumptions!$C$13+$B$8))*(1-Assumptions!$C$28)-(1/(1-$B$9)+Assumptions!$G$47)*(MAX(Assumptions!$C$11*$A33,Assumptions!$C$12/1000)+(B$26/$B$7*(1+Assumptions!$C$15)*(1+Assumptions!$C$14)+$B$10)))-$B$11 -> 23965.985 | C33: =$B$4*(($A33/(1+Assumptions!$C$10)-$A33*(Assumptions!$C$13+$B$8))*(1-Assumptions!$C$28)-(1/(1-$B$9)+Assumptions!$G$47)*(MAX(Assumptions!$C$11*$A33,Assumptions!$C$12/1000)+(C$26/$B$7*(1+Assumptions!$C$15)*(1+Assumptions!$C$14)+$B$10)))-$B$11 -> 18124.885 | D33: =$B$4*(($A33/(1+Assumptions!$C$10)-$A33*(Assumptions!$C$13+$B$8))*(1-Assumptions!$C$28)-(1/(1-$B$9)+Assumptions!$G$47)*(MAX(Assumptions!$C$11*$A33,Assumptions!$C$12/1000)+(D$26/$B$7*(1+Assumptions!$C$15)*(1+Assumptions!$C$14)+$B$10)))-$B$11 -> 12283.786 | E33: =$B$4*(($A33/(1+Assumptions!$C$10)-$A33*(Assumptions!$C$13+$B$8))*(1-Assumptions!$C$28)-(1/(1-$B$9)+Assumptions!$G$47)*(MAX(Assumptions!$C$11*$A33,Assumptions!$C$12/1000)+(E$26/$B$7*(1+Assumptions!$C$15)*(1+Assumptions!$C$14)+$B$10)))-$B$11 -> 6442.6859 | F33: =$B$4*(($A33/(1+Assumptions!$C$10)-$A33*(Assumptions!$C$13+$B$8))*(1-Assumptions!$C$28)-(1/(1-$B$9)+Assumptions!$G$47)*(MAX(Assumptions!$C$11*$A33,Assumptions!$C$12/1000)+(F$26/$B$7*(1+Assumptions!$C$15)*(1+Assumptions!$C$14)+$B$10)))-$B$11 -> 601.58628 | G33: =$B$4*(($A33/(1+Assumptions!$C$10)-$A33*(Assumptions!$C$13+$B$8))*(1-Assumptions!$C$28)-(1/(1-$B$9)+Assumptions!$G$47)*(MAX(Assumptions!$C$11*$A33,Assumptions!$C$12/1000)+(G$26/$B$7*(1+Assumptions!$C$15)*(1+Assumptions!$C$14)+$B$10)))-$B$11 -> -5239.5134 | H33: =$B$4*(($A33/(1+Assumptions!$C$10)-$A33*(Assumptions!$C$13+$B$8))*(1-Assumptions!$C$28)-(1/(1-$B$9)+Assumptions!$G$47)*(MAX(Assumptions!$C$11*$A33,Assumptions!$C$12/1000)+(H$26/$B$7*(1+Assumptions!$C$15)*(1+Assumptions!$C$14)+$B$10)))-$B$11 -> -11080.613
A35: Tabla bidimensional: EBITDA 2030 según volumen (filas) y tarifa del distribuidor (columnas)
A36: Unidades \ tarifa | B36: 3% | C36: 4% | D36: 5% | E36: 6% | F36: 8% | G36: 10%
B37: 0.03 | C37: 0.04 | D37: 0.05 | E37: 0.06 | F37: 0.08 | G37: 0.1
A38: 2000 | B38: =$A38*(($B$5/(1+Assumptions!$C$10)-$B$5*(Assumptions!$C$13+B$37))*(1-Assumptions!$C$28)-(1/(1-$B$9)+Assumptions!$G$47)*(MAX(Assumptions!$C$11*$B$5,Assumptions!$C$12/1000)+($B$6/$B$7*(1+Assumptions!$C$15)*(1+Assumptions!$C$14)+$B$10)))-$B$11 -> -20534.519 | C38: =$A38*(($B$5/(1+Assumptions!$C$10)-$B$5*(Assumptions!$C$13+C$37))*(1-Assumptions!$C$28)-(1/(1-$B$9)+Assumptions!$G$47)*(MAX(Assumptions!$C$11*$B$5,Assumptions!$C$12/1000)+($B$6/$B$7*(1+Assumptions!$C$15)*(1+Assumptions!$C$14)+$B$10)))-$B$11 -> -21014.519 | D38: =$A38*(($B$5/(1+Assumptions!$C$10)-$B$5*(Assumptions!$C$13+D$37))*(1-Assumptions!$C$28)-(1/(1-$B$9)+Assumptions!$G$47)*(MAX(Assumptions!$C$11*$B$5,Assumptions!$C$12/1000)+($B$6/$B$7*(1+Assumptions!$C$15)*(1+Assumptions!$C$14)+$B$10)))-$B$11 -> -21494.519 | E38: =$A38*(($B$5/(1+Assumptions!$C$10)-$B$5*(Assumptions!$C$13+E$37))*(1-Assumptions!$C$28)-(1/(1-$B$9)+Assumptions!$G$47)*(MAX(Assumptions!$C$11*$B$5,Assumptions!$C$12/1000)+($B$6/$B$7*(1+Assumptions!$C$15)*(1+Assumptions!$C$14)+$B$10)))-$B$11 -> -21974.519 | F38: =$A38*(($B$5/(1+Assumptions!$C$10)-$B$5*(Assumptions!$C$13+F$37))*(1-Assumptions!$C$28)-(1/(1-$B$9)+Assumptions!$G$47)*(MAX(Assumptions!$C$11*$B$5,Assumptions!$C$12/1000)+($B$6/$B$7*(1+Assumptions!$C$15)*(1+Assumptions!$C$14)+$B$10)))-$B$11 -> -22934.519 | G38: =$A38*(($B$5/(1+Assumptions!$C$10)-$B$5*(Assumptions!$C$13+G$37))*(1-Assumptions!$C$28)-(1/(1-$B$9)+Assumptions!$G$47)*(MAX(Assumptions!$C$11*$B$5,Assumptions!$C$12/1000)+($B$6/$B$7*(1+Assumptions!$C$15)*(1+Assumptions!$C$14)+$B$10)))-$B$11 -> -23894.519
A39: 4000 | B39: =$A39*(($B$5/(1+Assumptions!$C$10)-$B$5*(Assumptions!$C$13+B$37))*(1-Assumptions!$C$28)-(1/(1-$B$9)+Assumptions!$G$47)*(MAX(Assumptions!$C$11*$B$5,Assumptions!$C$12/1000)+($B$6/$B$7*(1+Assumptions!$C$15)*(1+Assumptions!$C$14)+$B$10)))-$B$11 -> -16079.038 | C39: =$A39*(($B$5/(1+Assumptions!$C$10)-$B$5*(Assumptions!$C$13+C$37))*(1-Assumptions!$C$28)-(1/(1-$B$9)+Assumptions!$G$47)*(MAX(Assumptions!$C$11*$B$5,Assumptions!$C$12/1000)+($B$6/$B$7*(1+Assumptions!$C$15)*(1+Assumptions!$C$14)+$B$10)))-$B$11 -> -17039.038 | D39: =$A39*(($B$5/(1+Assumptions!$C$10)-$B$5*(Assumptions!$C$13+D$37))*(1-Assumptions!$C$28)-(1/(1-$B$9)+Assumptions!$G$47)*(MAX(Assumptions!$C$11*$B$5,Assumptions!$C$12/1000)+($B$6/$B$7*(1+Assumptions!$C$15)*(1+Assumptions!$C$14)+$B$10)))-$B$11 -> -17999.038 | E39: =$A39*(($B$5/(1+Assumptions!$C$10)-$B$5*(Assumptions!$C$13+E$37))*(1-Assumptions!$C$28)-(1/(1-$B$9)+Assumptions!$G$47)*(MAX(Assumptions!$C$11*$B$5,Assumptions!$C$12/1000)+($B$6/$B$7*(1+Assumptions!$C$15)*(1+Assumptions!$C$14)+$B$10)))-$B$11 -> -18959.038 | F39: =$A39*(($B$5/(1+Assumptions!$C$10)-$B$5*(Assumptions!$C$13+F$37))*(1-Assumptions!$C$28)-(1/(1-$B$9)+Assumptions!$G$47)*(MAX(Assumptions!$C$11*$B$5,Assumptions!$C$12/1000)+($B$6/$B$7*(1+Assumptions!$C$15)*(1+Assumptions!$C$14)+$B$10)))-$B$11 -> -20879.038 | G39: =$A39*(($B$5/(1+Assumptions!$C$10)-$B$5*(Assumptions!$C$13+G$37))*(1-Assumptions!$C$28)-(1/(1-$B$9)+Assumptions!$G$47)*(MAX(Assumptions!$C$11*$B$5,Assumptions!$C$12/1000)+($B$6/$B$7*(1+Assumptions!$C$15)*(1+Assumptions!$C$14)+$B$10)))-$B$11 -> -22799.038
A40: 6000 | B40: =$A40*(($B$5/(1+Assumptions!$C$10)-$B$5*(Assumptions!$C$13+B$37))*(1-Assumptions!$C$28)-(1/(1-$B$9)+Assumptions!$G$47)*(MAX(Assumptions!$C$11*$B$5,Assumptions!$C$12/1000)+($B$6/$B$7*(1+Assumptions!$C$15)*(1+Assumptions!$C$14)+$B$10)))-$B$11 -> -11623.556 | C40: =$A40*(($B$5/(1+Assumptions!$C$10)-$B$5*(Assumptions!$C$13+C$37))*(1-Assumptions!$C$28)-(1/(1-$B$9)+Assumptions!$G$47)*(MAX(Assumptions!$C$11*$B$5,Assumptions!$C$12/1000)+($B$6/$B$7*(1+Assumptions!$C$15)*(1+Assumptions!$C$14)+$B$10)))-$B$11 -> -13063.556 | D40: =$A40*(($B$5/(1+Assumptions!$C$10)-$B$5*(Assumptions!$C$13+D$37))*(1-Assumptions!$C$28)-(1/(1-$B$9)+Assumptions!$G$47)*(MAX(Assumptions!$C$11*$B$5,Assumptions!$C$12/1000)+($B$6/$B$7*(1+Assumptions!$C$15)*(1+Assumptions!$C$14)+$B$10)))-$B$11 -> -14503.556 | E40: =$A40*(($B$5/(1+Assumptions!$C$10)-$B$5*(Assumptions!$C$13+E$37))*(1-Assumptions!$C$28)-(1/(1-$B$9)+Assumptions!$G$47)*(MAX(Assumptions!$C$11*$B$5,Assumptions!$C$12/1000)+($B$6/$B$7*(1+Assumptions!$C$15)*(1+Assumptions!$C$14)+$B$10)))-$B$11 -> -15943.556 | F40: =$A40*(($B$5/(1+Assumptions!$C$10)-$B$5*(Assumptions!$C$13+F$37))*(1-Assumptions!$C$28)-(1/(1-$B$9)+Assumptions!$G$47)*(MAX(Assumptions!$C$11*$B$5,Assumptions!$C$12/1000)+($B$6/$B$7*(1+Assumptions!$C$15)*(1+Assumptions!$C$14)+$B$10)))-$B$11 -> -18823.556 | G40: =$A40*(($B$5/(1+Assumptions!$C$10)-$B$5*(Assumptions!$C$13+G$37))*(1-Assumptions!$C$28)-(1/(1-$B$9)+Assumptions!$G$47)*(MAX(Assumptions!$C$11*$B$5,Assumptions!$C$12/1000)+($B$6/$B$7*(1+Assumptions!$C$15)*(1+Assumptions!$C$14)+$B$10)))-$B$11 -> -21703.556
A41: 8000 | B41: =$A41*(($B$5/(1+Assumptions!$C$10)-$B$5*(Assumptions!$C$13+B$37))*(1-Assumptions!$C$28)-(1/(1-$B$9)+Assumptions!$G$47)*(MAX(Assumptions!$C$11*$B$5,Assumptions!$C$12/1000)+($B$6/$B$7*(1+Assumptions!$C$15)*(1+Assumptions!$C$14)+$B$10)))-$B$11 -> -7168.0752 | C41: =$A41*(($B$5/(1+Assumptions!$C$10)-$B$5*(Assumptions!$C$13+C$37))*(1-Assumptions!$C$28)-(1/(1-$B$9)+Assumptions!$G$47)*(MAX(Assumptions!$C$11*$B$5,Assumptions!$C$12/1000)+($B$6/$B$7*(1+Assumptions!$C$15)*(1+Assumptions!$C$14)+$B$10)))-$B$11 -> -9088.0752 | D41: =$A41*(($B$5/(1+Assumptions!$C$10)-$B$5*(Assumptions!$C$13+D$37))*(1-Assumptions!$C$28)-(1/(1-$B$9)+Assumptions!$G$47)*(MAX(Assumptions!$C$11*$B$5,Assumptions!$C$12/1000)+($B$6/$B$7*(1+Assumptions!$C$15)*(1+Assumptions!$C$14)+$B$10)))-$B$11 -> -11008.075 | E41: =$A41*(($B$5/(1+Assumptions!$C$10)-$B$5*(Assumptions!$C$13+E$37))*(1-Assumptions!$C$28)-(1/(1-$B$9)+Assumptions!$G$47)*(MAX(Assumptions!$C$11*$B$5,Assumptions!$C$12/1000)+($B$6/$B$7*(1+Assumptions!$C$15)*(1+Assumptions!$C$14)+$B$10)))-$B$11 -> -12928.075 | F41: =$A41*(($B$5/(1+Assumptions!$C$10)-$B$5*(Assumptions!$C$13+F$37))*(1-Assumptions!$C$28)-(1/(1-$B$9)+Assumptions!$G$47)*(MAX(Assumptions!$C$11*$B$5,Assumptions!$C$12/1000)+($B$6/$B$7*(1+Assumptions!$C$15)*(1+Assumptions!$C$14)+$B$10)))-$B$11 -> -16768.075 | G41: =$A41*(($B$5/(1+Assumptions!$C$10)-$B$5*(Assumptions!$C$13+G$37))*(1-Assumptions!$C$28)-(1/(1-$B$9)+Assumptions!$G$47)*(MAX(Assumptions!$C$11*$B$5,Assumptions!$C$12/1000)+($B$6/$B$7*(1+Assumptions!$C$15)*(1+Assumptions!$C$14)+$B$10)))-$B$11 -> -20608.075
A42: 10000 | B42: =$A42*(($B$5/(1+Assumptions!$C$10)-$B$5*(Assumptions!$C$13+B$37))*(1-Assumptions!$C$28)-(1/(1-$B$9)+Assumptions!$G$47)*(MAX(Assumptions!$C$11*$B$5,Assumptions!$C$12/1000)+($B$6/$B$7*(1+Assumptions!$C$15)*(1+Assumptions!$C$14)+$B$10)))-$B$11 -> -2712.594 | C42: =$A42*(($B$5/(1+Assumptions!$C$10)-$B$5*(Assumptions!$C$13+C$37))*(1-Assumptions!$C$28)-(1/(1-$B$9)+Assumptions!$G$47)*(MAX(Assumptions!$C$11*$B$5,Assumptions!$C$12/1000)+($B$6/$B$7*(1+Assumptions!$C$15)*(1+Assumptions!$C$14)+$B$10)))-$B$11 -> -5112.594 | D42: =$A42*(($B$5/(1+Assumptions!$C$10)-$B$5*(Assumptions!$C$13+D$37))*(1-Assumptions!$C$28)-(1/(1-$B$9)+Assumptions!$G$47)*(MAX(Assumptions!$C$11*$B$5,Assumptions!$C$12/1000)+($B$6/$B$7*(1+Assumptions!$C$15)*(1+Assumptions!$C$14)+$B$10)))-$B$11 -> -7512.594 | E42: =$A42*(($B$5/(1+Assumptions!$C$10)-$B$5*(Assumptions!$C$13+E$37))*(1-Assumptions!$C$28)-(1/(1-$B$9)+Assumptions!$G$47)*(MAX(Assumptions!$C$11*$B$5,Assumptions!$C$12/1000)+($B$6/$B$7*(1+Assumptions!$C$15)*(1+Assumptions!$C$14)+$B$10)))-$B$11 -> -9912.594 | F42: =$A42*(($B$5/(1+Assumptions!$C$10)-$B$5*(Assumptions!$C$13+F$37))*(1-Assumptions!$C$28)-(1/(1-$B$9)+Assumptions!$G$47)*(MAX(Assumptions!$C$11*$B$5,Assumptions!$C$12/1000)+($B$6/$B$7*(1+Assumptions!$C$15)*(1+Assumptions!$C$14)+$B$10)))-$B$11 -> -14712.594 | G42: =$A42*(($B$5/(1+Assumptions!$C$10)-$B$5*(Assumptions!$C$13+G$37))*(1-Assumptions!$C$28)-(1/(1-$B$9)+Assumptions!$G$47)*(MAX(Assumptions!$C$11*$B$5,Assumptions!$C$12/1000)+($B$6/$B$7*(1+Assumptions!$C$15)*(1+Assumptions!$C$14)+$B$10)))-$B$11 -> -19512.594
A43: 15000 | B43: =$A43*(($B$5/(1+Assumptions!$C$10)-$B$5*(Assumptions!$C$13+B$37))*(1-Assumptions!$C$28)-(1/(1-$B$9)+Assumptions!$G$47)*(MAX(Assumptions!$C$11*$B$5,Assumptions!$C$12/1000)+($B$6/$B$7*(1+Assumptions!$C$15)*(1+Assumptions!$C$14)+$B$10)))-$B$11 -> 8426.109 | C43: =$A43*(($B$5/(1+Assumptions!$C$10)-$B$5*(Assumptions!$C$13+C$37))*(1-Assumptions!$C$28)-(1/(1-$B$9)+Assumptions!$G$47)*(MAX(Assumptions!$C$11*$B$5,Assumptions!$C$12/1000)+($B$6/$B$7*(1+Assumptions!$C$15)*(1+Assumptions!$C$14)+$B$10)))-$B$11 -> 4826.109 | D43: =$A43*(($B$5/(1+Assumptions!$C$10)-$B$5*(Assumptions!$C$13+D$37))*(1-Assumptions!$C$28)-(1/(1-$B$9)+Assumptions!$G$47)*(MAX(Assumptions!$C$11*$B$5,Assumptions!$C$12/1000)+($B$6/$B$7*(1+Assumptions!$C$15)*(1+Assumptions!$C$14)+$B$10)))-$B$11 -> 1226.109 | E43: =$A43*(($B$5/(1+Assumptions!$C$10)-$B$5*(Assumptions!$C$13+E$37))*(1-Assumptions!$C$28)-(1/(1-$B$9)+Assumptions!$G$47)*(MAX(Assumptions!$C$11*$B$5,Assumptions!$C$12/1000)+($B$6/$B$7*(1+Assumptions!$C$15)*(1+Assumptions!$C$14)+$B$10)))-$B$11 -> -2373.891 | F43: =$A43*(($B$5/(1+Assumptions!$C$10)-$B$5*(Assumptions!$C$13+F$37))*(1-Assumptions!$C$28)-(1/(1-$B$9)+Assumptions!$G$47)*(MAX(Assumptions!$C$11*$B$5,Assumptions!$C$12/1000)+($B$6/$B$7*(1+Assumptions!$C$15)*(1+Assumptions!$C$14)+$B$10)))-$B$11 -> -9573.891 | G43: =$A43*(($B$5/(1+Assumptions!$C$10)-$B$5*(Assumptions!$C$13+G$37))*(1-Assumptions!$C$28)-(1/(1-$B$9)+Assumptions!$G$47)*(MAX(Assumptions!$C$11*$B$5,Assumptions!$C$12/1000)+($B$6/$B$7*(1+Assumptions!$C$15)*(1+Assumptions!$C$14)+$B$10)))-$B$11 -> -16773.891
A44: 20000 | B44: =$A44*(($B$5/(1+Assumptions!$C$10)-$B$5*(Assumptions!$C$13+B$37))*(1-Assumptions!$C$28)-(1/(1-$B$9)+Assumptions!$G$47)*(MAX(Assumptions!$C$11*$B$5,Assumptions!$C$12/1000)+($B$6/$B$7*(1+Assumptions!$C$15)*(1+Assumptions!$C$14)+$B$10)))-$B$11 -> 19564.812 | C44: =$A44*(($B$5/(1+Assumptions!$C$10)-$B$5*(Assumptions!$C$13+C$37))*(1-Assumptions!$C$28)-(1/(1-$B$9)+Assumptions!$G$47)*(MAX(Assumptions!$C$11*$B$5,Assumptions!$C$12/1000)+($B$6/$B$7*(1+Assumptions!$C$15)*(1+Assumptions!$C$14)+$B$10)))-$B$11 -> 14764.812 | D44: =$A44*(($B$5/(1+Assumptions!$C$10)-$B$5*(Assumptions!$C$13+D$37))*(1-Assumptions!$C$28)-(1/(1-$B$9)+Assumptions!$G$47)*(MAX(Assumptions!$C$11*$B$5,Assumptions!$C$12/1000)+($B$6/$B$7*(1+Assumptions!$C$15)*(1+Assumptions!$C$14)+$B$10)))-$B$11 -> 9964.812 | E44: =$A44*(($B$5/(1+Assumptions!$C$10)-$B$5*(Assumptions!$C$13+E$37))*(1-Assumptions!$C$28)-(1/(1-$B$9)+Assumptions!$G$47)*(MAX(Assumptions!$C$11*$B$5,Assumptions!$C$12/1000)+($B$6/$B$7*(1+Assumptions!$C$15)*(1+Assumptions!$C$14)+$B$10)))-$B$11 -> 5164.812 | F44: =$A44*(($B$5/(1+Assumptions!$C$10)-$B$5*(Assumptions!$C$13+F$37))*(1-Assumptions!$C$28)-(1/(1-$B$9)+Assumptions!$G$47)*(MAX(Assumptions!$C$11*$B$5,Assumptions!$C$12/1000)+($B$6/$B$7*(1+Assumptions!$C$15)*(1+Assumptions!$C$14)+$B$10)))-$B$11 -> -4435.188 | G44: =$A44*(($B$5/(1+Assumptions!$C$10)-$B$5*(Assumptions!$C$13+G$37))*(1-Assumptions!$C$28)-(1/(1-$B$9)+Assumptions!$G$47)*(MAX(Assumptions!$C$11*$B$5,Assumptions!$C$12/1000)+($B$6/$B$7*(1+Assumptions!$C$15)*(1+Assumptions!$C$14)+$B$10)))-$B$11 -> -14035.188
A46: Retrasos de suministro y coste de financiación (aproximación)
A47: Gastos fijos mensuales 2028 | B47: =INDEX(Engine!$C$40:$Y$40,1,(Assumptions!$C$4-1)*6+2)/12 -> 1897.5
A48: Retraso adicional (meses) | B48: Caja adicional necesaria (€) | C48: Coste financiero anual al 5% | D48: al 7% | E48: al 10% | F48: al 12%
A49: 0 | B49: =A49*$B$47 -> 0 | C49: =(INDEX(Engine!$C$75:$Y$75,1,(Assumptions!$C$4-1)*6+2)+B49)*0.05 -> 2522.7864 | D49: =(INDEX(Engine!$C$75:$Y$75,1,(Assumptions!$C$4-1)*6+2)+B49)*0.07 -> 3531.901 | E49: =(INDEX(Engine!$C$75:$Y$75,1,(Assumptions!$C$4-1)*6+2)+B49)*0.1 -> 5045.5729 | F49: =(INDEX(Engine!$C$75:$Y$75,1,(Assumptions!$C$4-1)*6+2)+B49)*0.12 -> 6054.6874
A50: 3 | B50: =A50*$B$47 -> 5692.5 | C50: =(INDEX(Engine!$C$75:$Y$75,1,(Assumptions!$C$4-1)*6+2)+B50)*0.05 -> 2807.4114 | D50: =(INDEX(Engine!$C$75:$Y$75,1,(Assumptions!$C$4-1)*6+2)+B50)*0.07 -> 3930.376 | E50: =(INDEX(Engine!$C$75:$Y$75,1,(Assumptions!$C$4-1)*6+2)+B50)*0.1 -> 5614.8229 | F50: =(INDEX(Engine!$C$75:$Y$75,1,(Assumptions!$C$4-1)*6+2)+B50)*0.12 -> 6737.7874
A51: 6 | B51: =A51*$B$47 -> 11385 | C51: =(INDEX(Engine!$C$75:$Y$75,1,(Assumptions!$C$4-1)*6+2)+B51)*0.05 -> 3092.0364 | D51: =(INDEX(Engine!$C$75:$Y$75,1,(Assumptions!$C$4-1)*6+2)+B51)*0.07 -> 4328.851 | E51: =(INDEX(Engine!$C$75:$Y$75,1,(Assumptions!$C$4-1)*6+2)+B51)*0.1 -> 6184.0729 | F51: =(INDEX(Engine!$C$75:$Y$75,1,(Assumptions!$C$4-1)*6+2)+B51)*0.12 -> 7420.8874
A52: 9 | B52: =A52*$B$47 -> 17077.5 | C52: =(INDEX(Engine!$C$75:$Y$75,1,(Assumptions!$C$4-1)*6+2)+B52)*0.05 -> 3376.6614 | D52: =(INDEX(Engine!$C$75:$Y$75,1,(Assumptions!$C$4-1)*6+2)+B52)*0.07 -> 4727.326 | E52: =(INDEX(Engine!$C$75:$Y$75,1,(Assumptions!$C$4-1)*6+2)+B52)*0.1 -> 6753.3229 | F52: =(INDEX(Engine!$C$75:$Y$75,1,(Assumptions!$C$4-1)*6+2)+B52)*0.12 -> 8103.9874
A53: 12 | B53: =A53*$B$47 -> 22770 | C53: =(INDEX(Engine!$C$75:$Y$75,1,(Assumptions!$C$4-1)*6+2)+B53)*0.05 -> 3661.2864 | D53: =(INDEX(Engine!$C$75:$Y$75,1,(Assumptions!$C$4-1)*6+2)+B53)*0.07 -> 5125.801 | E53: =(INDEX(Engine!$C$75:$Y$75,1,(Assumptions!$C$4-1)*6+2)+B53)*0.1 -> 7322.5729 | F53: =(INDEX(Engine!$C$75:$Y$75,1,(Assumptions!$C$4-1)*6+2)+B53)*0.12 -> 8787.0874
A55: Lectura: cada mes de retraso consume gastos fijos sin ingresos; el anticipo pagado a Cuba ya está inmovilizado. La columna de coste financiero incluye la deuda del escenario en 2028.

Sheet Investment Returns
A1: Rentabilidad de la inversión (escenario seleccionado)
A2: FCF del proyecto sin financiación; valor terminal = EBITDA 2031 × múltiplo (si positivo). Descuento a fin de año.
A3: ="Escenario: "&Assumptions!$D$4 -> Escenario: Base
A5: Concepto | B5: 2027 | C5: 2028 | D5: 2029 | E5: 2030 | F5: 2031
A6: EBITDA | B6: =INDEX(Engine!$C$41:$Y$41,1,(Assumptions!$C$4-1)*6+1) -> -27190 | C6: =INDEX(Engine!$C$41:$Y$41,1,(Assumptions!$C$4-1)*6+2) -> -20174.519 | D6: =INDEX(Engine!$C$41:$Y$41,1,(Assumptions!$C$4-1)*6+3) -> -17112.908 | E6: =INDEX(Engine!$C$41:$Y$41,1,(Assumptions!$C$4-1)*6+4) -> -16251.297 | F6: =INDEX(Engine!$C$41:$Y$41,1,(Assumptions!$C$4-1)*6+5) -> -13849.686
A7: (-) Impuestos | B7: =INDEX(Engine!$C$53:$Y$53,1,(Assumptions!$C$4-1)*6+1) -> 0 | C7: =INDEX(Engine!$C$53:$Y$53,1,(Assumptions!$C$4-1)*6+2) -> 0 | D7: =INDEX(Engine!$C$53:$Y$53,1,(Assumptions!$C$4-1)*6+3) -> 0 | E7: =INDEX(Engine!$C$53:$Y$53,1,(Assumptions!$C$4-1)*6+4) -> 0 | F7: =INDEX(Engine!$C$53:$Y$53,1,(Assumptions!$C$4-1)*6+5) -> 0
A8: (-) Variación circulante | B8: =INDEX(Engine!$C$68:$Y$68,1,(Assumptions!$C$4-1)*6+1) -> 16687.568 | C8: =INDEX(Engine!$C$68:$Y$68,1,(Assumptions!$C$4-1)*6+2) -> 17572.212 | D8: =INDEX(Engine!$C$68:$Y$68,1,(Assumptions!$C$4-1)*6+3) -> 16323.893 | E8: =INDEX(Engine!$C$68:$Y$68,1,(Assumptions!$C$4-1)*6+4) -> 15030.979 | F8: =INDEX(Engine!$C$68:$Y$68,1,(Assumptions!$C$4-1)*6+5) -> 2967.4232
A9: (-) CAPEX | B9: =INDEX(Engine!$C$42:$Y$42,1,(Assumptions!$C$4-1)*6+1) -> 13000 | C9: =INDEX(Engine!$C$42:$Y$42,1,(Assumptions!$C$4-1)*6+2) -> 0 | D9: =INDEX(Engine!$C$42:$Y$42,1,(Assumptions!$C$4-1)*6+3) -> 3000 | E9: =INDEX(Engine!$C$42:$Y$42,1,(Assumptions!$C$4-1)*6+4) -> 0 | F9: =INDEX(Engine!$C$42:$Y$42,1,(Assumptions!$C$4-1)*6+5) -> 0
A10: FCF del proyecto | B10: =INDEX(Engine!$C$87:$Y$87,1,(Assumptions!$C$4-1)*6+1) -> -56877.568 | C10: =INDEX(Engine!$C$87:$Y$87,1,(Assumptions!$C$4-1)*6+2) -> -37746.731 | D10: =INDEX(Engine!$C$87:$Y$87,1,(Assumptions!$C$4-1)*6+3) -> -36436.801 | E10: =INDEX(Engine!$C$87:$Y$87,1,(Assumptions!$C$4-1)*6+4) -> -31282.276 | F10: =INDEX(Engine!$C$87:$Y$87,1,(Assumptions!$C$4-1)*6+5) -> -16817.109
A11: Valor terminal | B11: =INDEX(Engine!$C$89:$Y$89,1,(Assumptions!$C$4-1)*6+1) -> 0 | C11: =INDEX(Engine!$C$89:$Y$89,1,(Assumptions!$C$4-1)*6+2) -> 0 | D11: =INDEX(Engine!$C$89:$Y$89,1,(Assumptions!$C$4-1)*6+3) -> 0 | E11: =INDEX(Engine!$C$89:$Y$89,1,(Assumptions!$C$4-1)*6+4) -> 0 | F11: =INDEX(Engine!$C$89:$Y$89,1,(Assumptions!$C$4-1)*6+5) -> 0
A12: FCF + valor terminal | B12: =INDEX(Engine!$C$90:$Y$90,1,(Assumptions!$C$4-1)*6+1) -> -56877.568 | C12: =INDEX(Engine!$C$90:$Y$90,1,(Assumptions!$C$4-1)*6+2) -> -37746.731 | D12: =INDEX(Engine!$C$90:$Y$90,1,(Assumptions!$C$4-1)*6+3) -> -36436.801 | E12: =INDEX(Engine!$C$90:$Y$90,1,(Assumptions!$C$4-1)*6+4) -> -31282.276 | F12: =INDEX(Engine!$C$90:$Y$90,1,(Assumptions!$C$4-1)*6+5) -> -16817.109
A13: Factor de descuento | B13: =INDEX(Engine!$C$91:$Y$91,1,(Assumptions!$C$4-1)*6+1) -> 0.84745763 | C13: =INDEX(Engine!$C$91:$Y$91,1,(Assumptions!$C$4-1)*6+2) -> 0.71818443 | D13: =INDEX(Engine!$C$91:$Y$91,1,(Assumptions!$C$4-1)*6+3) -> 0.60863087 | E13: =INDEX(Engine!$C$91:$Y$91,1,(Assumptions!$C$4-1)*6+4) -> 0.51578888 | F13: =INDEX(Engine!$C$91:$Y$91,1,(Assumptions!$C$4-1)*6+5) -> 0.43710922
A14: Valor actual | B14: =INDEX(Engine!$C$92:$Y$92,1,(Assumptions!$C$4-1)*6+1) -> -48201.329 | C14: =INDEX(Engine!$C$92:$Y$92,1,(Assumptions!$C$4-1)*6+2) -> -27109.114 | D14: =INDEX(Engine!$C$92:$Y$92,1,(Assumptions!$C$4-1)*6+3) -> -22176.562 | E14: =INDEX(Engine!$C$92:$Y$92,1,(Assumptions!$C$4-1)*6+4) -> -16135.05 | F14: =INDEX(Engine!$C$92:$Y$92,1,(Assumptions!$C$4-1)*6+5) -> -7350.9135
A15: FCF acumulado | B15: =INDEX(Engine!$C$88:$Y$88,1,(Assumptions!$C$4-1)*6+1) -> -56877.568 | C15: =INDEX(Engine!$C$88:$Y$88,1,(Assumptions!$C$4-1)*6+2) -> -94624.299 | D15: =INDEX(Engine!$C$88:$Y$88,1,(Assumptions!$C$4-1)*6+3) -> -131061.1 | E15: =INDEX(Engine!$C$88:$Y$88,1,(Assumptions!$C$4-1)*6+4) -> -162343.38 | F15: =INDEX(Engine!$C$88:$Y$88,1,(Assumptions!$C$4-1)*6+5) -> -179160.48
A16: NOPAT | B16: =INDEX(Engine!$C$94:$Y$94,1,(Assumptions!$C$4-1)*6+1) -> -22342.5 | C16: =INDEX(Engine!$C$94:$Y$94,1,(Assumptions!$C$4-1)*6+2) -> -17080.889 | D16: =INDEX(Engine!$C$94:$Y$94,1,(Assumptions!$C$4-1)*6+3) -> -15234.681 | E16: =INDEX(Engine!$C$94:$Y$94,1,(Assumptions!$C$4-1)*6+4) -> -14588.473 | F16: =INDEX(Engine!$C$94:$Y$94,1,(Assumptions!$C$4-1)*6+5) -> -12787.265
A17: Capital invertido | B17: =INDEX(Engine!$C$95:$Y$95,1,(Assumptions!$C$4-1)*6+1) -> 27087.568 | C17: =INDEX(Engine!$C$95:$Y$95,1,(Assumptions!$C$4-1)*6+2) -> 42059.78 | D17: =INDEX(Engine!$C$95:$Y$95,1,(Assumptions!$C$4-1)*6+3) -> 58183.673 | E17: =INDEX(Engine!$C$95:$Y$95,1,(Assumptions!$C$4-1)*6+4) -> 70014.652 | F17: =INDEX(Engine!$C$95:$Y$95,1,(Assumptions!$C$4-1)*6+5) -> 69782.075
A18: ROIC | B18: =INDEX(Engine!$C$96:$Y$96,1,(Assumptions!$C$4-1)*6+1) -> -1.6496498 | C18: =INDEX(Engine!$C$96:$Y$96,1,(Assumptions!$C$4-1)*6+2) -> -0.49404321 | D18: =INDEX(Engine!$C$96:$Y$96,1,(Assumptions!$C$4-1)*6+3) -> -0.30395363 | E18: =INDEX(Engine!$C$96:$Y$96,1,(Assumptions!$C$4-1)*6+4) -> -0.22759225 | F18: =INDEX(Engine!$C$96:$Y$96,1,(Assumptions!$C$4-1)*6+5) -> -0.18294083
A21: VAN al coste de capital (€) | B21: =SUM(B14:F14) -> -120972.97
A22: TIR del proyecto | B22: =IFERROR(IRR(B12:F12),"no calculable") -> no calculable
A23: TIR sin valor terminal | B23: =IFERROR(IRR(B10:F10),"no calculable") -> no calculable
A24: Payback (año en que el FCF acumulado pasa a positivo) | B24: =IFERROR(1/(1/MIN(INDEX(Engine!$C$93:$Y$93,1,(Assumptions!$C$4-1)*6+1):INDEX(Engine!$C$93:$Y$93,1,(Assumptions!$C$4-1)*6+5))),"no se recupera en 2027-2031") -> no se recupera en 2027-2031
A25: Inversión máxima acumulada (mínimo del FCF acumulado) | B25: =MIN(B15:F15) -> -179160.48
A26: Múltiplo de la inversión (VA flujos positivos / VA flujos negativos) | B26: =IFERROR(SUMIF(B14:F14,">0")/-SUMIF(B14:F14,"<0"),"n/a") -> 0
A27: Valor atribuible a Arnaldo por su participación (equity × VAN positivo) | B27: =MAX(0,B21)*Assumptions!$C$29 -> 0 | C27: ="Royalties 2027-2031: "&TEXT(INDEX(Engine!$C$38:$Y$38,1,(Assumptions!$C$4-1)*6+1)+INDEX(Engine!$C$38:$Y$38,1,(Assumptions!$C$4-1)*6+2)+INDEX(Engine!$C$38:$Y$38,1,(Assumptions!$C$4-1)*6+3)+INDEX(Engine!$C$38:$Y$38,1,(Assumptions!$C$4-1)*6+4)+INDEX(Engine!$C$38:$Y$38,1,(Assumptions!$C$4-1)*6+5),"#,##0")&" €" -> Royalties 2027-2031: 0 €
A29: Advertencia: con 5 años de horizonte y valor terminal por múltiplo, la TIR es muy sensible al EBITDA de 2031. Ver 'Scenarios' y 'Sensitivity Analysis'.

Sheet Risk Register
A1: Riesgos con impacto en el modelo (resumen; registro completo en 07_OPERATIONS/Risk Register.xlsx)
A4: ID | B4: Riesgo | C4: Severidad | D4: Variable afectada | E4: Mitigación
A5: R01 | B5: No existe vía legal para fabricar/exportar una marca de titularidad extranjera en Cuba | C5: Crítico | D5: Todo el proyecto A | E5: Fase 0: confirmación escrita del exportador y del organismo competente antes de invertir
A6: R02 | B6: Habanos S.A./Cubatabaco exige titularidad o control de la marca | C6: Crítico | D6: Valor de la marca | E6: No ceder la marca; si es condición, NO-GO o licencia con opción de recompra
A7: R03 | B7: Coste FOB superior al supuesto (sin cotización) | C7: Alto | D7: Contribución unitaria | E7: Sensibilidad PVP×FOB; FOB máximo en 'Unit Economics'
A8: R04 | B8: Retrasos de producción/transporte (anticipo inmovilizado) | C8: Alto | D8: Caja | E8: Lotes pequeños, hitos de pago, seguro
A9: R05 | B9: Imposibilidad de pagar a Cuba por canal bancario | C9: Alto | D9: Operativa | E9: Validar banco antes de firmar; carta de crédito
A10: R06 | B10: Distribuidor no acepta la marca o exige tarifa mayor | C10: Alto | D10: Volumen/margen | E10: Cartas de interés previas; tabla volumen×tarifa
A11: R07 | B11: Cambio normativo UE (fiscalidad, TPD) 2028+ | C11: Medio | D11: Precio/costes | E11: Seguimiento; el mínimo propuesto afecta poco a PVP ≥12 €
A12: R08 | B12: Rotación lenta en expendedurías (envejecimiento, merma) | C12: Medio | D12: Circulante | E12: Cobertura 6 meses; humidificación en 3PL
A13: R09 | B13: Calidad inconsistente entre lotes | C13: Medio | D13: Marca | E13: Ficha técnica, catas ciegas, rechazo contractual
A14: R10 | B14: Bloqueo de suministro (escenario Estrés) | C14: Alto | D14: Continuidad | E14: Plan de contingencia; marca transferible a otro origen (con cambio de producto)

Sheet Sources & Validation
A1: Fuentes y validación de supuestos
A2: Fecha de consulta: 10/10/2026. Acceso mediante motor de búsqueda (descarga directa bloqueada en el entorno).
A4: ID | B4: Fuente | C4: Tipo | D4: Dato utilizado | E4: Estado | F4: URL
A5: S01 | B5: Habanos S.A. — ficha enciclopédica | C5: Secundaria | D5: Habanos S.A. (1994) controla promoción, distribución y exportación mundial de puros premium cubanos; estructura 50/50 Cubatabaco / socio privado. | E5: VERIFICADO (con S05, S21) | F5: https://en.wikipedia.org/wiki/Habanos_S.A.
A6: S02 | B6: Cigar Aficionado — New Cuban cigars / Regional Editions | C6: Secundaria | D6: Ediciones Regionales: las solicitan distribuidores exclusivos; compra de 25.000 unidades por referencia; exclusividad regional >= 2 años. | E6: PROBABLE | F6: https://www.cigaraficionado.com/article/new-cuban-cigars-from-habanos
A7: S03 | B7: Gaceta Oficial de Cuba No. 71 Ordinaria 2026 / Decreto-Ley 133/2026 | C7: Primaria (índice) | D7: DL 133/2026 modifica DL 88, 89 y 90/2024 (mipymes, CNA, TCP); faculta a mipymes a importar/exportar directamente previa autorización del MINCEX. | E7: VERIFICADO (con S04) | F7: https://www.gacetaoficial.gob.cu/es/gaceta-oficial-no-71-ordinaria-de-2026
A8: S04 | B8: CiberCuba — MINCEX actualiza reglas para importar y exportar (03/09/2026) | C8: Secundaria | D8: Resolución MINCEX (Gaceta No. 73) fija requisitos para operar comercio exterior y lista de productos no comerciables directamente (contenido de la lista no confirmado). | E8: PROBABLE | F8: https://en.cibercuba.com/noticias/2026-09-03-u1-e135253-s27061-nid339462-mincex-actualiza-reglas-importar-exportar-cuba
A9: S05 | B9: Tobacco Asia — Cuba Opens Tobacco to Private Investment (2026) | C9: Secundaria | D9: Medida 58: usufructo de tierra a personas jurídicas privadas, tabaco incluido; Tabacuba mantiene el monopolio de compra de hoja; Habanos S.A. mantiene marketing y exportación. | E9: VERIFICADO (con S01, S46) | F9: https://www.tobaccoasia.com/features/cuba-opens-tobacco-to-private-investment/
A10: S06 | B10: CiberCuba — Decreto 183/2026 sucursales de empresas extranjeras (06/10/2026) | C10: Secundaria | D10: Regula facultades de sucursales extranjeras (importar/exportar, mayorista, facturar); minorista prohibido. Sin mención a tabaco. | E10: PROBABLE | F10: https://en.cibercuba.com/noticias/2026-10-06-u1-e207888-s27061-nid342081-cuba-prohibe-sucursales-empresas-extranjeras
A11: S07 | B11: Infobae / Cubadebate — Decreto-Ley 128/2026 modifica Ley 118 de Inversión Extranjera (03/09/2026) | C11: Secundaria + medio oficial | D11: Firmado 28/07/2026, GO No. 73 de 03/09/2026: contratación directa de trabajadores por empresas mixtas y de capital extranjero; cuentas en el exterior sin autorización previa del BCC. | E11: VERIFICADO (Infobae + Cubadebate + Radio Rebelde) | F11: https://www.infobae.com/cuba/2026/09/03/que-cambia-para-las-empresas-extranjeras-en-cuba-desde-este-3-de-septiembre-con-el-decreto-ley-128/
A12: S08 | B12: US-Cuba Trade and Economic Council — BAT vende el 50% de Brascuba (05/10/2026) | C12: Secundaria | D12: BAT vende su 50% en la empresa mixta Brascuba a Tabagest S.A.: retirada de un socio extranjero del sector tabaco. | E12: PROBABLE | F12: https://www.cubatrade.org/blog/2026/10/5/k2bx5ab4es4p93polzfwzfxq3k34jf
A13: S09 | B13: Directorio Cubano — Nota de la Aduana de Cuba sobre decomisos | C13: Secundaria (reproduce nota oficial) | D13: Exportación de tabaco torcido regulada por la Resolución 98/2022 del MINAG; viajeros: hasta 20 unidades sueltas sin documentación; más, con factura de tienda autorizada. | E13: PROBABLE | F13: https://www.directoriocubano.info/cuba/nota-informativa-de-la-aduana-de-cuba-sobre-nuevos-decomisos-en-el-aeropuerto-jose-marti-de-la-habana/
A14: S10 | B14: Davidoff — ficha enciclopédica | C14: Secundaria | D14: Precedente: puros Davidoff fabricados en El Laguito (La Habana) desde 1968/69 hasta 1990/91; ruptura con Cubatabaco por calidad y titularidad de la marca. | E14: PROBABLE | F14: https://en.wikipedia.org/wiki/Davidoff
A15: S11 | B15: CigarSense / Pipedia — Dunhill Cuban cigars | C15: Secundaria | D15: Precedente: marca Dunhill fabricada en Cuba (acuerdo 1982, venta 1984) hasta ~1991. | E15: PROBABLE | F15: https://www.cigarsense.com/the-history-of-the-dunhill-cuban-cigars/
... A62: N07 | B62: Ley 95/2010 del Impuesto sobre Sociedades de Andorra | C62: Norma (no releída hoy) | D62: Tipo general 10% en Andorra; régimen y sustancia deben confirmarse con asesor andorrano. | E62: HIPÓTESIS (confirmar) | F62: https://www.bopa.ad
A64: Controles automáticos del modelo
A65: Balance cuadra en los 4 escenarios | D65: =IF(SUMPRODUCT(ABS(Engine!$C$84:$Y$84))<0.5,"OK","ERROR") -> OK
A66: Reparto del PVP suma 100% (Import & Taxes) | D66: =IF(ABS('Import & Taxes'!D29-1)<0.0001,"OK","ERROR") -> OK
A67: Caja final conciliada con variación (Cash Flow) | D67: =IF(SUMPRODUCT(ABS('Cash Flow'!B19:F19))<0.5,"OK","ERROR") -> OK
A68: Sensibilidad: forma cerrada = motor (EBITDA 2030) | D68: =IF(ABS('Sensitivity Analysis'!C13)<1,"OK","ERROR") -> OK
A69: Stock final nunca negativo | D69: =IF(MIN(Engine!$C$16:$Y$16)>=-0.01,"OK","ERROR") -> OK

Sheet Engine
A1: Motor de cálculo — 4 escenarios en paralelo (no editar: sólo fórmulas)
A2: Bloques: Conservador C:G · Base I:M · Optimista O:S · Estrés U:Y. Las hojas de presentación leen el escenario seleccionado.
C3: Conservador | I3: Base | O3: Optimista | U3: Estrés
A4: Concepto | B4: Unidad | C4: 2027 | D4: 2028 | E4: 2029 | F4: 2030 | G4: 2031 | I4: 2027 | J4: 2028 | K4: 2029 | L4: 2030 | M4: 2031 | O4: 2027 | P4: 2028 | Q4: 2029 | R4: 2030 | S4: 2031 | U4: 2027 | V4: 2028 | W4: 2029 | X4: 2030 | Y4: 2031
A6: VOLUMEN E INVENTARIO (unidades)
A7: Año | C7: =Assumptions!$C$8+0 -> 2027 | D7: =Assumptions!$C$8+1 -> 2028 | E7: =Assumptions!$C$8+2 -> 2029 | F7: =Assumptions!$C$8+3 -> 2030 | G7: =Assumptions!$C$8+4 -> 2031 | I7: =Assumptions!$C$8+0 -> 2027 | J7: =Assumptions!$C$8+1 -> 2028 | K7: =Assumptions!$C$8+2 -> 2029 | L7: =Assumptions!$C$8+3 -> 2030 | M7: =Assumptions!$C$8+4 -> 2031 | O7: =Assumptions!$C$8+0 -> 2027 | P7: =Assumptions!$C$8+1 -> 2028 | Q7: =Assumptions!$C$8+2 -> 2029 | R7: =Assumptions!$C$8+3 -> 2030 | S7: =Assumptions!$C$8+4 -> 2031 | U7: =Assumptions!$C$8+0 -> 2027 | V7: =Assumptions!$C$8+1 -> 2028 | W7: =Assumptions!$C$8+2 -> 2029 | X7: =Assumptions!$C$8+3 -> 2030 | Y7: =Assumptions!$C$8+4 -> 2031
A8: Demanda | C8: ='Sales Forecast'!$B$5 -> 0 | D8: ='Sales Forecast'!$C$5 -> 1000 | E8: ='Sales Forecast'!$D$5 -> 1500 | F8: ='Sales Forecast'!$E$5 -> 2000 | G8: ='Sales Forecast'!$F$5 -> 2500 | I8: ='Sales Forecast'!$B$6 -> 0 | J8: ='Sales Forecast'!$C$6 -> 2000 | K8: ='Sales Forecast'!$D$6 -> 3500 | L8: ='Sales Forecast'!$E$6 -> 5000 | M8: ='Sales Forecast'!$F$6 -> 6500 | O8: ='Sales Forecast'!$B$7 -> 0 | P8: ='Sales Forecast'!$C$7 -> 3500 | Q8: ='Sales Forecast'!$D$7 -> 6000 | R8: ='Sales Forecast'!$E$7 -> 9000 | S8: ='Sales Forecast'!$F$7 -> 12000 | U8: ='Sales Forecast'!$B$8 -> 0 | V8: ='Sales Forecast'!$C$8 -> 2000 | W8: ='Sales Forecast'!$D$8 -> 3500 | X8: ='Sales Forecast'!$E$8 -> 5000 | Y8: ='Sales Forecast'!$F$8 -> 6500
A9: Suministro disponible (1/0) | C9: =IF(C7<Assumptions!$C$49,1,0) -> 1 | D9: =IF(D7<Assumptions!$C$49,1,0) -> 1 | E9: =IF(E7<Assumptions!$C$49,1,0) -> 1 | F9: =IF(F7<Assumptions!$C$49,1,0) -> 1 | G9: =IF(G7<Assumptions!$C$49,1,0) -> 1 | I9: =IF(I7<Assumptions!$D$49,1,0) -> 1 | J9: =IF(J7<Assumptions!$D$49,1,0) -> 1 | K9: =IF(K7<Assumptions!$D$49,1,0) -> 1 | L9: =IF(L7<Assumptions!$D$49,1,0) -> 1 | M9: =IF(M7<Assumptions!$D$49,1,0) -> 1 | O9: =IF(O7<Assumptions!$E$49,1,0) -> 1 | P9: =IF(P7<Assumptions!$E$49,1,0) -> 1 | Q9: =IF(Q7<Assumptions!$E$49,1,0) -> 1 | R9: =IF(R7<Assumptions!$E$49,1,0) -> 1 | S9: =IF(S7<Assumptions!$E$49,1,0) -> 1 | U9: =IF(U7<Assumptions!$F$49,1,0) -> 1 | V9: =IF(V7<Assumptions!$F$49,1,0) -> 1 | W9: =IF(W7<Assumptions!$F$49,1,0) -> 0 | X9: =IF(X7<Assumptions!$F$49,1,0) -> 0 | Y9: =IF(Y7<Assumptions!$F$49,1,0) -> 0
A10: Factor de consumo por unidad vendida (merma+muestras) | C10: =1/(1-Assumptions!$C$46)+Assumptions!$C$47 -> 1.0926316 | D10: =1/(1-Assumptions!$C$46)+Assumptions!$C$47 -> 1.0926316 | E10: =1/(1-Assumptions!$C$46)+Assumptions!$C$47 -> 1.0926316 | F10: =1/(1-Assumptions!$C$46)+Assumptions!$C$47 -> 1.0926316 | G10: =1/(1-Assumptions!$C$46)+Assumptions!$C$47 -> 1.0926316 | I10: =1/(1-Assumptions!$D$46)+Assumptions!$D$47 -> 1.0609278 | J10: =1/(1-Assumptions!$D$46)+Assumptions!$D$47 -> 1.0609278 | K10: =1/(1-Assumptions!$D$46)+Assumptions!$D$47 -> 1.0609278 | L10: =1/(1-Assumptions!$D$46)+Assumptions!$D$47 -> 1.0609278 | M10: =1/(1-Assumptions!$D$46)+Assumptions!$D$47 -> 1.0609278 | O10: =1/(1-Assumptions!$E$46)+Assumptions!$E$47 -> 1.0454082 | P10: =1/(1-Assumptions!$E$46)+Assumptions!$E$47 -> 1.0454082 | Q10: =1/(1-Assumptions!$E$46)+Assumptions!$E$47 -> 1.0454082 | R10: =1/(1-Assumptions!$E$46)+Assumptions!$E$47 -> 1.0454082 | S10: =1/(1-Assumptions!$E$46)+Assumptions!$E$47 -> 1.0454082 | U10: =1/(1-Assumptions!$F$46)+Assumptions!$F$47 -> 1.1269565 | V10: =1/(1-Assumptions!$F$46)+Assumptions!$F$47 -> 1.1269565 | W10: =1/(1-Assumptions!$F$46)+Assumptions!$F$47 -> 1.1269565 | X10: =1/(1-Assumptions!$F$46)+Assumptions!$F$47 -> 1.1269565 | Y10: =1/(1-Assumptions!$F$46)+Assumptions!$F$47 -> 1.1269565
A11: Stock inicial | C11: =0 -> 0 | D11: =C16 -> 500 | E11: =D16 -> 750 | F11: =E16 -> 1000 | G11: =F16 -> 1250 | I11: =0 -> 0 | J11: =I16 -> 1000 | K11: =J16 -> 1750 | L11: =K16 -> 2500 | M11: =L16 -> 3250 | O11: =0 -> 0 | P11: =O16 -> 1750 | Q11: =P16 -> 3000 | R11: =Q16 -> 4500 | S11: =R16 -> 6000 | U11: =0 -> 0 | V11: =U16 -> 1000 | W11: =V16 -> 1750 | X11: =W16 -> 0 | Y11: =X16 -> 0
A12: Stock objetivo a cierre | C12: =Assumptions!$C$22/12*'Sales Forecast'!$C$5*C9 -> 500 | D12: =Assumptions!$C$22/12*'Sales Forecast'!$D$5*D9 -> 750 | E12: =Assumptions!$C$22/12*'Sales Forecast'!$E$5*E9 -> 1000 | F12: =Assumptions!$C$22/12*'Sales Forecast'!$F$5*F9 -> 1250 | G12: =Assumptions!$C$22/12*'Sales Forecast'!$F$5*G9 -> 1250 | I12: =Assumptions!$C$22/12*'Sales Forecast'!$C$6*I9 -> 1000 | J12: =Assumptions!$C$22/12*'Sales Forecast'!$D$6*J9 -> 1750 | K12: =Assumptions!$C$22/12*'Sales Forecast'!$E$6*K9 -> 2500 | L12: =Assumptions!$C$22/12*'Sales Forecast'!$F$6*L9 -> 3250 | M12: =Assumptions!$C$22/12*'Sales Forecast'!$F$6*M9 -> 3250 | O12: =Assumptions!$C$22/12*'Sales Forecast'!$C$7*O9 -> 1750 | P12: =Assumptions!$C$22/12*'Sales Forecast'!$D$7*P9 -> 3000 | Q12: =Assumptions!$C$22/12*'Sales Forecast'!$E$7*Q9 -> 4500 | R12: =Assumptions!$C$22/12*'Sales Forecast'!$F$7*R9 -> 6000 | S12: =Assumptions!$C$22/12*'Sales Forecast'!$F$7*S9 -> 6000 | U12: =Assumptions!$C$22/12*'Sales Forecast'!$C$8*U9 -> 1000 | V12: =Assumptions!$C$22/12*'Sales Forecast'!$D$8*V9 -> 1750 | W12: =Assumptions!$C$22/12*'Sales Forecast'!$E$8*W9 -> 0 | X12: =Assumptions!$C$22/12*'Sales Forecast'!$F$8*X9 -> 0 | Y12: =Assumptions!$C$22/12*'Sales Forecast'!$F$8*Y9 -> 0
A13: Unidades compradas (importadas) | C13: =IF(C9=1,MAX(0,C8*C10+C12-C11),0) -> 500 | D13: =IF(D9=1,MAX(0,D8*D10+D12-D11),0) -> 1342.6316 | E13: =IF(E9=1,MAX(0,E8*E10+E12-E11),0) -> 1888.9474 | F13: =IF(F9=1,MAX(0,F8*F10+F12-F11),0) -> 2435.2632 | G13: =IF(G9=1,MAX(0,G8*G10+G12-G11),0) -> 2731.5789 | I13: =IF(I9=1,MAX(0,I8*I10+I12-I11),0) -> 1000 | J13: =IF(J9=1,MAX(0,J8*J10+J12-J11),0) -> 2871.8557 | K13: =IF(K9=1,MAX(0,K8*K10+K12-K11),0) -> 4463.2474 | L13: =IF(L9=1,MAX(0,L8*L10+L12-L11),0) -> 6054.6392 | M13: =IF(M9=1,MAX(0,M8*M10+M12-M11),0) -> 6896.0309 | O13: =IF(O9=1,MAX(0,O8*O10+O12-O11),0) -> 1750 | P13: =IF(P9=1,MAX(0,P8*P10+P12-P11),0) -> 4908.9286 | Q13: =IF(Q9=1,MAX(0,Q8*Q10+Q12-Q11),0) -> 7772.449 | R13: =IF(R9=1,MAX(0,R8*R10+R12-R11),0) -> 10908.673 | S13: =IF(S9=1,MAX(0,S8*S10+S12-S11),0) -> 12544.898 | U13: =IF(U9=1,MAX(0,U8*U10+U12-U11),0) -> 1000 | V13: =IF(V9=1,MAX(0,V8*V10+V12-V11),0) -> 3003.913 | W13: =IF(W9=1,MAX(0,W8*W10+W12-W11),0) -> 0 | X13: =IF(X9=1,MAX(0,X8*X10+X12-X11),0) -> 0 | Y13: =IF(Y9=1,MAX(0,Y8*Y10+Y12-Y11),0) -> 0
A14: Unidades vendidas | C14: =IF(C9=1,C8,MIN(C8,C11/C10)) -> 0 | D14: =IF(D9=1,D8,MIN(D8,D11/D10)) -> 1000 | E14: =IF(E9=1,E8,MIN(E8,E11/E10)) -> 1500 | F14: =IF(F9=1,F8,MIN(F8,F11/F10)) -> 2000 | G14: =IF(G9=1,G8,MIN(G8,G11/G10)) -> 2500 | I14: =IF(I9=1,I8,MIN(I8,I11/I10)) -> 0 | J14: =IF(J9=1,J8,MIN(J8,J11/J10)) -> 2000 | K14: =IF(K9=1,K8,MIN(K8,K11/K10)) -> 3500 | L14: =IF(L9=1,L8,MIN(L8,L11/L10)) -> 5000 | M14: =IF(M9=1,M8,MIN(M8,M11/M10)) -> 6500 | O14: =IF(O9=1,O8,MIN(O8,O11/O10)) -> 0 | P14: =IF(P9=1,P8,MIN(P8,P11/P10)) -> 3500 | Q14: =IF(Q9=1,Q8,MIN(Q8,Q11/Q10)) -> 6000 | R14: =IF(R9=1,R8,MIN(R8,R11/R10)) -> 9000 | S14: =IF(S9=1,S8,MIN(S8,S11/S10)) -> 12000 | U14: =IF(U9=1,U8,MIN(U8,U11/U10)) -> 0 | V14: =IF(V9=1,V8,MIN(V8,V11/V10)) -> 2000 | W14: =IF(W9=1,W8,MIN(W8,W11/W10)) -> 1552.8549 | X14: =IF(X9=1,X8,MIN(X8,X11/X10)) -> 0 | Y14: =IF(Y9=1,Y8,MIN(Y8,Y11/Y10)) -> 0
A15: Unidades consumidas (ventas+merma+muestras) | C15: =C14*C10 -> 0 | D15: =D14*D10 -> 1092.6316 | E15: =E14*E10 -> 1638.9474 | F15: =F14*F10 -> 2185.2632 | G15: =G14*G10 -> 2731.5789 | I15: =I14*I10 -> 0 | J15: =J14*J10 -> 2121.8557 | K15: =K14*K10 -> 3713.2474 | L15: =L14*L10 -> 5304.6392 | M15: =M14*M10 -> 6896.0309 | O15: =O14*O10 -> 0 | P15: =P14*P10 -> 3658.9286 | Q15: =Q14*Q10 -> 6272.449 | R15: =R14*R10 -> 9408.6735 | S15: =S14*S10 -> 12544.898 | U15: =U14*U10 -> 0 | V15: =V14*V10 -> 2253.913 | W15: =W14*W10 -> 1750 | X15: =X14*X10 -> 0 | Y15: =Y14*Y10 -> 0
A16: Stock final | C16: =C11+C13-C15 -> 500 | D16: =D11+D13-D15 -> 750 | E16: =E11+E13-E15 -> 1000 | F16: =F11+F13-F15 -> 1250 | G16: =G11+G13-G15 -> 1250 | I16: =I11+I13-I15 -> 1000 | J16: =J11+J13-J15 -> 1750 | K16: =K11+K13-K15 -> 2500 | L16: =L11+L13-L15 -> 3250 | M16: =M11+M13-M15 -> 3250 | O16: =O11+O13-O15 -> 1750 | P16: =P11+P13-P15 -> 3000 | Q16: =Q11+Q13-Q15 -> 4500 | R16: =R11+R13-R15 -> 6000 | S16: =S11+S13-S15 -> 6000 | U16: =U11+U13-U15 -> 1000 | V16: =V11+V13-V15 -> 1750 | W16: =W11+W13-W15 -> 0 | X16: =X11+X13-X15 -> 0 | Y16: =Y11+Y13-Y15 -> 0
A18: ECONOMÍA UNITARIA (€/u)
A19: PVP | C19: =Assumptions!$C$39 -> 20 | D19: =Assumptions!$C$39 -> 20 | E19: =Assumptions!$C$39 -> 20 | F19: =Assumptions!$C$39 -> 20 | G19: =Assumptions!$C$39 -> 20 | I19: =Assumptions!$D$39 -> 24 | J19: =Assumptions!$D$39 -> 24 | K19: =Assumptions!$D$39 -> 24 | L19: =Assumptions!$D$39 -> 24 | M19: =Assumptions!$D$39 -> 24 | O19: =Assumptions!$E$39 -> 28 | P19: =Assumptions!$E$39 -> 28 | Q19: =Assumptions!$E$39 -> 28 | R19: =Assumptions!$E$39 -> 28 | S19: =Assumptions!$E$39 -> 28 | U19: =Assumptions!$F$39 -> 24 | V19: =Assumptions!$F$39 -> 24 | W19: =Assumptions!$F$39 -> 24 | X19: =Assumptions!$F$39 -> 24 | Y19: =Assumptions!$F$39 -> 24
A20: Fabricación FOB en € | C20: =Assumptions!$C$40/Assumptions!$C$19 -> 6.0869565 | D20: =Assumptions!$C$40/Assumptions!$C$19 -> 6.0869565 | E20: =Assumptions!$C$40/Assumptions!$C$19 -> 6.0869565 | F20: =Assumptions!$C$40/Assumptions!$C$19 -> 6.0869565 | G20: =Assumptions!$C$40/Assumptions!$C$19 -> 6.0869565 | I20: =Assumptions!$D$40/Assumptions!$C$19 -> 5.2173913 | J20: =Assumptions!$D$40/Assumptions!$C$19 -> 5.2173913 | K20: =Assumptions!$D$40/Assumptions!$C$19 -> 5.2173913 | L20: =Assumptions!$D$40/Assumptions!$C$19 -> 5.2173913 | M20: =Assumptions!$D$40/Assumptions!$C$19 -> 5.2173913 | O20: =Assumptions!$E$40/Assumptions!$C$19 -> 4.3478261 | P20: =Assumptions!$E$40/Assumptions!$C$19 -> 4.3478261 | Q20: =Assumptions!$E$40/Assumptions!$C$19 -> 4.3478261 | R20: =Assumptions!$E$40/Assumptions!$C$19 -> 4.3478261 | S20: =Assumptions!$E$40/Assumptions!$C$19 -> 4.3478261 | U20: =Assumptions!$F$40/Assumptions!$C$19 -> 6.5217391 | V20: =Assumptions!$F$40/Assumptions!$C$19 -> 6.5217391 | W20: =Assumptions!$F$40/Assumptions!$C$19 -> 6.5217391 | X20: =Assumptions!$F$40/Assumptions!$C$19 -> 6.5217391 | Y20: =Assumptions!$F$40/Assumptions!$C$19 -> 6.5217391
A21: Packaging | C21: ='Product Cost'!$D$13*Assumptions!$C$41 -> 1.815 | D21: ='Product Cost'!$D$13*Assumptions!$C$41 -> 1.815 | E21: ='Product Cost'!$D$13*Assumptions!$C$41 -> 1.815 | F21: ='Product Cost'!$D$13*Assumptions!$C$41 -> 1.815 | G21: ='Product Cost'!$D$13*Assumptions!$C$41 -> 1.815 | I21: ='Product Cost'!$D$13*Assumptions!$D$41 -> 1.65 | J21: ='Product Cost'!$D$13*Assumptions!$D$41 -> 1.65 | K21: ='Product Cost'!$D$13*Assumptions!$D$41 -> 1.65 | L21: ='Product Cost'!$D$13*Assumptions!$D$41 -> 1.65 | M21: ='Product Cost'!$D$13*Assumptions!$D$41 -> 1.65 | O21: ='Product Cost'!$D$13*Assumptions!$E$41 -> 1.485 | P21: ='Product Cost'!$D$13*Assumptions!$E$41 -> 1.485 | Q21: ='Product Cost'!$D$13*Assumptions!$E$41 -> 1.485 | R21: ='Product Cost'!$D$13*Assumptions!$E$41 -> 1.485 | S21: ='Product Cost'!$D$13*Assumptions!$E$41 -> 1.485 | U21: ='Product Cost'!$D$13*Assumptions!$F$41 -> 1.98 | V21: ='Product Cost'!$D$13*Assumptions!$F$41 -> 1.98 | W21: ='Product Cost'!$D$13*Assumptions!$F$41 -> 1.98 | X21: ='Product Cost'!$D$13*Assumptions!$F$41 -> 1.98 | Y21: ='Product Cost'!$D$13*Assumptions!$F$41 -> 1.98
A22: Valor CIF (base aduanera) | C22: =(C20+C21+Assumptions!$C$42+Assumptions!$C$43)*(1+Assumptions!$C$15) -> 8.9464663 | D22: =(D20+D21+Assumptions!$C$42+Assumptions!$C$43)*(1+Assumptions!$C$15) -> 8.9464663 | E22: =(E20+E21+Assumptions!$C$42+Assumptions!$C$43)*(1+Assumptions!$C$15) -> 8.9464663 | F22: =(F20+F21+Assumptions!$C$42+Assumptions!$C$43)*(1+Assumptions!$C$15) -> 8.9464663 | G22: =(G20+G21+Assumptions!$C$42+Assumptions!$C$43)*(1+Assumptions!$C$15) -> 8.9464663 | I22: =(I20+I21+Assumptions!$D$42+Assumptions!$D$43)*(1+Assumptions!$C$15) -> 7.7057283 | J22: =(J20+J21+Assumptions!$D$42+Assumptions!$D$43)*(1+Assumptions!$C$15) -> 7.7057283 | K22: =(K20+K21+Assumptions!$D$42+Assumptions!$D$43)*(1+Assumptions!$C$15) -> 7.7057283 | L22: =(L20+L21+Assumptions!$D$42+Assumptions!$D$43)*(1+Assumptions!$C$15) -> 7.7057283 | M22: =(M20+M21+Assumptions!$D$42+Assumptions!$D$43)*(1+Assumptions!$C$15) -> 7.7057283 | O22: =(O20+O21+Assumptions!$E$42+Assumptions!$E$43)*(1+Assumptions!$C$15) -> 6.4649902 | P22: =(P20+P21+Assumptions!$E$42+Assumptions!$E$43)*(1+Assumptions!$C$15) -> 6.4649902 | Q22: =(Q20+Q21+Assumptions!$E$42+Assumptions!$E$43)*(1+Assumptions!$C$15) -> 6.4649902 | R22: =(R20+R21+Assumptions!$E$42+Assumptions!$E$43)*(1+Assumptions!$C$15) -> 6.4649902 | S22: =(S20+S21+Assumptions!$E$42+Assumptions!$E$43)*(1+Assumptions!$C$15) -> 6.4649902 | U22: =(U20+U21+Assumptions!$F$42+Assumptions!$F$43)*(1+Assumptions!$C$15) -> 9.8004978 | V22: =(V20+V21+Assumptions!$F$42+Assumptions!$F$43)*(1+Assumptions!$C$15) -> 9.8004978 | W22: =(W20+W21+Assumptions!$F$42+Assumptions!$F$43)*(1+Assumptions!$C$15) -> 9.8004978 | X22: =(X20+X21+Assumptions!$F$42+Assumptions!$F$43)*(1+Assumptions!$C$15) -> 9.8004978 | Y22: =(Y20+Y21+Assumptions!$F$42+Assumptions!$F$43)*(1+Assumptions!$C$15) -> 9.8004978
A23: Arancel | C23: =C22*Assumptions!$C$14 -> 2.3260812 | D23: =D22*Assumptions!$C$14 -> 2.3260812 | E23: =E22*Assumptions!$C$14 -> 2.3260812 | F23: =F22*Assumptions!$C$14 -> 2.3260812 | G23: =G22*Assumptions!$C$14 -> 2.3260812 | I23: =I22*Assumptions!$C$14 -> 2.0034893 | J23: =J22*Assumptions!$C$14 -> 2.0034893 | K23: =K22*Assumptions!$C$14 -> 2.0034893 | L23: =L22*Assumptions!$C$14 -> 2.0034893 | M23: =M22*Assumptions!$C$14 -> 2.0034893 | O23: =O22*Assumptions!$C$14 -> 1.6808975 | P23: =P22*Assumptions!$C$14 -> 1.6808975 | Q23: =Q22*Assumptions!$C$14 -> 1.6808975 | R23: =R22*Assumptions!$C$14 -> 1.6808975 | S23: =S22*Assumptions!$C$14 -> 1.6808975 | U23: =U22*Assumptions!$C$14 -> 2.5481294 | V23: =V22*Assumptions!$C$14 -> 2.5481294 | W23: =W22*Assumptions!$C$14 -> 2.5481294 | X23: =X22*Assumptions!$C$14 -> 2.5481294 | Y23: =Y22*Assumptions!$C$14 -> 2.5481294
A24: Coste en destino (sin IEE ni IVA) | C24: =C22+C23+Assumptions!$C$16+Assumptions!$C$44 -> 11.702548 | D24: =D22+D23+Assumptions!$C$16+Assumptions!$C$44 -> 11.702548 | E24: =E22+E23+Assumptions!$C$16+Assumptions!$C$44 -> 11.702548 | F24: =F22+F23+Assumptions!$C$16+Assumptions!$C$44 -> 11.702548 | G24: =G22+G23+Assumptions!$C$16+Assumptions!$C$44 -> 11.702548 | I24: =I22+I23+Assumptions!$C$16+Assumptions!$D$44 -> 10.089218 | J24: =J22+J23+Assumptions!$C$16+Assumptions!$D$44 -> 10.089218 | K24: =K22+K23+Assumptions!$C$16+Assumptions!$D$44 -> 10.089218 | L24: =L22+L23+Assumptions!$C$16+Assumptions!$D$44 -> 10.089218 | M24: =M22+M23+Assumptions!$C$16+Assumptions!$D$44 -> 10.089218 | O24: =O22+O23+Assumptions!$C$16+Assumptions!$E$44 -> 8.4758877 | P24: =P22+P23+Assumptions!$C$16+Assumptions!$E$44 -> 8.4758877 | Q24: =Q22+Q23+Assumptions!$C$16+Assumptions!$E$44 -> 8.4758877 | R24: =R22+R23+Assumptions!$C$16+Assumptions!$E$44 -> 8.4758877 | S24: =S22+S23+Assumptions!$C$16+Assumptions!$E$44 -> 8.4758877 | U24: =U22+U23+Assumptions!$C$16+Assumptions!$F$44 -> 12.778627 | V24: =V22+V23+Assumptions!$C$16+Assumptions!$F$44 -> 12.778627 | W24: =W22+W23+Assumptions!$C$16+Assumptions!$F$44 -> 12.778627 | X24: =X22+X23+Assumptions!$C$16+Assumptions!$F$44 -> 12.778627 | Y24: =Y22+Y23+Assumptions!$C$16+Assumptions!$F$44 -> 12.778627
A25: Impuesto especial por unidad | C25: =MAX(Assumptions!$C$11*C19,Assumptions!$C$12/1000) -> 3.16 | D25: =MAX(Assumptions!$C$11*D19,Assumptions!$C$12/1000) -> 3.16 | E25: =MAX(Assumptions!$C$11*E19,Assumptions!$C$12/1000) -> 3.16 | F25: =MAX(Assumptions!$C$11*F19,Assumptions!$C$12/1000) -> 3.16 | G25: =MAX(Assumptions!$C$11*G19,Assumptions!$C$12/1000) -> 3.16 | I25: =MAX(Assumptions!$C$11*I19,Assumptions!$C$12/1000) -> 3.792 | J25: =MAX(Assumptions!$C$11*J19,Assumptions!$C$12/1000) -> 3.792 | K25: =MAX(Assumptions!$C$11*K19,Assumptions!$C$12/1000) -> 3.792 | L25: =MAX(Assumptions!$C$11*L19,Assumptions!$C$12/1000) -> 3.792 | M25: =MAX(Assumptions!$C$11*M19,Assumptions!$C$12/1000) -> 3.792 | O25: =MAX(Assumptions!$C$11*O19,Assumptions!$C$12/1000) -> 4.424 | P25: =MAX(Assumptions!$C$11*P19,Assumptions!$C$12/1000) -> 4.424 | Q25: =MAX(Assumptions!$C$11*Q19,Assumptions!$C$12/1000) -> 4.424 | R25: =MAX(Assumptions!$C$11*R19,Assumptions!$C$12/1000) -> 4.424 | S25: =MAX(Assumptions!$C$11*S19,Assumptions!$C$12/1000) -> 4.424 | U25: =MAX(Assumptions!$C$11*U19,Assumptions!$C$12/1000) -> 3.792 | V25: =MAX(Assumptions!$C$11*V19,Assumptions!$C$12/1000) -> 3.792 | W25: =MAX(Assumptions!$C$11*W19,Assumptions!$C$12/1000) -> 3.792 | X25: =MAX(Assumptions!$C$11*X19,Assumptions!$C$12/1000) -> 3.792 | Y25: =MAX(Assumptions!$C$11*Y19,Assumptions!$C$12/1000) -> 3.792
A26: Contribución por unidad vendida | C26: =(C19/(1+Assumptions!$C$10)-C19*(Assumptions!$C$13+Assumptions!$C$45))*(1-Assumptions!$C$28)-C10*(C25+C24) -> -2.7103632 | D26: =(D19/(1+Assumptions!$C$10)-D19*(Assumptions!$C$13+Assumptions!$C$45))*(1-Assumptions!$C$28)-D10*(D25+D24) -> -2.7103632 | E26: =(E19/(1+Assumptions!$C$10)-E19*(Assumptions!$C$13+Assumptions!$C$45))*(1-Assumptions!$C$28)-E10*(E25+E24) -> -2.7103632 | F26: =(F19/(1+Assumptions!$C$10)-F19*(Assumptions!$C$13+Assumptions!$C$45))*(1-Assumptions!$C$28)-F10*(F25+F24) -> -2.7103632 | G26: =(G19/(1+Assumptions!$C$10)-G19*(Assumptions!$C$13+Assumptions!$C$45))*(1-Assumptions!$C$28)-G10*(G25+G24) -> -2.7103632 | I26: =(I19/(1+Assumptions!$C$10)-I19*(Assumptions!$C$13+Assumptions!$D$45))*(1-Assumptions!$C$28)-I10*(I25+I24) -> 1.7477406 | J26: =(J19/(1+Assumptions!$C$10)-J19*(Assumptions!$C$13+Assumptions!$D$45))*(1-Assumptions!$C$28)-J10*(J25+J24) -> 1.7477406 | K26: =(K19/(1+Assumptions!$C$10)-K19*(Assumptions!$C$13+Assumptions!$D$45))*(1-Assumptions!$C$28)-K10*(K25+K24) -> 1.7477406 | L26: =(L19/(1+Assumptions!$C$10)-L19*(Assumptions!$C$13+Assumptions!$D$45))*(1-Assumptions!$C$28)-L10*(L25+L24) -> 1.7477406 | M26: =(M19/(1+Assumptions!$C$10)-M19*(Assumptions!$C$13+Assumptions!$D$45))*(1-Assumptions!$C$28)-M10*(M25+M24) -> 1.7477406 | O26: =(O19/(1+Assumptions!$C$10)-O19*(Assumptions!$C$13+Assumptions!$E$45))*(1-Assumptions!$C$28)-O10*(O25+O24) -> 5.874848 | P26: =(P19/(1+Assumptions!$C$10)-P19*(Assumptions!$C$13+Assumptions!$E$45))*(1-Assumptions!$C$28)-P10*(P25+P24) -> 5.874848 | Q26: =(Q19/(1+Assumptions!$C$10)-Q19*(Assumptions!$C$13+Assumptions!$E$45))*(1-Assumptions!$C$28)-Q10*(Q25+Q24) -> 5.874848 | R26: =(R19/(1+Assumptions!$C$10)-R19*(Assumptions!$C$13+Assumptions!$E$45))*(1-Assumptions!$C$28)-R10*(R25+R24) -> 5.874848 | S26: =(S19/(1+Assumptions!$C$10)-S19*(Assumptions!$C$13+Assumptions!$E$45))*(1-Assumptions!$C$28)-S10*(S25+S24) -> 5.874848 | U26: =(U19/(1+Assumptions!$C$10)-U19*(Assumptions!$C$13+Assumptions!$F$45))*(1-Assumptions!$C$28)-U10*(U25+U24) -> -2.4396657 | V26: =(V19/(1+Assumptions!$C$10)-V19*(Assumptions!$C$13+Assumptions!$F$45))*(1-Assumptions!$C$28)-V10*(V25+V24) -> -2.4396657 | W26: =(W19/(1+Assumptions!$C$10)-W19*(Assumptions!$C$13+Assumptions!$F$45))*(1-Assumptions!$C$28)-W10*(W25+W24) -> -2.4396657 | X26: =(X19/(1+Assumptions!$C$10)-X19*(Assumptions!$C$13+Assumptions!$F$45))*(1-Assumptions!$C$28)-X10*(X25+X24) -> -2.4396657 | Y26: =(Y19/(1+Assumptions!$C$10)-Y19*(Assumptions!$C$13+Assumptions!$F$45))*(1-Assumptions!$C$28)-Y10*(Y25+Y24) -> -2.4396657
A28: CUENTA DE RESULTADOS (€)
A29: Ventas a PVP (consumidor, IVA incl.) — informativo | C29: =C14*C19 -> 0 | D29: =D14*D19 -> 20000 | E29: =E14*E19 -> 30000 | F29: =F14*F19 -> 40000 | G29: =G14*G19 -> 50000 | I29: =I14*I19 -> 0 | J29: =J14*J19 -> 48000 | K29: =K14*K19 -> 84000 | L29: =L14*L19 -> 120000 | M29: =M14*M19 -> 156000 | O29: =O14*O19 -> 0 | P29: =P14*P19 -> 98000 | Q29: =Q14*Q19 -> 168000 | R29: =R14*R19 -> 252000 | S29: =S14*S19 -> 336000 | U29: =U14*U19 -> 0 | V29: =V14*V19 -> 48000 | W29: =W14*W19 -> 37268.519 | X29: =X14*X19 -> 0 | Y29: =Y14*Y19 -> 0
A30: Ventas a PVP sin IVA | C30: =C14*C19/(1+Assumptions!$C$10) -> 0 | D30: =D14*D19/(1+Assumptions!$C$10) -> 16528.926 | E30: =E14*E19/(1+Assumptions!$C$10) -> 24793.388 | F30: =F14*F19/(1+Assumptions!$C$10) -> 33057.851 | G30: =G14*G19/(1+Assumptions!$C$10) -> 41322.314 | I30: =I14*I19/(1+Assumptions!$C$10) -> 0 | J30: =J14*J19/(1+Assumptions!$C$10) -> 39669.421 | K30: =K14*K19/(1+Assumptions!$C$10) -> 69421.488 | L30: =L14*L19/(1+Assumptions!$C$10) -> 99173.554 | M30: =M14*M19/(1+Assumptions!$C$10) -> 128925.62 | O30: =O14*O19/(1+Assumptions!$C$10) -> 0 | P30: =P14*P19/(1+Assumptions!$C$10) -> 80991.736 | Q30: =Q14*Q19/(1+Assumptions!$C$10) -> 138842.98 | R30: =R14*R19/(1+Assumptions!$C$10) -> 208264.46 | S30: =S14*S19/(1+Assumptions!$C$10) -> 277685.95 | U30: =U14*U19/(1+Assumptions!$C$10) -> 0 | V30: =V14*V19/(1+Assumptions!$C$10) -> 39669.421 | W30: =W14*W19/(1+Assumptions!$C$10) -> 30800.429 | X30: =X14*X19/(1+Assumptions!$C$10) -> 0 | Y30: =Y14*Y19/(1+Assumptions!$C$10) -> 0
A31: (-) Margen expendedor | C31: =C14*C19*Assumptions!$C$13 -> 0 | D31: =D14*D19*Assumptions!$C$13 -> 1800 | E31: =E14*E19*Assumptions!$C$13 -> 2700 | F31: =F14*F19*Assumptions!$C$13 -> 3600 | G31: =G14*G19*Assumptions!$C$13 -> 4500 | I31: =I14*I19*Assumptions!$C$13 -> 0 | J31: =J14*J19*Assumptions!$C$13 -> 4320 | K31: =K14*K19*Assumptions!$C$13 -> 7560 | L31: =L14*L19*Assumptions!$C$13 -> 10800 | M31: =M14*M19*Assumptions!$C$13 -> 14040 | O31: =O14*O19*Assumptions!$C$13 -> 0 | P31: =P14*P19*Assumptions!$C$13 -> 8820 | Q31: =Q14*Q19*Assumptions!$C$13 -> 15120 | R31: =R14*R19*Assumptions!$C$13 -> 22680 | S31: =S14*S19*Assumptions!$C$13 -> 30240 | U31: =U14*U19*Assumptions!$C$13 -> 0 | V31: =V14*V19*Assumptions!$C$13 -> 4320 | W31: =W14*W19*Assumptions!$C$13 -> 3354.1667 | X31: =X14*X19*Assumptions!$C$13 -> 0 | Y31: =Y14*Y19*Assumptions!$C$13 -> 0
A32: (-) Tarifa distribuidor | C32: =C14*C19*Assumptions!$C$45 -> 0 | D32: =D14*D19*Assumptions!$C$45 -> 1200 | E32: =E14*E19*Assumptions!$C$45 -> 1800 | F32: =F14*F19*Assumptions!$C$45 -> 2400 | G32: =G14*G19*Assumptions!$C$45 -> 3000 | I32: =I14*I19*Assumptions!$D$45 -> 0 | J32: =J14*J19*Assumptions!$D$45 -> 2400 | K32: =K14*K19*Assumptions!$D$45 -> 4200 | L32: =L14*L19*Assumptions!$D$45 -> 6000 | M32: =M14*M19*Assumptions!$D$45 -> 7800 | O32: =O14*O19*Assumptions!$E$45 -> 0 | P32: =P14*P19*Assumptions!$E$45 -> 4410 | Q32: =Q14*Q19*Assumptions!$E$45 -> 7560 | R32: =R14*R19*Assumptions!$E$45 -> 11340 | S32: =S14*S19*Assumptions!$E$45 -> 15120 | U32: =U14*U19*Assumptions!$F$45 -> 0 | V32: =V14*V19*Assumptions!$F$45 -> 2880 | W32: =W14*W19*Assumptions!$F$45 -> 2236.1111 | X32: =X14*X19*Assumptions!$F$45 -> 0 | Y32: =Y14*Y19*Assumptions!$F$45 -> 0
A33: Ingresos de la marca (antes de IEE) | C33: =C30-C31-C32 -> 0 | D33: =D30-D31-D32 -> 13528.926 | E33: =E30-E31-E32 -> 20293.388 | F33: =F30-F31-F32 -> 27057.851 | G33: =G30-G31-G32 -> 33822.314 | I33: =I30-I31-I32 -> 0 | J33: =J30-J31-J32 -> 32949.421 | K33: =K30-K31-K32 -> 57661.488 | L33: =L30-L31-L32 -> 82373.554 | M33: =M30-M31-M32 -> 107085.62 | O33: =O30-O31-O32 -> 0 | P33: =P30-P31-P32 -> 67761.736 | Q33: =Q30-Q31-Q32 -> 116162.98 | R33: =R30-R31-R32 -> 174244.46 | S33: =S30-S31-S32 -> 232325.95 | U33: =U30-U31-U32 -> 0 | V33: =V30-V31-V32 -> 32469.421 | W33: =W30-W31-W32 -> 25210.151 | X33: =X30-X31-X32 -> 0 | Y33: =Y30-Y31-Y32 -> 0
A34: (-) Impuesto especial devengado | C34: =C15*C25 -> 0 | D34: =D15*D25 -> 3452.7158 | E34: =E15*E25 -> 5179.0737 | F34: =F15*F25 -> 6905.4316 | G34: =G15*G25 -> 8631.7895 | I34: =I15*I25 -> 0 | J34: =J15*J25 -> 8046.0767 | K34: =K15*K25 -> 14080.634 | L34: =L15*L25 -> 20115.192 | M34: =M15*M25 -> 26149.749 | O34: =O15*O25 -> 0 | P34: =P15*P25 -> 16187.1 | Q34: =Q15*Q25 -> 27749.314 | R34: =R15*R25 -> 41623.971 | S34: =S15*S25 -> 55498.629 | U34: =U15*U25 -> 0 | V34: =V15*V25 -> 8546.8383 | W34: =W15*W25 -> 6636 | X34: =X15*X25 -> 0 | Y34: =Y15*Y25 -> 0
A35: Ingresos netos de impuestos | C35: =C33-C34 -> 0 | D35: =D33-D34 -> 10076.21 | E35: =E33-E34 -> 15114.315 | F35: =F33-F34 -> 20152.42 | G35: =G33-G34 -> 25190.525 | I35: =I33-I34 -> 0 | J35: =J33-J34 -> 24903.345 | K35: =K33-K34 -> 43580.853 | L35: =L33-L34 -> 62258.362 | M35: =M33-M34 -> 80935.871 | O35: =O33-O34 -> 0 | P35: =P33-P34 -> 51574.636 | Q35: =Q33-Q34 -> 88413.661 | R35: =R33-R34 -> 132620.49 | S35: =S33-S34 -> 176827.32 | U35: =U33-U34 -> 0 | V35: =V33-V34 -> 23922.583 | W35: =W33-W34 -> 18574.151 | X35: =X33-X34 -> 0 | Y35: =Y33-Y34 -> 0
A36: (-) Coste de ventas (incl. merma y muestras) | C36: =C15*C24 -> 0 | D36: =D15*D24 -> 12786.573 | E36: =E15*E24 -> 19179.86 | F36: =F15*F24 -> 25573.146 | G36: =G15*G24 -> 31966.433 | I36: =I15*I24 -> 0 | J36: =J15*J24 -> 21407.864 | K36: =K15*K24 -> 37463.761 | L36: =L15*L24 -> 53519.659 | M36: =M15*M24 -> 69575.557 | O36: =O15*O24 -> 0 | P36: =P15*P24 -> 31012.668 | Q36: =Q15*Q24 -> 53164.573 | R36: =R15*R24 -> 79746.859 | S36: =S15*S24 -> 106329.15 | U36: =U15*U24 -> 0 | V36: =V15*V24 -> 28801.915 | W36: =W15*W24 -> 22362.598 | X36: =X15*X24 -> 0 | Y36: =Y15*Y24 -> 0
A37: (-) Gastos de despacho aduanero | C37: =IF(C13>0,Assumptions!$C$18*Assumptions!$C$17,0) -> 900 | D37: =IF(D13>0,Assumptions!$C$18*Assumptions!$C$17,0) -> 900 | E37: =IF(E13>0,Assumptions!$C$18*Assumptions!$C$17,0) -> 900 | F37: =IF(F13>0,Assumptions!$C$18*Assumptions!$C$17,0) -> 900 | G37: =IF(G13>0,Assumptions!$C$18*Assumptions!$C$17,0) -> 900 | I37: =IF(I13>0,Assumptions!$C$18*Assumptions!$C$17,0) -> 900 | J37: =IF(J13>0,Assumptions!$C$18*Assumptions!$C$17,0) -> 900 | K37: =IF(K13>0,Assumptions!$C$18*Assumptions!$C$17,0) -> 900 | L37: =IF(L13>0,Assumptions!$C$18*Assumptions!$C$17,0) -> 900 | M37: =IF(M13>0,Assumptions!$C$18*Assumptions!$C$17,0) -> 900 | O37: =IF(O13>0,Assumptions!$C$18*Assumptions!$C$17,0) -> 900 | P37: =IF(P13>0,Assumptions!$C$18*Assumptions!$C$17,0) -> 900 | Q37: =IF(Q13>0,Assumptions!$C$18*Assumptions!$C$17,0) -> 900 | R37: =IF(R13>0,Assumptions!$C$18*Assumptions!$C$17,0) -> 900 | S37: =IF(S13>0,Assumptions!$C$18*Assumptions!$C$17,0) -> 900 | U37: =IF(U13>0,Assumptions!$C$18*Assumptions!$C$17,0) -> 900 | V37: =IF(V13>0,Assumptions!$C$18*Assumptions!$C$17,0) -> 900 | W37: =IF(W13>0,Assumptions!$C$18*Assumptions!$C$17,0) -> 0 | X37: =IF(X13>0,Assumptions!$C$18*Assumptions!$C$17,0) -> 0 | Y37: =IF(Y13>0,Assumptions!$C$18*Assumptions!$C$17,0) -> 0
A38: (-) Royalty de nombre a Arnaldo | C38: =C33*Assumptions!$C$28 -> 0 | D38: =D33*Assumptions!$C$28 -> 0 | E38: =E33*Assumptions!$C$28 -> 0 | F38: =F33*Assumptions!$C$28 -> 0 | G38: =G33*Assumptions!$C$28 -> 0 | I38: =I33*Assumptions!$C$28 -> 0 | J38: =J33*Assumptions!$C$28 -> 0 | K38: =K33*Assumptions!$C$28 -> 0 | L38: =L33*Assumptions!$C$28 -> 0 | M38: =M33*Assumptions!$C$28 -> 0 | O38: =O33*Assumptions!$C$28 -> 0 | P38: =P33*Assumptions!$C$28 -> 0 | Q38: =Q33*Assumptions!$C$28 -> 0 | R38: =R33*Assumptions!$C$28 -> 0 | S38: =S33*Assumptions!$C$28 -> 0 | U38: =U33*Assumptions!$C$28 -> 0 | V38: =V33*Assumptions!$C$28 -> 0 | W38: =W33*Assumptions!$C$28 -> 0 | X38: =X33*Assumptions!$C$28 -> 0 | Y38: =Y33*Assumptions!$C$28 -> 0
A39: Margen bruto | C39: =C35-C36-C37-C38 -> -900 | D39: =D35-D36-D37-D38 -> -3610.3632 | E39: =E35-E36-E37-E38 -> -4965.5448 | F39: =F35-F36-F37-F38 -> -6320.7263 | G39: =G35-G36-G37-G38 -> -7675.9079 | I39: =I35-I36-I37-I38 -> -900 | J39: =J35-J36-J37-J38 -> 2595.4812 | K39: =K35-K36-K37-K38 -> 5217.0921 | L39: =L35-L36-L37-L38 -> 7838.703 | M39: =M35-M36-M37-M38 -> 10460.314 | O39: =O35-O36-O37-O38 -> -900 | P39: =P35-P36-P37-P38 -> 19661.968 | Q39: =Q35-Q36-Q37-Q38 -> 34349.088 | R39: =R35-R36-R37-R38 -> 51973.632 | S39: =S35-S36-S37-S38 -> 69598.176 | U39: =U35-U36-U37-U38 -> -900 | V39: =V35-V36-V37-V38 -> -5779.3314 | W39: =W35-W36-W37-W38 -> -3788.447 | X39: =X35-X36-X37-X38 -> 0 | Y39: =Y35-Y36-Y37-Y38 -> 0
A40: (-) Gastos fijos | C40: ='Operating Expenses'!$C$17*Assumptions!$C$50 -> 30233.5 | D40: ='Operating Expenses'!$D$17*Assumptions!$C$50 -> 26185.5 | E40: ='Operating Expenses'!$E$17*Assumptions!$C$50 -> 25679.5 | F40: ='Operating Expenses'!$F$17*Assumptions!$C$50 -> 27703.5 | G40: ='Operating Expenses'!$G$17*Assumptions!$C$50 -> 27956.5 | I40: ='Operating Expenses'!$C$17*Assumptions!$D$50 -> 26290 | J40: ='Operating Expenses'!$D$17*Assumptions!$D$50 -> 22770 | K40: ='Operating Expenses'!$E$17*Assumptions!$D$50 -> 22330 | L40: ='Operating Expenses'!$F$17*Assumptions!$D$50 -> 24090 | M40: ='Operating Expenses'!$G$17*Assumptions!$D$50 -> 24310 | O40: ='Operating Expenses'!$C$17*Assumptions!$E$50 -> 28919 | P40: ='Operating Expenses'!$D$17*Assumptions!$E$50 -> 25047 | Q40: ='Operating Expenses'!$E$17*Assumptions!$E$50 -> 24563 | R40: ='Operating Expenses'!$F$17*Assumptions!$E$50 -> 26499 | S40: ='Operating Expenses'!$G$17*Assumptions!$E$50 -> 26741 | U40: ='Operating Expenses'!$C$17*Assumptions!$F$50 -> 31548 | V40: ='Operating Expenses'!$D$17*Assumptions!$F$50 -> 27324 | W40: ='Operating Expenses'!$E$17*Assumptions!$F$50 -> 26796 | X40: ='Operating Expenses'!$F$17*Assumptions!$F$50 -> 28908 | Y40: ='Operating Expenses'!$G$17*Assumptions!$F$50 -> 29172
A41: EBITDA | C41: =C39-C40 -> -31133.5 | D41: =D39-D40 -> -29795.863 | E41: =E39-E40 -> -30645.045 | F41: =F39-F40 -> -34024.226 | G41: =G39-G40 -> -35632.408 | I41: =I39-I40 -> -27190 | J41: =J39-J40 -> -20174.519 | K41: =K39-K40 -> -17112.908 | L41: =L39-L40 -> -16251.297 | M41: =M39-M40 -> -13849.686 | O41: =O39-O40 -> -29819 | P41: =P39-P40 -> -5385.032 | Q41: =Q39-Q40 -> 9786.0879 | R41: =R39-R40 -> 25474.632 | S41: =S39-S40 -> 42857.176 | U41: =U39-U40 -> -32448 | V41: =V39-V40 -> -33103.331 | W41: =W39-W40 -> -30584.447 | X41: =X39-X40 -> -28908 | Y41: =Y39-Y40 -> -29172
A42: CAPEX intangible | C42: ='Operating Expenses'!$C$22 -> 13000 | D42: ='Operating Expenses'!$D$22 -> 0 | E42: ='Operating Expenses'!$E$22 -> 3000 | F42: ='Operating Expenses'!$F$22 -> 0 | G42: ='Operating Expenses'!$G$22 -> 0 | I42: ='Operating Expenses'!$C$22 -> 13000 | J42: ='Operating Expenses'!$D$22 -> 0 | K42: ='Operating Expenses'!$E$22 -> 3000 | L42: ='Operating Expenses'!$F$22 -> 0 | M42: ='Operating Expenses'!$G$22 -> 0 | O42: ='Operating Expenses'!$C$22 -> 13000 | P42: ='Operating Expenses'!$D$22 -> 0 | Q42: ='Operating Expenses'!$E$22 -> 3000 | R42: ='Operating Expenses'!$F$22 -> 0 | S42: ='Operating Expenses'!$G$22 -> 0 | U42: ='Operating Expenses'!$C$22 -> 13000 | V42: ='Operating Expenses'!$D$22 -> 0 | W42: ='Operating Expenses'!$E$22 -> 3000 | X42: ='Operating Expenses'!$F$22 -> 0 | Y42: ='Operating Expenses'!$G$22 -> 0
A43: CAPEX acumulado | C43: =0+C42 -> 13000 | D43: =C43+D42 -> 13000 | E43: =D43+E42 -> 16000 | F43: =E43+F42 -> 16000 | G43: =F43+G42 -> 16000 | I43: =0+I42 -> 13000 | J43: =I43+J42 -> 13000 | K43: =J43+K42 -> 16000 | L43: =K43+L42 -> 16000 | M43: =L43+M42 -> 16000 | O43: =0+O42 -> 13000 | P43: =O43+P42 -> 13000 | Q43: =P43+Q42 -> 16000 | R43: =Q43+R42 -> 16000 | S43: =R43+S42 -> 16000 | U43: =0+U42 -> 13000 | V43: =U43+V42 -> 13000 | W43: =V43+W42 -> 16000 | X43: =W43+X42 -> 16000 | Y43: =X43+Y42 -> 16000
A44: (-) Amortización | C44: =C43/Assumptions!$C$33 -> 2600 | D44: =D43/Assumptions!$C$33 -> 2600 | E44: =E43/Assumptions!$C$33 -> 3200 | F44: =F43/Assumptions!$C$33 -> 3200 | G44: =G43/Assumptions!$C$33 -> 3200 | I44: =I43/Assumptions!$C$33 -> 2600 | J44: =J43/Assumptions!$C$33 -> 2600 | K44: =K43/Assumptions!$C$33 -> 3200 | L44: =L43/Assumptions!$C$33 -> 3200 | M44: =M43/Assumptions!$C$33 -> 3200 | O44: =O43/Assumptions!$C$33 -> 2600 | P44: =P43/Assumptions!$C$33 -> 2600 | Q44: =Q43/Assumptions!$C$33 -> 3200 | R44: =R43/Assumptions!$C$33 -> 3200 | S44: =S43/Assumptions!$C$33 -> 3200 | U44: =U43/Assumptions!$C$33 -> 2600 | V44: =V43/Assumptions!$C$33 -> 2600 | W44: =W43/Assumptions!$C$33 -> 3200 | X44: =X43/Assumptions!$C$33 -> 3200 | Y44: =Y43/Assumptions!$C$33 -> 3200
A45: Amortización acumulada | C45: =0+C44 -> 2600 | D45: =C45+D44 -> 5200 | E45: =D45+E44 -> 8400 | F45: =E45+F44 -> 11600 | G45: =F45+G44 -> 14800 | I45: =0+I44 -> 2600 | J45: =I45+J44 -> 5200 | K45: =J45+K44 -> 8400 | L45: =K45+L44 -> 11600 | M45: =L45+M44 -> 14800 | O45: =0+O44 -> 2600 | P45: =O45+P44 -> 5200 | Q45: =P45+Q44 -> 8400 | R45: =Q45+R44 -> 11600 | S45: =R45+S44 -> 14800 | U45: =0+U44 -> 2600 | V45: =U45+V44 -> 5200 | W45: =V45+W44 -> 8400 | X45: =W45+X44 -> 11600 | Y45: =X45+Y44 -> 14800
A46: Intangible neto | C46: =C43-C45 -> 10400 | D46: =D43-D45 -> 7800 | E46: =E43-E45 -> 7600 | F46: =F43-F45 -> 4400 | G46: =G43-G45 -> 1200 | I46: =I43-I45 -> 10400 | J46: =J43-J45 -> 7800 | K46: =K43-K45 -> 7600 | L46: =L43-L45 -> 4400 | M46: =M43-M45 -> 1200 | O46: =O43-O45 -> 10400 | P46: =P43-P45 -> 7800 | Q46: =Q43-Q45 -> 7600 | R46: =R43-R45 -> 4400 | S46: =S43-S45 -> 1200 | U46: =U43-U45 -> 10400 | V46: =V43-V45 -> 7800 | W46: =W43-W45 -> 7600 | X46: =X43-X45 -> 4400 | Y46: =Y43-Y45 -> 1200
A47: EBIT | C47: =C41-C44 -> -33733.5 | D47: =D41-D44 -> -32395.863 | E47: =E41-E44 -> -33845.045 | F47: =F41-F44 -> -37224.226 | G47: =G41-G44 -> -38832.408 | I47: =I41-I44 -> -29790 | J47: =J41-J44 -> -22774.519 | K47: =K41-K44 -> -20312.908 | L47: =L41-L44 -> -19451.297 | M47: =M41-M44 -> -17049.686 | O47: =O41-O44 -> -32419 | P47: =P41-P44 -> -7985.032 | Q47: =Q41-Q44 -> 6586.0879 | R47: =R41-R44 -> 22274.632 | S47: =S41-S44 -> 39657.176 | U47: =U41-U44 -> -35048 | V47: =V41-V44 -> -35703.331 | W47: =W41-W44 -> -33784.447 | X47: =X41-X44 -> -32108 | Y47: =Y41-Y44 -> -32372
A48: (-) Gastos financieros (sobre deuda inicial del año) | C48: =0*Assumptions!$C$31 -> 0 | D48: =C75*Assumptions!$C$31 -> 504.82141 | E48: =D75*Assumptions!$C$31 -> 3123.9182 | F48: =E75*Assumptions!$C$31 -> 6113.9211 | G48: =F75*Assumptions!$C$31 -> 9289.3272 | I48: =0*Assumptions!$C$31 -> 0 | J48: =I75*Assumptions!$C$31 -> 831.42976 | K48: =J75*Assumptions!$C$31 -> 3531.901 | L48: =K75*Assumptions!$C$31 -> 6329.7101 | M48: =L75*Assumptions!$C$31 -> 8962.5491 | O48: =0*Assumptions!$C$31 -> 0 | P48: =O75*Assumptions!$C$31 -> 1687.528 | Q48: =P75*Assumptions!$C$31 -> 4139.6676 | R48: =Q75*Assumptions!$C$31 -> 5992.26 | S48: =R75*Assumptions!$C$31 -> 6624.9461 | U48: =0*Assumptions!$C$31 -> 0 | V48: =U75*Assumptions!$C$31 -> 1844.6491 | W48: =V75*Assumptions!$C$31 -> 4748.3321 | X48: =W75*Assumptions!$C$31 -> 5177.4532 | Y48: =X75*Assumptions!$C$31 -> 7380.6749
A49: Resultado antes de impuestos | C49: =C47-C48 -> -33733.5 | D49: =D47-D48 -> -32900.685 | E49: =E47-E48 -> -36968.963 | F49: =F47-F48 -> -43338.147 | G49: =G47-G48 -> -48121.735 | I49: =I47-I48 -> -29790 | J49: =J47-J48 -> -23605.949 | K49: =K47-K48 -> -23844.809 | L49: =L47-L48 -> -25781.007 | M49: =M47-M48 -> -26012.235 | O49: =O47-O48 -> -32419 | P49: =P47-P48 -> -9672.5601 | Q49: =Q47-Q48 -> 2446.4204 | R49: =R47-R48 -> 16282.372 | S49: =S47-S48 -> 33032.23 | U49: =U47-U48 -> -35048 | V49: =V47-V48 -> -37547.981 | W49: =W47-W48 -> -38532.779 | X49: =X47-X48 -> -37285.453 | Y49: =Y47-Y48 -> -39752.675
A50: Bases negativas pendientes (inicio) | C50: =0 -> 0 | D50: =C52 -> 33733.5 | E50: =D52 -> 66634.185 | F50: =E52 -> 103603.15 | G50: =F52 -> 146941.29 | I50: =0 -> 0 | J50: =I52 -> 29790 | K50: =J52 -> 53395.949 | L50: =K52 -> 77240.757 | M50: =L52 -> 103021.76 | O50: =0 -> 0 | P50: =O52 -> 32419 | Q50: =P52 -> 42091.56 | R50: =Q52 -> 39645.14 | S50: =R52 -> 23362.768 | U50: =0 -> 0 | V50: =U52 -> 35048 | W50: =V52 -> 72595.981 | X50: =W52 -> 111128.76 | Y50: =X52 -> 148414.21
A51: Base imponible tras compensación | C51: =MAX(0,C49-C50) -> 0 | D51: =MAX(0,D49-D50) -> 0 | E51: =MAX(0,E49-E50) -> 0 | F51: =MAX(0,F49-F50) -> 0 | G51: =MAX(0,G49-G50) -> 0 | I51: =MAX(0,I49-I50) -> 0 | J51: =MAX(0,J49-J50) -> 0 | K51: =MAX(0,K49-K50) -> 0 | L51: =MAX(0,L49-L50) -> 0 | M51: =MAX(0,M49-M50) -> 0 | O51: =MAX(0,O49-O50) -> 0 | P51: =MAX(0,P49-P50) -> 0 | Q51: =MAX(0,Q49-Q50) -> 0 | R51: =MAX(0,R49-R50) -> 0 | S51: =MAX(0,S49-S50) -> 9669.462 | U51: =MAX(0,U49-U50) -> 0 | V51: =MAX(0,V49-V50) -> 0 | W51: =MAX(0,W49-W50) -> 0 | X51: =MAX(0,X49-X50) -> 0 | Y51: =MAX(0,Y49-Y50) -> 0
A52: Bases negativas pendientes (cierre) | C52: =MAX(0,C50-MAX(C49,0))+MAX(-C49,0) -> 33733.5 | D52: =MAX(0,D50-MAX(D49,0))+MAX(-D49,0) -> 66634.185 | E52: =MAX(0,E50-MAX(E49,0))+MAX(-E49,0) -> 103603.15 | F52: =MAX(0,F50-MAX(F49,0))+MAX(-F49,0) -> 146941.29 | G52: =MAX(0,G50-MAX(G49,0))+MAX(-G49,0) -> 195063.03 | I52: =MAX(0,I50-MAX(I49,0))+MAX(-I49,0) -> 29790 | J52: =MAX(0,J50-MAX(J49,0))+MAX(-J49,0) -> 53395.949 | K52: =MAX(0,K50-MAX(K49,0))+MAX(-K49,0) -> 77240.757 | L52: =MAX(0,L50-MAX(L49,0))+MAX(-L49,0) -> 103021.76 | M52: =MAX(0,M50-MAX(M49,0))+MAX(-M49,0) -> 129034 | O52: =MAX(0,O50-MAX(O49,0))+MAX(-O49,0) -> 32419 | P52: =MAX(0,P50-MAX(P49,0))+MAX(-P49,0) -> 42091.56 | Q52: =MAX(0,Q50-MAX(Q49,0))+MAX(-Q49,0) -> 39645.14 | R52: =MAX(0,R50-MAX(R49,0))+MAX(-R49,0) -> 23362.768 | S52: =MAX(0,S50-MAX(S49,0))+MAX(-S49,0) -> 0 | U52: =MAX(0,U50-MAX(U49,0))+MAX(-U49,0) -> 35048 | V52: =MAX(0,V50-MAX(V49,0))+MAX(-V49,0) -> 72595.981 | W52: =MAX(0,W50-MAX(W49,0))+MAX(-W49,0) -> 111128.76 | X52: =MAX(0,X50-MAX(X49,0))+MAX(-X49,0) -> 148414.21 | Y52: =MAX(0,Y50-MAX(Y49,0))+MAX(-Y49,0) -> 188166.89
A53: (-) Impuesto sobre Sociedades | C53: =C51*Assumptions!$C$30 -> 0 | D53: =D51*Assumptions!$C$30 -> 0 | E53: =E51*Assumptions!$C$30 -> 0 | F53: =F51*Assumptions!$C$30 -> 0 | G53: =G51*Assumptions!$C$30 -> 0 | I53: =I51*Assumptions!$C$30 -> 0 | J53: =J51*Assumptions!$C$30 -> 0 | K53: =K51*Assumptions!$C$30 -> 0 | L53: =L51*Assumptions!$C$30 -> 0 | M53: =M51*Assumptions!$C$30 -> 0 | O53: =O51*Assumptions!$C$30 -> 0 | P53: =P51*Assumptions!$C$30 -> 0 | Q53: =Q51*Assumptions!$C$30 -> 0 | R53: =R51*Assumptions!$C$30 -> 0 | S53: =S51*Assumptions!$C$30 -> 2417.3655 | U53: =U51*Assumptions!$C$30 -> 0 | V53: =V51*Assumptions!$C$30 -> 0 | W53: =W51*Assumptions!$C$30 -> 0 | X53: =X51*Assumptions!$C$30 -> 0 | Y53: =Y51*Assumptions!$C$30 -> 0
A54: Resultado neto | C54: =C49-C53 -> -33733.5 | D54: =D49-D53 -> -32900.685 | E54: =E49-E53 -> -36968.963 | F54: =F49-F53 -> -43338.147 | G54: =G49-G53 -> -48121.735 | I54: =I49-I53 -> -29790 | J54: =J49-J53 -> -23605.949 | K54: =K49-K53 -> -23844.809 | L54: =L49-L53 -> -25781.007 | M54: =M49-M53 -> -26012.235 | O54: =O49-O53 -> -32419 | P54: =P49-P53 -> -9672.5601 | Q54: =Q49-Q53 -> 2446.4204 | R54: =R49-R53 -> 16282.372 | S54: =S49-S53 -> 30614.864 | U54: =U49-U53 -> -35048 | V54: =V49-V53 -> -37547.981 | W54: =W49-W53 -> -38532.779 | X54: =X49-X53 -> -37285.453 | Y54: =Y49-Y53 -> -39752.675
A56: CAPITAL CIRCULANTE (€, saldos a cierre)
A57: Existencias (coste en destino) | C57: =C16*C24 -> 5851.2738 | D57: =D16*D24 -> 8776.9107 | E57: =E16*E24 -> 11702.548 | F57: =F16*F24 -> 14628.184 | G57: =G16*G24 -> 14628.184 | I57: =I16*I24 -> 10089.218 | J57: =J16*J24 -> 17656.131 | K57: =K16*K24 -> 25223.044 | L57: =L16*L24 -> 32789.957 | M57: =M16*M24 -> 32789.957 | O57: =O16*O24 -> 14832.803 | P57: =P16*P24 -> 25427.663 | Q57: =Q16*Q24 -> 38141.495 | R57: =R16*R24 -> 50855.326 | S57: =S16*S24 -> 50855.326 | U57: =U16*U24 -> 12778.627 | V57: =V16*V24 -> 22362.598 | W57: =W16*W24 -> 0 | X57: =X16*X24 -> 0 | Y57: =Y16*Y24 -> 0
A58: IEE pagado en el año | C58: =IF(Assumptions!$C$26=1,C13,C15)*C25 -> 1580 | D58: =IF(Assumptions!$C$26=1,D13,D15)*D25 -> 4242.7158 | E58: =IF(Assumptions!$C$26=1,E13,E15)*E25 -> 5969.0737 | F58: =IF(Assumptions!$C$26=1,F13,F15)*F25 -> 7695.4316 | G58: =IF(Assumptions!$C$26=1,G13,G15)*G25 -> 8631.7895 | I58: =IF(Assumptions!$C$26=1,I13,I15)*I25 -> 3792 | J58: =IF(Assumptions!$C$26=1,J13,J15)*J25 -> 10890.077 | K58: =IF(Assumptions!$C$26=1,K13,K15)*K25 -> 16924.634 | L58: =IF(Assumptions!$C$26=1,L13,L15)*L25 -> 22959.192 | M58: =IF(Assumptions!$C$26=1,M13,M15)*M25 -> 26149.749 | O58: =IF(Assumptions!$C$26=1,O13,O15)*O25 -> 7742 | P58: =IF(Assumptions!$C$26=1,P13,P15)*P25 -> 21717.1 | Q58: =IF(Assumptions!$C$26=1,Q13,Q15)*Q25 -> 34385.314 | R58: =IF(Assumptions!$C$26=1,R13,R15)*R25 -> 48259.971 | S58: =IF(Assumptions!$C$26=1,S13,S15)*S25 -> 55498.629 | U58: =IF(Assumptions!$C$26=1,U13,U15)*U25 -> 3792 | V58: =IF(Assumptions!$C$26=1,V13,V15)*V25 -> 11390.838 | W58: =IF(Assumptions!$C$26=1,W13,W15)*W25 -> 0 | X58: =IF(Assumptions!$C$26=1,X13,X15)*X25 -> 0 | Y58: =IF(Assumptions!$C$26=1,Y13,Y15)*Y25 -> 0
A59: IEE anticipado sobre existencias | C59: =IF(Assumptions!$C$26=1,C16*C25,0) -> 1580 | D59: =IF(Assumptions!$C$26=1,D16*D25,0) -> 2370 | E59: =IF(Assumptions!$C$26=1,E16*E25,0) -> 3160 | F59: =IF(Assumptions!$C$26=1,F16*F25,0) -> 3950 | G59: =IF(Assumptions!$C$26=1,G16*G25,0) -> 3950 | I59: =IF(Assumptions!$C$26=1,I16*I25,0) -> 3792 | J59: =IF(Assumptions!$C$26=1,J16*J25,0) -> 6636 | K59: =IF(Assumptions!$C$26=1,K16*K25,0) -> 9480 | L59: =IF(Assumptions!$C$26=1,L16*L25,0) -> 12324 | M59: =IF(Assumptions!$C$26=1,M16*M25,0) -> 12324 | O59: =IF(Assumptions!$C$26=1,O16*O25,0) -> 7742 | P59: =IF(Assumptions!$C$26=1,P16*P25,0) -> 13272 | Q59: =IF(Assumptions!$C$26=1,Q16*Q25,0) -> 19908 | R59: =IF(Assumptions!$C$26=1,R16*R25,0) -> 26544 | S59: =IF(Assumptions!$C$26=1,S16*S25,0) -> 26544 | U59: =IF(Assumptions!$C$26=1,U16*U25,0) -> 3792 | V59: =IF(Assumptions!$C$26=1,V16*V25,0) -> 6636 | W59: =IF(Assumptions!$C$26=1,W16*W25,0) -> 0 | X59: =IF(Assumptions!$C$26=1,X16*X25,0) -> 0 | Y59: =IF(Assumptions!$C$26=1,Y16*Y25,0) -> 0
A60: Clientes (distribuidor) | C60: =C33*(1+Assumptions!$C$10)*Assumptions!$C$24/365 -> 0 | D60: =D33*(1+Assumptions!$C$10)*Assumptions!$C$24/365 -> 2018.2192 | E60: =E33*(1+Assumptions!$C$10)*Assumptions!$C$24/365 -> 3027.3288 | F60: =F33*(1+Assumptions!$C$10)*Assumptions!$C$24/365 -> 4036.4384 | G60: =G33*(1+Assumptions!$C$10)*Assumptions!$C$24/365 -> 5045.5479 | I60: =I33*(1+Assumptions!$C$10)*Assumptions!$C$24/365 -> 0 | J60: =J33*(1+Assumptions!$C$10)*Assumptions!$C$24/365 -> 4915.3315 | K60: =K33*(1+Assumptions!$C$10)*Assumptions!$C$24/365 -> 8601.8301 | L60: =L33*(1+Assumptions!$C$10)*Assumptions!$C$24/365 -> 12288.329 | M60: =M33*(1+Assumptions!$C$10)*Assumptions!$C$24/365 -> 15974.827 | O60: =O33*(1+Assumptions!$C$10)*Assumptions!$C$24/365 -> 0 | P60: =P33*(1+Assumptions!$C$10)*Assumptions!$C$24/365 -> 10108.566 | Q60: =Q33*(1+Assumptions!$C$10)*Assumptions!$C$24/365 -> 17328.97 | R60: =R33*(1+Assumptions!$C$10)*Assumptions!$C$24/365 -> 25993.455 | S60: =S33*(1+Assumptions!$C$10)*Assumptions!$C$24/365 -> 34657.94 | U60: =U33*(1+Assumptions!$C$10)*Assumptions!$C$24/365 -> 0 | V60: =V33*(1+Assumptions!$C$10)*Assumptions!$C$24/365 -> 4843.726 | W60: =W33*(1+Assumptions!$C$10)*Assumptions!$C$24/365 -> 3760.8019 | X60: =X33*(1+Assumptions!$C$10)*Assumptions!$C$24/365 -> 0 | Y60: =Y33*(1+Assumptions!$C$10)*Assumptions!$C$24/365 -> 0
A61: Anticipos a fábrica (pedidos en curso) | C61: =Assumptions!$C$23*D13*(D20+D21+Assumptions!$C$42)*MIN(1,Assumptions!$C$48/12) -> 2753.0515 | D61: =Assumptions!$C$23*E13*(E20+E21+Assumptions!$C$42)*MIN(1,Assumptions!$C$48/12) -> 3873.266 | E61: =Assumptions!$C$23*F13*(F20+F21+Assumptions!$C$42)*MIN(1,Assumptions!$C$48/12) -> 4993.4806 | F61: =Assumptions!$C$23*G13*(G20+G21+Assumptions!$C$42)*MIN(1,Assumptions!$C$48/12) -> 5601.0729 | G61: =Assumptions!$C$23*G13*(G20+G21+Assumptions!$C$42)*MIN(1,Assumptions!$C$48/12) -> 5601.0729 | I61: =Assumptions!$C$23*J13*(J20+J21+Assumptions!$D$42)*MIN(1,Assumptions!$D$48/12) -> 4258.3585 | J61: =Assumptions!$C$23*K13*(K20+K21+Assumptions!$D$42)*MIN(1,Assumptions!$D$48/12) -> 6618.058 | K61: =Assumptions!$C$23*L13*(L20+L21+Assumptions!$D$42)*MIN(1,Assumptions!$D$48/12) -> 8977.7575 | L61: =Assumptions!$C$23*M13*(M20+M21+Assumptions!$D$42)*MIN(1,Assumptions!$D$48/12) -> 10225.365 | M61: =Assumptions!$C$23*M13*(M20+M21+Assumptions!$D$42)*MIN(1,Assumptions!$D$48/12) -> 10225.365 | O61: =Assumptions!$C$23*P13*(P20+P21+Assumptions!$E$42)*MIN(1,Assumptions!$E$48/12) -> 4935.7854 | P61: =Assumptions!$C$23*Q13*(Q20+Q21+Assumptions!$E$42)*MIN(1,Assumptions!$E$48/12) -> 7814.9722 | Q61: =Assumptions!$C$23*R13*(R20+R21+Assumptions!$E$42)*MIN(1,Assumptions!$E$48/12) -> 10968.355 | R61: =Assumptions!$C$23*S13*(S20+S21+Assumptions!$E$42)*MIN(1,Assumptions!$E$48/12) -> 12613.531 | S61: =Assumptions!$C$23*S13*(S20+S21+Assumptions!$E$42)*MIN(1,Assumptions!$E$48/12) -> 12613.531 | U61: =Assumptions!$C$23*V13*(V20+V21+Assumptions!$F$42)*MIN(1,Assumptions!$F$48/12) -> 11079.106 | V61: =Assumptions!$C$23*W13*(W20+W21+Assumptions!$F$42)*MIN(1,Assumptions!$F$48/12) -> 0 | W61: =Assumptions!$C$23*X13*(X20+X21+Assumptions!$F$42)*MIN(1,Assumptions!$F$48/12) -> 0 | X61: =Assumptions!$C$23*Y13*(Y20+Y21+Assumptions!$F$42)*MIN(1,Assumptions!$F$48/12) -> 0 | Y61: =Assumptions!$C$23*Y13*(Y20+Y21+Assumptions!$F$42)*MIN(1,Assumptions!$F$48/12) -> 0
A62: IVA de importación soportado en el año | C62: =(C13*(C22+C23)+C58)*Assumptions!$C$10 -> 1515.4175 | D62: =(D13*(D22+D23)+D58)*Assumptions!$C$10 -> 4069.2948 | E62: =(E13*(E22+E23)+E58)*Assumptions!$C$10 -> 5725.0878 | F62: =(F13*(F22+F23)+F58)*Assumptions!$C$10 -> 7380.8808 | G62: =(G13*(G22+G23)+G58)*Assumptions!$C$10 -> 8278.965 | I62: =(I13*(I22+I23)+I58)*Assumptions!$C$10 -> 2835.2557 | J62: =(J13*(J22+J23)+J58)*Assumptions!$C$10 -> 8142.4452 | K62: =(K13*(K22+K23)+K58)*Assumptions!$C$10 -> 12654.448 | L62: =(L13*(L22+L23)+L58)*Assumptions!$C$10 -> 17166.45 | M62: =(M13*(M22+M23)+M58)*Assumptions!$C$10 -> 19552.011 | O62: =(O13*(O22+O23)+O58)*Assumptions!$C$10 -> 4619.4337 | P62: =(P13*(P22+P23)+P58)*Assumptions!$C$10 -> 12957.983 | Q62: =(Q13*(Q22+Q23)+Q58)*Assumptions!$C$10 -> 20516.75 | R62: =(R13*(R22+R23)+R58)*Assumptions!$C$10 -> 28795.368 | S62: =(S13*(S22+S23)+S58)*Assumptions!$C$10 -> 33114.471 | U62: =(U13*(U22+U23)+U58)*Assumptions!$C$10 -> 3389.5317 | V62: =(V13*(V22+V23)+V58)*Assumptions!$C$10 -> 10181.859 | W62: =(W13*(W22+W23)+W58)*Assumptions!$C$10 -> 0 | X62: =(X13*(X22+X23)+X58)*Assumptions!$C$10 -> 0 | Y62: =(Y13*(Y22+Y23)+Y58)*Assumptions!$C$10 -> 0
A63: Hacienda deudora por IVA | C63: =C62*Assumptions!$C$27 -> 378.85437 | D63: =D62*Assumptions!$C$27 -> 1017.3237 | E63: =E62*Assumptions!$C$27 -> 1431.2719 | F63: =F62*Assumptions!$C$27 -> 1845.2202 | G63: =G62*Assumptions!$C$27 -> 2069.7413 | I63: =I62*Assumptions!$C$27 -> 708.81392 | J63: =J62*Assumptions!$C$27 -> 2035.6113 | K63: =K62*Assumptions!$C$27 -> 3163.6119 | L63: =L62*Assumptions!$C$27 -> 4291.6126 | M63: =M62*Assumptions!$C$27 -> 4888.0027 | O63: =O62*Assumptions!$C$27 -> 1154.8584 | P63: =P62*Assumptions!$C$27 -> 3239.4957 | Q63: =Q62*Assumptions!$C$27 -> 5129.1876 | R63: =R62*Assumptions!$C$27 -> 7198.842 | S63: =S62*Assumptions!$C$27 -> 8278.6178 | U63: =U62*Assumptions!$C$27 -> 847.38293 | V63: =V62*Assumptions!$C$27 -> 2545.4646 | W63: =W62*Assumptions!$C$27 -> 0 | X63: =X62*Assumptions!$C$27 -> 0 | Y63: =Y62*Assumptions!$C$27 -> 0
A64: Proveedores de gastos generales | C64: =C40*Assumptions!$C$25/365 -> 2484.9452 | D64: =D40*Assumptions!$C$25/365 -> 2152.2329 | E64: =E40*Assumptions!$C$25/365 -> 2110.6438 | F64: =F40*Assumptions!$C$25/365 -> 2277 | G64: =G40*Assumptions!$C$25/365 -> 2297.7945 | I64: =I40*Assumptions!$C$25/365 -> 2160.8219 | J64: =J40*Assumptions!$C$25/365 -> 1871.5068 | K64: =K40*Assumptions!$C$25/365 -> 1835.3425 | L64: =L40*Assumptions!$C$25/365 -> 1980 | M64: =M40*Assumptions!$C$25/365 -> 1998.0822 | O64: =O40*Assumptions!$C$25/365 -> 2376.9041 | P64: =P40*Assumptions!$C$25/365 -> 2058.6575 | Q64: =Q40*Assumptions!$C$25/365 -> 2018.8767 | R64: =R40*Assumptions!$C$25/365 -> 2178 | S64: =S40*Assumptions!$C$25/365 -> 2197.8904 | U64: =U40*Assumptions!$C$25/365 -> 2592.9863 | V64: =V40*Assumptions!$C$25/365 -> 2245.8082 | W64: =W40*Assumptions!$C$25/365 -> 2202.411 | X64: =X40*Assumptions!$C$25/365 -> 2376 | Y64: =Y40*Assumptions!$C$25/365 -> 2397.6986
A65: IVA repercutido en el año | C65: =C33*Assumptions!$C$10 -> 0 | D65: =D33*Assumptions!$C$10 -> 2841.0744 | E65: =E33*Assumptions!$C$10 -> 4261.6116 | F65: =F33*Assumptions!$C$10 -> 5682.1488 | G65: =G33*Assumptions!$C$10 -> 7102.686 | I65: =I33*Assumptions!$C$10 -> 0 | J65: =J33*Assumptions!$C$10 -> 6919.3785 | K65: =K33*Assumptions!$C$10 -> 12108.912 | L65: =L33*Assumptions!$C$10 -> 17298.446 | M65: =M33*Assumptions!$C$10 -> 22487.98 | O65: =O33*Assumptions!$C$10 -> 0 | P65: =P33*Assumptions!$C$10 -> 14229.964 | Q65: =Q33*Assumptions!$C$10 -> 24394.225 | R65: =R33*Assumptions!$C$10 -> 36591.337 | S65: =S33*Assumptions!$C$10 -> 48788.45 | U65: =U33*Assumptions!$C$10 -> 0 | V65: =V33*Assumptions!$C$10 -> 6818.5785 | W65: =W33*Assumptions!$C$10 -> 5294.1317 | X65: =X33*Assumptions!$C$10 -> 0 | Y65: =Y33*Assumptions!$C$10 -> 0
A66: Hacienda acreedora por IVA | C66: =C65*Assumptions!$C$27 -> 0 | D66: =D65*Assumptions!$C$27 -> 710.2686 | E66: =E65*Assumptions!$C$27 -> 1065.4029 | F66: =F65*Assumptions!$C$27 -> 1420.5372 | G66: =G65*Assumptions!$C$27 -> 1775.6715 | I66: =I65*Assumptions!$C$27 -> 0 | J66: =J65*Assumptions!$C$27 -> 1729.8446 | K66: =K65*Assumptions!$C$27 -> 3027.2281 | L66: =L65*Assumptions!$C$27 -> 4324.6116 | M66: =M65*Assumptions!$C$27 -> 5621.995 | O66: =O65*Assumptions!$C$27 -> 0 | P66: =P65*Assumptions!$C$27 -> 3557.4911 | Q66: =Q65*Assumptions!$C$27 -> 6098.5562 | R66: =R65*Assumptions!$C$27 -> 9147.8343 | S66: =S65*Assumptions!$C$27 -> 12197.112 | U66: =U65*Assumptions!$C$27 -> 0 | V66: =V65*Assumptions!$C$27 -> 1704.6446 | W66: =W65*Assumptions!$C$27 -> 1323.5329 | X66: =X65*Assumptions!$C$27 -> 0 | Y66: =Y65*Assumptions!$C$27 -> 0
A67: Capital circulante neto | C67: =C57+C59+C60+C61+C63-C64-C66 -> 8078.2344 | D67: =D57+D59+D60+D61+D63-D64-D66 -> 15193.218 | E67: =E57+E59+E60+E61+E63-E64-E66 -> 21138.582 | F67: =F57+F59+F60+F61+F63-F64-F66 -> 26363.379 | G67: =G57+G59+G60+G61+G63-G64-G66 -> 27221.081 | I67: =I57+I59+I60+I61+I63-I64-I66 -> 16687.568 | J67: =J57+J59+J60+J61+J63-J64-J66 -> 34259.78 | K67: =K57+K59+K60+K61+K63-K64-K66 -> 50583.673 | L67: =L57+L59+L60+L61+L63-L64-L66 -> 65614.652 | M67: =M57+M59+M60+M61+M63-M64-M66 -> 68582.075 | O67: =O57+O59+O60+O61+O63-O64-O66 -> 26288.543 | P67: =P57+P59+P60+P61+P63-P64-P66 -> 54246.548 | Q67: =Q57+Q59+Q60+Q61+Q63-Q64-Q66 -> 83358.574 | R67: =R57+R59+R60+R61+R63-R64-R66 -> 111879.32 | S67: =S57+S59+S60+S61+S63-S64-S66 -> 118554.41 | U67: =U57+U59+U60+U61+U63-U64-U66 -> 25904.13 | V67: =V57+V59+V60+V61+V63-V64-V66 -> 32437.336 | W67: =W57+W59+W60+W61+W63-W64-W66 -> 234.85807 | X67: =X57+X59+X60+X61+X63-X64-X66 -> -2376 | Y67: =Y57+Y59+Y60+Y61+Y63-Y64-Y66 -> -2397.6986
A68: Variación del circulante | C68: =C67-0 -> 8078.2344 | D68: =D67-C67 -> 7114.9837 | E68: =E67-D67 -> 5945.3641 | F68: =F67-E67 -> 5224.7966 | G68: =G67-F67 -> 857.70184 | I68: =I67-0 -> 16687.568 | J68: =J67-I67 -> 17572.212 | K68: =K67-J67 -> 16323.893 | L68: =L67-K67 -> 15030.979 | M68: =M67-L67 -> 2967.4232 | O68: =O67-0 -> 26288.543 | P68: =P67-O67 -> 27958.005 | Q68: =Q67-P67 -> 29112.026 | R68: =R67-Q67 -> 28520.746 | S68: =S67-R67 -> 6675.0922 | U68: =U67-0 -> 25904.13 | V68: =V67-U67 -> 6533.2055 | W68: =W67-V67 -> -32202.477 | X68: =X67-W67 -> -2610.8581 | Y68: =Y67-X67 -> -21.69863
A70: FLUJOS DE CAJA Y FINANCIACIÓN (€)
A71: Flujo de explotación | C71: =C54+C44-C68 -> -39211.734 | D71: =D54+D44-D68 -> -37415.668 | E71: =E54+E44-E68 -> -39714.327 | F71: =F54+F44-F68 -> -45362.944 | G71: =G54+G44-G68 -> -45779.437 | I71: =I54+I44-I68 -> -43877.568 | J71: =J54+J44-J68 -> -38578.161 | K71: =K54+K44-K68 -> -36968.702 | L71: =L54+L44-L68 -> -37611.986 | M71: =M54+M44-M68 -> -25779.658 | O71: =O54+O44-O68 -> -56107.543 | P71: =P54+P44-P68 -> -35030.565 | Q71: =Q54+Q44-Q68 -> -23465.606 | R71: =R54+R44-R68 -> -9038.3739 | S71: =S54+S44-S68 -> 27139.772 | U71: =U54+U44-U68 -> -58352.13 | V71: =V54+V44-V68 -> -41481.186 | W71: =W54+W44-W68 -> -3130.3016 | X71: =X54+X44-X68 -> -31474.595 | Y71: =Y54+Y44-Y68 -> -36530.976
A72: Flujo de inversión | C72: =-C42 -> -13000 | D72: =-D42 -> 0 | E72: =-E42 -> -3000 | F72: =-F42 -> 0 | G72: =-G42 -> 0 | I72: =-I42 -> -13000 | J72: =-J42 -> 0 | K72: =-K42 -> -3000 | L72: =-L42 -> 0 | M72: =-M42 -> 0 | O72: =-O42 -> -13000 | P72: =-P42 -> 0 | Q72: =-Q42 -> -3000 | R72: =-R42 -> 0 | S72: =-S42 -> 0 | U72: =-U42 -> -13000 | V72: =-V42 -> 0 | W72: =-W42 -> -3000 | X72: =-X42 -> 0 | Y72: =-Y42 -> 0
A73: Aportación de capital | C73: =IF(0=0,Assumptions!$C$9,0) -> 50000 | D73: =IF(1=0,Assumptions!$C$9,0) -> 0 | E73: =IF(2=0,Assumptions!$C$9,0) -> 0 | F73: =IF(3=0,Assumptions!$C$9,0) -> 0 | G73: =IF(4=0,Assumptions!$C$9,0) -> 0 | I73: =IF(0=0,Assumptions!$C$9,0) -> 50000 | J73: =IF(1=0,Assumptions!$C$9,0) -> 0 | K73: =IF(2=0,Assumptions!$C$9,0) -> 0 | L73: =IF(3=0,Assumptions!$C$9,0) -> 0 | M73: =IF(4=0,Assumptions!$C$9,0) -> 0 | O73: =IF(0=0,Assumptions!$C$9,0) -> 50000 | P73: =IF(1=0,Assumptions!$C$9,0) -> 0 | Q73: =IF(2=0,Assumptions!$C$9,0) -> 0 | R73: =IF(3=0,Assumptions!$C$9,0) -> 0 | S73: =IF(4=0,Assumptions!$C$9,0) -> 0 | U73: =IF(0=0,Assumptions!$C$9,0) -> 50000 | V73: =IF(1=0,Assumptions!$C$9,0) -> 0 | W73: =IF(2=0,Assumptions!$C$9,0) -> 0 | X73: =IF(3=0,Assumptions!$C$9,0) -> 0 | Y73: =IF(4=0,Assumptions!$C$9,0) -> 0
A74: Posición neta de caja antes de financiación ajena | C74: =0-0+C71+C72+C73 -> -2211.7344 | D74: =C77-C75+D71+D72+D73 -> -39627.403 | E74: =D77-D75+E71+E72+E73 -> -82341.73 | F74: =E77-E75+F71+F72+F73 -> -127704.67 | G74: =F77-F75+G71+G72+G73 -> -173484.11 | I74: =0-0+I71+I72+I73 -> -6877.5681 | J74: =I77-I75+J71+J72+J73 -> -45455.729 | K74: =J77-J75+K71+K72+K73 -> -85424.431 | L74: =K77-K75+L71+L72+L73 -> -123036.42 | M74: =L77-L75+M71+M72+M73 -> -148816.07 | O74: =0-0+O71+O72+O73 -> -19107.543 | P74: =O77-O75+P71+P72+P73 -> -54138.108 | Q74: =P77-P75+Q71+Q72+Q73 -> -80603.714 | R74: =Q77-Q75+R71+R72+R73 -> -89642.088 | S74: =R77-R75+S71+S72+S73 -> -62502.316 | U74: =0-0+U71+U72+U73 -> -21352.13 | V74: =U77-U75+V71+V72+V73 -> -62833.316 | W74: =V77-V75+W71+W72+W73 -> -68963.618 | X74: =W77-W75+X71+X72+X73 -> -100438.21 | Y74: =X77-X75+Y71+Y72+Y73 -> -136969.19
A75: Financiación ajena necesaria (saldo) | C75: =MAX(0,Assumptions!$C$32-C74) -> 7211.7344 | D75: =MAX(0,Assumptions!$C$32-D74) -> 44627.403 | E75: =MAX(0,Assumptions!$C$32-E74) -> 87341.73 | F75: =MAX(0,Assumptions!$C$32-F74) -> 132704.67 | G75: =MAX(0,Assumptions!$C$32-G74) -> 178484.11 | I75: =MAX(0,Assumptions!$C$32-I74) -> 11877.568 | J75: =MAX(0,Assumptions!$C$32-J74) -> 50455.729 | K75: =MAX(0,Assumptions!$C$32-K74) -> 90424.431 | L75: =MAX(0,Assumptions!$C$32-L74) -> 128036.42 | M75: =MAX(0,Assumptions!$C$32-M74) -> 153816.07 | O75: =MAX(0,Assumptions!$C$32-O74) -> 24107.543 | P75: =MAX(0,Assumptions!$C$32-P74) -> 59138.108 | Q75: =MAX(0,Assumptions!$C$32-Q74) -> 85603.714 | R75: =MAX(0,Assumptions!$C$32-R74) -> 94642.088 | S75: =MAX(0,Assumptions!$C$32-S74) -> 67502.316 | U75: =MAX(0,Assumptions!$C$32-U74) -> 26352.13 | V75: =MAX(0,Assumptions!$C$32-V74) -> 67833.316 | W75: =MAX(0,Assumptions!$C$32-W74) -> 73963.618 | X75: =MAX(0,Assumptions!$C$32-X74) -> 105438.21 | Y75: =MAX(0,Assumptions!$C$32-Y74) -> 141969.19
A76: Disposición / (devolución) de financiación | C76: =C75-0 -> 7211.7344 | D76: =D75-C75 -> 37415.668 | E76: =E75-D75 -> 42714.327 | F76: =F75-E75 -> 45362.944 | G76: =G75-F75 -> 45779.437 | I76: =I75-0 -> 11877.568 | J76: =J75-I75 -> 38578.161 | K76: =K75-J75 -> 39968.702 | L76: =L75-K75 -> 37611.986 | M76: =M75-L75 -> 25779.658 | O76: =O75-0 -> 24107.543 | P76: =P75-O75 -> 35030.565 | Q76: =Q75-P75 -> 26465.606 | R76: =R75-Q75 -> 9038.3739 | S76: =S75-R75 -> -27139.772 | U76: =U75-0 -> 26352.13 | V76: =V75-U75 -> 41481.186 | W76: =W75-V75 -> 6130.3016 | X76: =X75-W75 -> 31474.595 | Y76: =Y75-X75 -> 36530.976
A77: Caja final | C77: =C74+C75 -> 5000 | D77: =D74+D75 -> 5000 | E77: =E74+E75 -> 5000 | F77: =F74+F75 -> 5000 | G77: =G74+G75 -> 5000 | I77: =I74+I75 -> 5000 | J77: =J74+J75 -> 5000 | K77: =K74+K75 -> 5000 | L77: =L74+L75 -> 5000 | M77: =M74+M75 -> 5000 | O77: =O74+O75 -> 5000 | P77: =P74+P75 -> 5000 | Q77: =Q74+Q75 -> 5000 | R77: =R74+R75 -> 5000 | S77: =S74+S75 -> 5000 | U77: =U74+U75 -> 5000 | V77: =V74+V75 -> 5000 | W77: =W74+W75 -> 5000 | X77: =X74+X75 -> 5000 | Y77: =Y74+Y75 -> 5000
A79: BALANCE (€)
A80: Total activo | C80: =C77+C57+C59+C60+C61+C63+C46 -> 25963.18 | D80: =D77+D57+D59+D60+D61+D63+D46 -> 30855.72 | E80: =E77+E57+E59+E60+E61+E63+E46 -> 36914.629 | F80: =F77+F57+F59+F60+F61+F63+F46 -> 39460.916 | G80: =G77+G57+G59+G60+G61+G63+G46 -> 37494.547 | I80: =I77+I57+I59+I60+I61+I63+I46 -> 34248.39 | J80: =J77+J57+J59+J60+J61+J63+J46 -> 50661.132 | K80: =K77+K57+K59+K60+K61+K63+K46 -> 68046.244 | L80: =L77+L57+L59+L60+L61+L63+L46 -> 81319.263 | M80: =M77+M57+M59+M60+M61+M63+M46 -> 82402.152 | O80: =O77+O57+O59+O60+O61+O63+O46 -> 44065.447 | P80: =P77+P57+P59+P60+P61+P63+P46 -> 72662.697 | Q80: =Q77+Q57+Q59+Q60+Q61+Q63+Q46 -> 104076.01 | R80: =R77+R57+R59+R60+R61+R63+R46 -> 132605.15 | S80: =S77+S57+S59+S60+S61+S63+S46 -> 139149.41 | U80: =U77+U57+U59+U60+U61+U63+U46 -> 43897.116 | V80: =V77+V57+V59+V60+V61+V63+V46 -> 49187.788 | W80: =W77+W57+W59+W60+W61+W63+W46 -> 16360.802 | X80: =X77+X57+X59+X60+X61+X63+X46 -> 9400 | Y80: =Y77+Y57+Y59+Y60+Y61+Y63+Y46 -> 6200
A81: Total pasivo exigible | C81: =C64+C66+C75 -> 9696.6796 | D81: =D64+D66+D75 -> 47489.904 | E81: =E64+E66+E75 -> 90517.776 | F81: =F64+F66+F75 -> 136402.21 | G81: =G64+G66+G75 -> 182557.58 | I81: =I64+I66+I75 -> 14038.39 | J81: =J64+J66+J75 -> 54057.08 | K81: =K64+K66+K75 -> 95287.001 | L81: =L64+L66+L75 -> 134341.03 | M81: =M64+M66+M75 -> 161436.15 | O81: =O64+O66+O75 -> 26484.447 | P81: =P64+P66+P75 -> 64754.257 | Q81: =Q64+Q66+Q75 -> 93721.147 | R81: =R64+R66+R75 -> 105967.92 | S81: =S64+S66+S75 -> 81897.318 | U81: =U64+U66+U75 -> 28945.116 | V81: =V64+V66+V75 -> 71783.769 | W81: =W64+W66+W75 -> 77489.562 | X81: =X64+X66+X75 -> 107814.21 | Y81: =Y64+Y66+Y75 -> 144366.89
A82: Resultados acumulados | C82: =0+C54 -> -33733.5 | D82: =C82+D54 -> -66634.185 | E82: =D82+E54 -> -103603.15 | F82: =E82+F54 -> -146941.29 | G82: =F82+G54 -> -195063.03 | I82: =0+I54 -> -29790 | J82: =I82+J54 -> -53395.949 | K82: =J82+K54 -> -77240.757 | L82: =K82+L54 -> -103021.76 | M82: =L82+M54 -> -129034 | O82: =0+O54 -> -32419 | P82: =O82+P54 -> -42091.56 | Q82: =P82+Q54 -> -39645.14 | R82: =Q82+R54 -> -23362.768 | S82: =R82+S54 -> 7252.0965 | U82: =0+U54 -> -35048 | V82: =U82+V54 -> -72595.981 | W82: =V82+W54 -> -111128.76 | X82: =W82+X54 -> -148414.21 | Y82: =X82+Y54 -> -188166.89
A83: Patrimonio neto | C83: =Assumptions!$C$9+C82 -> 16266.5 | D83: =Assumptions!$C$9+D82 -> -16634.185 | E83: =Assumptions!$C$9+E82 -> -53603.148 | F83: =Assumptions!$C$9+F82 -> -96941.295 | G83: =Assumptions!$C$9+G82 -> -145063.03 | I83: =Assumptions!$C$9+I82 -> 20210 | J83: =Assumptions!$C$9+J82 -> -3395.9486 | K83: =Assumptions!$C$9+K82 -> -27240.757 | L83: =Assumptions!$C$9+L82 -> -53021.765 | M83: =Assumptions!$C$9+M82 -> -79034 | O83: =Assumptions!$C$9+O82 -> 17581 | P83: =Assumptions!$C$9+P82 -> 7908.4399 | Q83: =Assumptions!$C$9+Q82 -> 10354.86 | R83: =Assumptions!$C$9+R82 -> 26637.232 | S83: =Assumptions!$C$9+S82 -> 57252.096 | U83: =Assumptions!$C$9+U82 -> 14952 | V83: =Assumptions!$C$9+V82 -> -22595.981 | W83: =Assumptions!$C$9+W82 -> -61128.76 | X83: =Assumptions!$C$9+X82 -> -98414.213 | Y83: =Assumptions!$C$9+Y82 -> -138166.89
A84: CONTROL: Activo − Pasivo − PN (debe ser 0) | C84: =ROUND(C80-C81-C83,2) -> 0 | D84: =ROUND(D80-D81-D83,2) -> 0 | E84: =ROUND(E80-E81-E83,2) -> 0 | F84: =ROUND(F80-F81-F83,2) -> 0 | G84: =ROUND(G80-G81-G83,2) -> 0 | I84: =ROUND(I80-I81-I83,2) -> 0 | J84: =ROUND(J80-J81-J83,2) -> 0 | K84: =ROUND(K80-K81-K83,2) -> 0 | L84: =ROUND(L80-L81-L83,2) -> 0 | M84: =ROUND(M80-M81-M83,2) -> 0 | O84: =ROUND(O80-O81-O83,2) -> 0 | P84: =ROUND(P80-P81-P83,2) -> 0 | Q84: =ROUND(Q80-Q81-Q83,2) -> 0 | R84: =ROUND(R80-R81-R83,2) -> 0 | S84: =ROUND(S80-S81-S83,2) -> 0 | U84: =ROUND(U80-U81-U83,2) -> 0 | V84: =ROUND(V80-V81-V83,2) -> 0 | W84: =ROUND(W80-W81-W83,2) -> 0 | X84: =ROUND(X80-X81-X83,2) -> 0 | Y84: =ROUND(Y80-Y81-Y83,2) -> 0
A86: RENTABILIDAD (€)
A87: Flujo de caja libre del proyecto (sin financiación) | C87: =C41-C53-C68-C42 -> -52211.734 | D87: =D41-D53-D68-D42 -> -36910.847 | E87: =E41-E53-E68-E42 -> -39590.409 | F87: =F41-F53-F68-F42 -> -39249.023 | G87: =G41-G53-G68-G42 -> -36490.11 | I87: =I41-I53-I68-I42 -> -56877.568 | J87: =J41-J53-J68-J42 -> -37746.731 | K87: =K41-K53-K68-K42 -> -36436.801 | L87: =L41-L53-L68-L42 -> -31282.276 | M87: =M41-M53-M68-M42 -> -16817.109 | O87: =O41-O53-O68-O42 -> -69107.543 | P87: =P41-P53-P68-P42 -> -33343.037 | Q87: =Q41-Q53-Q68-Q42 -> -22325.938 | R87: =R41-R53-R68-R42 -> -3046.1139 | S87: =S41-S53-S68-S42 -> 33764.718 | U87: =U41-U53-U68-U42 -> -71352.13 | V87: =V41-V53-V68-V42 -> -39636.537 | W87: =W41-W53-W68-W42 -> -1381.9695 | X87: =X41-X53-X68-X42 -> -26297.142 | Y87: =Y41-Y53-Y68-Y42 -> -29150.301
A88: FCF acumulado | C88: =0+C87 -> -52211.734 | D88: =C88+D87 -> -89122.581 | E88: =D88+E87 -> -128712.99 | F88: =E88+F87 -> -167962.01 | G88: =F88+G87 -> -204452.12 | I88: =0+I87 -> -56877.568 | J88: =I88+J87 -> -94624.299 | K88: =J88+K87 -> -131061.1 | L88: =K88+L87 -> -162343.38 | M88: =L88+M87 -> -179160.48 | O88: =0+O87 -> -69107.543 | P88: =O88+P87 -> -102450.58 | Q88: =P88+Q87 -> -124776.52 | R88: =Q88+R87 -> -127822.63 | S88: =R88+S87 -> -94057.914 | U88: =0+U87 -> -71352.13 | V88: =U88+V87 -> -110988.67 | W88: =V88+W87 -> -112370.64 | X88: =W88+X87 -> -138667.78 | Y88: =X88+Y87 -> -167818.08
A89: Valor terminal (sólo 2031; EBITDA>0 × múltiplo) | C89: =IF(0=4,MAX(0,C41)*Assumptions!$C$35,0) -> 0 | D89: =IF(1=4,MAX(0,D41)*Assumptions!$C$35,0) -> 0 | E89: =IF(2=4,MAX(0,E41)*Assumptions!$C$35,0) -> 0 | F89: =IF(3=4,MAX(0,F41)*Assumptions!$C$35,0) -> 0 | G89: =IF(4=4,MAX(0,G41)*Assumptions!$C$35,0) -> 0 | I89: =IF(0=4,MAX(0,I41)*Assumptions!$C$35,0) -> 0 | J89: =IF(1=4,MAX(0,J41)*Assumptions!$C$35,0) -> 0 | K89: =IF(2=4,MAX(0,K41)*Assumptions!$C$35,0) -> 0 | L89: =IF(3=4,MAX(0,L41)*Assumptions!$C$35,0) -> 0 | M89: =IF(4=4,MAX(0,M41)*Assumptions!$C$35,0) -> 0 | O89: =IF(0=4,MAX(0,O41)*Assumptions!$C$35,0) -> 0 | P89: =IF(1=4,MAX(0,P41)*Assumptions!$C$35,0) -> 0 | Q89: =IF(2=4,MAX(0,Q41)*Assumptions!$C$35,0) -> 0 | R89: =IF(3=4,MAX(0,R41)*Assumptions!$C$35,0) -> 0 | S89: =IF(4=4,MAX(0,S41)*Assumptions!$C$35,0) -> 214285.88 | U89: =IF(0=4,MAX(0,U41)*Assumptions!$C$35,0) -> 0 | V89: =IF(1=4,MAX(0,V41)*Assumptions!$C$35,0) -> 0 | W89: =IF(2=4,MAX(0,W41)*Assumptions!$C$35,0) -> 0 | X89: =IF(3=4,MAX(0,X41)*Assumptions!$C$35,0) -> 0 | Y89: =IF(4=4,MAX(0,Y41)*Assumptions!$C$35,0) -> 0
A90: FCF + valor terminal | C90: =C87+C89 -> -52211.734 | D90: =D87+D89 -> -36910.847 | E90: =E87+E89 -> -39590.409 | F90: =F87+F89 -> -39249.023 | G90: =G87+G89 -> -36490.11 | I90: =I87+I89 -> -56877.568 | J90: =J87+J89 -> -37746.731 | K90: =K87+K89 -> -36436.801 | L90: =L87+L89 -> -31282.276 | M90: =M87+M89 -> -16817.109 | O90: =O87+O89 -> -69107.543 | P90: =P87+P89 -> -33343.037 | Q90: =Q87+Q89 -> -22325.938 | R90: =R87+R89 -> -3046.1139 | S90: =S87+S89 -> 248050.6 | U90: =U87+U89 -> -71352.13 | V90: =V87+V89 -> -39636.537 | W90: =W87+W89 -> -1381.9695 | X90: =X87+X89 -> -26297.142 | Y90: =Y87+Y89 -> -29150.301
A91: Factor de descuento (fin de año) | C91: =1/(1+Assumptions!$C$34)^(0+1) -> 0.84745763 | D91: =1/(1+Assumptions!$C$34)^(1+1) -> 0.71818443 | E91: =1/(1+Assumptions!$C$34)^(2+1) -> 0.60863087 | F91: =1/(1+Assumptions!$C$34)^(3+1) -> 0.51578888 | G91: =1/(1+Assumptions!$C$34)^(4+1) -> 0.43710922 | I91: =1/(1+Assumptions!$C$34)^(0+1) -> 0.84745763 | J91: =1/(1+Assumptions!$C$34)^(1+1) -> 0.71818443 | K91: =1/(1+Assumptions!$C$34)^(2+1) -> 0.60863087 | L91: =1/(1+Assumptions!$C$34)^(3+1) -> 0.51578888 | M91: =1/(1+Assumptions!$C$34)^(4+1) -> 0.43710922 | O91: =1/(1+Assumptions!$C$34)^(0+1) -> 0.84745763 | P91: =1/(1+Assumptions!$C$34)^(1+1) -> 0.71818443 | Q91: =1/(1+Assumptions!$C$34)^(2+1) -> 0.60863087 | R91: =1/(1+Assumptions!$C$34)^(3+1) -> 0.51578888 | S91: =1/(1+Assumptions!$C$34)^(4+1) -> 0.43710922 | U91: =1/(1+Assumptions!$C$34)^(0+1) -> 0.84745763 | V91: =1/(1+Assumptions!$C$34)^(1+1) -> 0.71818443 | W91: =1/(1+Assumptions!$C$34)^(2+1) -> 0.60863087 | X91: =1/(1+Assumptions!$C$34)^(3+1) -> 0.51578888 | Y91: =1/(1+Assumptions!$C$34)^(4+1) -> 0.43710922
A92: Valor actual | C92: =C90*C91 -> -44247.233 | D92: =D90*D91 -> -26508.796 | E92: =E90*E91 -> -24095.945 | F92: =F90*F91 -> -20244.209 | G92: =G90*G91 -> -15950.163 | I92: =I90*I91 -> -48201.329 | J92: =J90*J91 -> -27109.114 | K92: =K90*K91 -> -22176.562 | L92: =L90*L91 -> -16135.05 | M92: =M90*M91 -> -7350.9135 | O92: =O90*O91 -> -58565.715 | P92: =P90*P91 -> -23946.45 | Q92: =Q90*Q91 -> -13588.255 | R92: =R90*R91 -> -1571.1517 | S92: =S90*S91 -> 108425.2 | U92: =U90*U91 -> -60467.907 | V92: =V90*V91 -> -28466.344 | W92: =W90*W91 -> -841.1093 | X92: =X90*X91 -> -13563.773 | Y92: =Y90*Y91 -> -12741.865
A93: Año de recuperación (si ocurre) | C93: =IF(AND(C88>=0,-1<0),C7,"") | D93: =IF(AND(D88>=0,C88<0),D7,"") | E93: =IF(AND(E88>=0,D88<0),E7,"") | F93: =IF(AND(F88>=0,E88<0),F7,"") | G93: =IF(AND(G88>=0,F88<0),G7,"") | I93: =IF(AND(I88>=0,-1<0),I7,"") | J93: =IF(AND(J88>=0,I88<0),J7,"") | K93: =IF(AND(K88>=0,J88<0),K7,"") | L93: =IF(AND(L88>=0,K88<0),L7,"") | M93: =IF(AND(M88>=0,L88<0),M7,"") | O93: =IF(AND(O88>=0,-1<0),O7,"") | P93: =IF(AND(P88>=0,O88<0),P7,"") | Q93: =IF(AND(Q88>=0,P88<0),Q7,"") | R93: =IF(AND(R88>=0,Q88<0),R7,"") | S93: =IF(AND(S88>=0,R88<0),S7,"") | U93: =IF(AND(U88>=0,-1<0),U7,"") | V93: =IF(AND(V88>=0,U88<0),V7,"") | W93: =IF(AND(W88>=0,V88<0),W7,"") | X93: =IF(AND(X88>=0,W88<0),X7,"") | Y93: =IF(AND(Y88>=0,X88<0),Y7,"")
