Workbook

Sheet Dashboard
A1: Proyecto B — Importación premium · Dashboard
A2: Decisiones por vía y cifras clave (fórmulas).
A4: Indicador | B4: Valor
A5: Oferta Behike: precio ofertado / PVP oficial | B5: ='Oferta Behike 56'!B7 -> 0.019047619
A6: Oferta Behike: valor oficial del lote supuesto | B6: ='Oferta Behike 56'!B11 -> 52500
A7: B3: contribución por unidad | B7: ='B3 Importador no cubano'!B22 -> 3.939629
A8: B3: contribución / PVP | B8: ='B3 Importador no cubano'!B23 -> 0.26264193
A9: B3: caja inmovilizada lote mediano | B9: ='B3 Importador no cubano'!C29 -> 44404.565
A10: B3: beneficio por operación lote mediano | B10: ='B3 Importador no cubano'!C33 -> 21255.637
A11: B3: unidades/año para punto muerto | B11: ='B3 Importador no cubano'!C39 -> 4721.2568
A12: B2: rentabilidad sobre inversión (referencia) | B12: ='B2 Expendeduría'!B11 -> -0.016
A14: Decisión Proyecto B: NO-GO a Habanos directo y a la oferta Behike; GO condicionado sólo para B3 tras validar exclusiva de fabricante y 10 cartas de interés de expendedurías especialistas.

Sheet Supuestos
A1: Supuestos — Proyecto B (importación y distribución premium)
A2: Valores azules editables. Fecha de corte 10/10/2026.
B3: Supuesto editable (input) | C3: Fórmula | D3: Resultado clave | E3: Alerta / bloqueo
A5: Parámetro | B5: Valor | C5: Estado | D5: Fuente
A6: IVA | B6: 0.21 | C6: VERIFICADO | D6: Ley 37/1992
A7: IEE cigarros (ad valorem sobre PVP) | B7: 0.158 | C7: VERIFICADO | D7: S14
A8: IEE mínimo (€/1.000 u) | B8: 47 | C8: VERIFICADO | D8: S14
A9: Margen expendedor | B9: 0.09 | C9: PROBABLE | D9: S15
A10: Arancel 2402 10 00 sin preferencia (p.ej. Cuba) | B10: 0.26 | C10: PROBABLE | D10: S32
A11: Arancel con preferencia (R. Dominicana EPA / Centroamérica AA) con prueba de origen | B11: 0 | C11: PROBABLE | D11: S33; confirmar TARIC
A12: USD por EUR | B12: 1.15 | C12: HIPÓTESIS
A13: Marcas fiscales + identificador único (€/u) | B13: 0.03 | C13: HIPÓTESIS | D13: S27, S28
A14: Despacho por envío (€) | B14: 450 | C14: HIPÓTESIS
A15: Notificación EU-CEG + ficha por nueva referencia (€) | B15: 600 | C15: HIPÓTESIS | D15: S29; cotizar consultor
A16: Gastos fijos anuales del importador-distribuidor (€) | B16: 18000 | C16: HIPÓTESIS | D16: Gestoría, seguros, almacén, comercial, software
A17: Coste de oportunidad del capital inmovilizado (anual) | B17: 0.08 | C17: HIPÓTESIS
A18: Cohiba Behike BHK 56 — PVP expendeduría por unidad (mar-2026) | B18: 262.5 | C18: PROBABLE | D18: S19 (coherente con S20)
A19: Oferta recibida por el promotor — precio por caja de 10 | B19: 50 | C19: HIPÓTESIS | D19: No verificada; comunicada verbalmente
A20: Umbral penal del contrabando de labores de tabaco (€) | B20: 15000 | C20: PROBABLE | D20: N01

Sheet Oferta Behike 56
A1: Análisis de la oferta 'Cohiba Behike 56 a ~50 € la caja de 10'
A2: No se calcula beneficio: sin procedencia, autenticidad, disponibilidad legal y derecho de distribución acreditados, el 'margen' no existe.
A4: Cajas que se ofrecerían (supuesto para dimensionar el riesgo) | B4: 20
A5: PVP oficial en expendeduría por caja de 10 | B5: =Supuestos!$B$18*10 -> 2625
A6: Precio ofertado por caja | B6: =Supuestos!$B$19 -> 50
A7: Precio ofertado / PVP oficial | B7: =B6/B5 -> 0.019047619
A8: Descuento implícito | B8: =1-B7 -> 0.98095238
A9: IVA + IEE contenidos en el PVP oficial de una caja | B9: =B5*Supuestos!$B$6/(1+Supuestos!$B$6)+B5*Supuestos!$B$7 -> 870.32851
A10: ¿El precio ofertado cubre siquiera los impuestos españoles de la caja? | B10: =IF(B6>=B9,"Sí","NO: el precio no cubre ni el 6% del IVA+IEE que soporta la caja") -> NO: el precio no cubre ni el 6% del IVA+IEE que soporta la caja
A11: Valor oficial de la mercancía del lote | B11: =B4*B5 -> 52500
A12: ¿Supera el umbral penal de contrabando de tabaco? | B12: =IF(B11>=Supuestos!$B$20,"SÍ: exposición penal (LO 12/1995)","No: infracción administrativa") -> SÍ: exposición penal (LO 12/1995)
A13: Formato comercial legítimo conocido | B13: Caja de 10 unidades con sello de garantía holográfico, código único y estampado 'Hecho en Cuba' (S20, S36)
A14: Cajas de 25 o sin sello / sin código verificable | B14: Indicador típico de falsificación (S20)
A17: Hipótesis explicativas de un precio del ~2% del PVP (de más a menos probable)
A18: Hipótesis | B18: Probabilidad cualitativa | C18: Consecuencia
A19: Falsificación (relleno de tabaco no Habanos, anillas y cajas copiadas) | B19: Muy alta | C19: Delito contra la propiedad industrial (art. 274 CP); decomiso
A20: Producto auténtico desviado o sustraído de la cadena estatal cubana | B20: Alta | C20: Receptación/contrabando; decomiso; sin derecho de venta
A21: Producto auténtico de 'segunda' / rechazos de fábrica sin sello | B21: Media | C21: Exportación ilegal desde Cuba (Res. 98/2022, S09); no comercializable en España
A22: Error de comunicación (precio por unidad de otra referencia, o divisa) | B22: Baja | C22: Verificar por escrito antes de cualquier conversación adicional
A23: Oferta legítima de un exportador autorizado | B23: Prácticamente nula | C23: Habanos no vende a 2% del PVP; los Behike tienen asignación limitada
A26: DECISIÓN: NO-GO absoluto. No negociar, no pagar señal, no recibir muestras, no transportar en equipaje. Ver 'Authenticity & Provenance Protocol.pdf'.

Sheet B1 Habanos directo
A1: B1 — Importación directa de Habanos (Cohiba, Trinidad, Montecristo, Partagás...)
A2: Evaluación de acceso. No se modeliza margen porque la vía no es legalmente accesible para un tercero.
A4: Pregunta | B4: Respuesta | C4: Estado | D4: Fuente
A5: ¿Puede una SL española comprar directamente a Habanos S.A.? | B5: No, salvo ser nombrada distribuidor exclusivo por Habanos para un territorio. | C5: PROBABLE | D5: S01, S02, S21
A6: Distribuidor exclusivo en España (salvo Canarias) | B6: Tabacalera S.L.U. | C6: VERIFICADO | D6: S21
A7: Situación del distribuidor exclusivo (2026) | B7: Cuentas bloqueadas por sanciones UE a su accionista indirecto Chen Zhi (30/07/2026); pagos con autorización del Tesoro. | C7: VERIFICADO | D7: S21, S23
A8: ¿Importación paralela de Habanos genuinos comprados en Cuba u otro país no-EEE? | B8: Infringe la marca: el agotamiento en la UE es regional (EEE). Requiere consentimiento del titular. | C8: PROBABLE | D8: N02
A9: ¿Compra a otro distribuidor de la UE (comercio intracomunitario)? | B9: Agotamiento en el EEE permite reventa de producto puesto legítimamente en el mercado del EEE, pero en España la venta al por menor es monopolio de expendedurías y el mayorista necesita habilitación CMT, marcas fiscales españolas y precio publicado en BOE. | C9: PROBABLE | D9: N02, S17, S18, S27
A10: ¿Ediciones regionales propias? | B10: Sólo las solicita el distribuidor exclusivo; mínimo 25.000 unidades por referencia. | C10: PROBABLE | D10: S02
A11: ¿Subastas o reventa de colección en España? | B11: La venta al consumidor fuera de expendedurías no está permitida; las subastas internacionales operan fuera de España. | C11: PROBABLE | D11: S16, S26
A12: CONCLUSIÓN | B12: NO-GO para importación directa. Vía legal residual: operar como expendeduría (B2) o como distribuidor intracomunitario habilitado de stock legítimo del EEE (muy limitada y dependiente de que existan márgenes). | C12: PROBABLE

Sheet B3 Importador no cubano
A1: B3 — Importador-distribuidor habilitado de puros premium no cubanos (R. Dominicana, Nicaragua, Honduras)
A2: Requiere acuerdo de distribución exclusiva con un fabricante que hoy no tenga distribución en España. Lotes por referencia.
A5: Origen preferente (1 = con preferencia arancelaria, 0 = sin preferencia) | B5: 1
A6: PVP por unidad (€) | B6: 15
A7: Precio de compra FOB por unidad (USD), caja incluida | B7: 3.8
A8: Flete + seguro + manipulación por unidad (€) | B8: 0.35
A9: Tarifa distribuidor logístico (Logista u otro) % PVP | B9: 0.05
A10: Merma + muestras (% sobre ventas) | B10: 0.05
A11: Referencias nuevas por año (notificación EU-CEG) | B11: 4
A13: Economía unitaria
A14: IVA incluido | B14: =B6*Supuestos!$B$6/(1+Supuestos!$B$6) -> 2.6033058
A15: IEE | B15: =MAX(Supuestos!$B$7*B6,Supuestos!$B$8/1000) -> 2.37
A16: Margen expendedor | B16: =B6*Supuestos!$B$9 -> 1.35
A17: Tarifa distribuidor logístico | B17: =B6*B9 -> 0.75
A18: Ingreso del importador antes de IEE | B18: =B6-B14-B16-B17 -> 10.296694
A19: Coste CIF por unidad | B19: =B7/Supuestos!$B$12+B8 -> 3.6543478
A20: Arancel | B20: =B19*IF(B5=1,Supuestos!$B$11,Supuestos!$B$10) -> 0
A21: Coste en destino (CIF + arancel + marcas) | B21: =B19+B20+Supuestos!$B$13 -> 3.6843478
A22: Contribución por unidad (tras IEE, coste y merma) | B22: =B18-(1+B10)*(B15+B21) -> 3.939629
A23: Contribución / PVP | B23: =B22/B6 -> 0.26264193
A25: Operaciones por tamaño de lote
A26: Concepto | B26: Lote pequeño | C26: Lote mediano | D26: Lote grande
A27: Unidades del lote | B27: 2000 | C27: 6000 | D27: 15000
A28: Meses para vender el lote (rotación) | B28: 6 | C28: 9 | D28: 12
A29: Caja inmovilizada al importar (coste en destino + IEE + IVA importación) | B29: =B27*($B$21+$B$15)*(1+Supuestos!$B$6)+Supuestos!$B$14 -> 15101.522 | C29: =C27*($B$21+$B$15)*(1+Supuestos!$B$6)+Supuestos!$B$14 -> 44404.565 | D29: =D27*($B$21+$B$15)*(1+Supuestos!$B$6)+Supuestos!$B$14 -> 110336.41
A30: Contribución del lote | B30: =B27*$B$22 -> 7879.258 | C30: =C27*$B$22 -> 23637.774 | D30: =D27*$B$22 -> 59094.435
A31: (-) Despacho y notificaciones atribuibles al lote | B31: =Supuestos!$B$14+Supuestos!$B$15 -> 1050 | C31: =Supuestos!$B$14+Supuestos!$B$15 -> 1050 | D31: =Supuestos!$B$14+Supuestos!$B$15 -> 1050
A32: (-) Coste del capital inmovilizado (medio, durante la rotación) | B32: =B29/2*Supuestos!$B$17*B28/12 -> 302.03043 | C32: =C29/2*Supuestos!$B$17*C28/12 -> 1332.137 | D32: =D29/2*Supuestos!$B$17*D28/12 -> 4413.4565
A33: Beneficio por operación (antes de gastos fijos) | B33: =B30-B31-B32 -> 6527.2276 | C33: =C30-C31-C32 -> 21255.637 | D33: =D30-D31-D32 -> 53630.978
A34: Rentabilidad por operación sobre caja inmovilizada | B34: =IFERROR(B33/B29,0) -> 0.43222317 | C34: =IFERROR(C33/C29,0) -> 0.47868135 | D34: =IFERROR(D33/D29,0) -> 0.48606781
A35: Operaciones al año (12 / rotación) | B35: =12/B28 -> 2 | C35: =12/C28 -> 1.3333333 | D35: =12/D28 -> 1
A36: Beneficio anual antes de fijos (una referencia) | B36: =B33*B35 -> 13054.455 | C36: =C33*C35 -> 28340.849 | D36: =D33*D35 -> 53630.978
A37: Gastos fijos anuales del importador | B37: =Supuestos!$B$16 -> 18000 | C37: =Supuestos!$B$16 -> 18000 | D37: =Supuestos!$B$16 -> 18000
A38: Referencias necesarias para cubrir fijos | B38: =IFERROR(B37/B36,"n/a") -> 1.3788396 | C38: =IFERROR(C37/C36,"n/a") -> 0.63512564 | D38: =IFERROR(D37/D36,"n/a") -> 0.33562692
A39: Unidades/año para punto muerto | B39: =IFERROR((B37+Supuestos!$B$14*B35)/$B$22,"n/a") -> 4797.4061 | C39: =IFERROR((C37+Supuestos!$B$14*C35)/$B$22,"n/a") -> 4721.2568 | D39: =IFERROR((D37+Supuestos!$B$14*D35)/$B$22,"n/a") -> 4683.1821
A40: Beneficio por caja de 20 unidades | B40: =$B$22*20 -> 78.79258 | C40: =$B$22*20 -> 78.79258 | D40: =$B$22*20 -> 78.79258
A41: Escenario NO-GO de esta vía: si ningún fabricante concede exclusiva para España o si el distribuidor logístico exige >8% del PVP, la contribución cae por debajo de 2 €/u (ver 'Comparativa').

Sheet B2 Expendeduría
A1: B2 — Explotar una expendeduría especializada (canal minorista legal de Habanos)
A2: Referencia económica. La titularidad es personal (persona física) y exige gestión directa: incompatible a priori con el traslado del promotor a Andorra.
A4: Ventas anuales de puros premium (PVP con impuestos, €) | B4: 400000
A5: Margen legal del expendedor sobre PVP | B5: =Supuestos!$B$9 -> 0.09
A6: Margen bruto de puros (€) | B6: =B4*B5 -> 36000
A7: Otras labores y productos (margen bruto, €) | B7: 30000
A8: Gastos de explotación (personal, local, humidor, seguros) € | B8: 70000
A9: Resultado antes de impuestos (€) | B9: =B6+B7-B8 -> -4000
A10: Inversión: adquisición/traspaso de la concesión + local + humidor (€) | B10: 250000
A11: Rentabilidad sobre inversión | B11: =IFERROR(B9/B10,0) -> -0.016
A13: Estado: HIPÓTESIS en todos los importes salvo el margen. El precio de una transmisión de expendeduría y los requisitos personales deben confirmarse con el CMT (RD 1199/1999).
A14: Aprovisionamiento de Habanos depende del distribuidor exclusivo (Tabacalera), hoy afectado por sanciones (S21).

Sheet Comparativa
A1: Comparativa de vías del Proyecto B
A4: Vía | B4: Acceso legal | C4: Capital | D4: Margen potencial | E4: Barrera principal | F4: Decisión
A5: B1 Importación directa de Habanos | B5: No accesible | C5: — | D5: — | E5: Exclusiva de Habanos/Tabacalera; importación paralela = infracción de marca | F5: NO-GO
A6: B1' Distribución intracomunitaria de Habanos del EEE | B6: Muy limitada | C6: Alto | D6: Bajo | E6: Requiere habilitación, marcas fiscales españolas y precio BOE; margen comprimido por precios oficiales | F6: NO-GO salvo oportunidad documentada
A7: B2 Expendeduría especializada | B7: Legal (titular persona física) | C7: 200–300 k€ (HIPÓTESIS) | D7: Bajo-medio | E7: Incompatible con residencia en Andorra; aprovisionamiento afectado por sanciones a Tabacalera | F7: NO prioritaria
A8: B3 Importador de marcas no cubanas | B8: Legal con habilitación CMT | C8: 30–75 k€ | D8: Medio | E8: Requiere exclusiva de fabricante y aceptación del distribuidor logístico | F8: GO condicionado a validación
A9: Oferta Behike 56 a 50 €/caja | B9: Ilegal / no acreditada | C9: — | D9: — | E9: Falsificación o desvío casi seguros | F9: NO-GO absoluto
A11: Contribución unitaria B3 con los supuestos actuales (€/u) | B11: ='B3 Importador no cubano'!B22 -> 3.939629
A12: Unidades/año punto muerto B3 (lote mediano) | B12: ='B3 Importador no cubano'!C39 -> 4721.2568

Sheet Fuentes
A1: Fuentes (consulta 10/10/2026)
A3: ID | B3: Fuente | C3: Dato | D3: Estado | E3: URL
A4: S01 | B4: Habanos S.A. — ficha enciclopédica | C4: Habanos S.A. (1994) controla promoción, distribución y exportación mundial de puros premium cubanos; estructura 50/50 Cubatabaco / socio privado. | D4: VERIFICADO (con S05, S21) | E4: https://en.wikipedia.org/wiki/Habanos_S.A.
A5: S02 | B5: Cigar Aficionado — New Cuban cigars / Regional Editions | C5: Ediciones Regionales: las solicitan distribuidores exclusivos; compra de 25.000 unidades por referencia; exclusividad regional >= 2 años. | D5: PROBABLE | E5: https://www.cigaraficionado.com/article/new-cuban-cigars-from-habanos
A6: S09 | B6: Directorio Cubano — Nota de la Aduana de Cuba sobre decomisos | C6: Exportación de tabaco torcido regulada por la Resolución 98/2022 del MINAG; viajeros: hasta 20 unidades sueltas sin documentación; más, con factura de tienda autorizada. | D6: PROBABLE | E6: https://www.directoriocubano.info/cuba/nota-informativa-de-la-aduana-de-cuba-sobre-nuevos-decomisos-en-el-aeropuerto-jose-marti-de-la-habana/
A7: S14 | B7: Agencia Tributaria — Novedades Ley 7/2024 en Impuestos Especiales (vigor 2025) | C7: Cigarros y cigarritos: 15,8% sobre PVP; mínimo 47 €/1.000 unidades. | D7: VERIFICADO | E7: https://sede.agenciatributaria.gob.es/Sede/impuestos-especiales-medioambientales/novedades-impuestos-especiales-medioambientales/2024/diciembre/26/novedades-ley-72024-materia-impuestos-2025.html
A8: S15 | B8: Ley 13/1998 de Ordenación del Mercado de Tabacos (BOE-A-1998-10407) | C8: Margen de expendedores: 8,5% general; cigarros 9% (texto original). Pendiente confirmar redacción consolidada vigente. | D8: PROBABLE | E8: https://www.boe.es/buscar/doc.php?id=BOE-A-1998-10407
A9: S16 | B9: Real Decreto 1199/1999 (consolidado BOE, últ. act. 10/07/2025) | C9: Desarrolla Ley 13/1998: estatuto concesional de expendedurías; art. 31 remite a márgenes de la Ley; libertad de fabricación, importación y mayorista con habilitación. | D9: VERIFICADO | E9: https://www.boe.es/buscar/act.php?id=BOE-A-1999-15353
A10: S17 | B10: Comisionado para el Mercado de Tabacos — Guía para operadores mayoristas (v. 28/10/2024) | C10: Habilitación como fabricante (incluye titulares de marca e importadores) y como distribuidor: plazo máximo de resolución 15 días hábiles; obligaciones de información mensual/anual. | D10: VERIFICADO | E10: https://www.hacienda.gob.es/es-ES/Areas%20Tematicas/CMTabacos/Paginas/MayoristasCMT.aspx
A11: S18 | B11: BOE — Resoluciones del CMT de precios de venta al público 2026 (p.ej. BOE-A-2026-12799, BOE-A-2026-16756) | C11: Los PVP de cada labor se publican por resolución del CMT en el BOE antes de su aplicación en expendedurías. | D11: VERIFICADO | E11: https://www.boe.es/diario_boe/txt.php?id=BOE-A-2026-12799
A12: S19 | B12: Tabacon.es — Cohiba Behike BHK 56 (10) | C12: PVP expendeduría (mar-2026): 262,50 €/unidad; caja de 10: 2.625 €; punto de venta con recargo: 301,90 €/u. | D12: PROBABLE (coherente con S20) | E12: https://tabacon.es/tabacos/cohiba-behike-bhk-56-10/
A13: S20 | B13: Cigar Aficionado — Ten facts about Cohiba Behike / price increases | C13: Behike auténtico sólo en cajas de 10; las cajas de 25 son falsificación habitual; en 2023 BHK 56 en España a 250 €/u. | D13: VERIFICADO (2 artículos) | E13: https://www.cigaraficionado.com/article/ten-facts-about-cohiba-behike-cuba-s-top-cigar-brand
A14: S21 | B14: 14ymedio / Periódico Cubano / Directorio Cubano — congelación de cuentas de Tabacalera (2026) | C14: Tabacalera S.L.U., distribuidor exclusivo de Habanos en España (salvo Canarias), con cuentas bloqueadas por sanciones UE a Chen Zhi (30/07/2026); pagos sujetos a autorización del Tesoro. | D14: VERIFICADO (3 medios) | E14: https://www.14ymedio.com/internacional/autoridades-espanolas-congelan-cuentas-tabacalera_1_1130763.html
... A25: N02 | B25: Reglamento (UE) 2017/1001 sobre la marca de la UE, art. 15; STJUE C-355/96 Silhouette | C25: Agotamiento del derecho de marca sólo regional (EEE): importar desde terceros países producto genuino sin consentimiento del titular infringe la marca. | D25: PROBABLE | E25: https://eur-lex.europa.eu/eli/reg/2017/1001/oj
