Workbook

Sheet Plan 180 días
A1: Plan de ejecución de 180 días (26 semanas) — Proyecto A con vía B3 en validación
A2: Semana 1 = semana de aprobación de la Fase 0 por el promotor. 'Bloqueada' = depende de tercero o de un Go previo. Costes = HIPÓTESIS.
A4: ID | B4: Fase | C4: Tarea | D4: Responsable | E4: Depende de | F4: Inicio (sem) | G4: Duración (sem) | H4: Fin (sem) | I4: Coste est. (€) | J4: Riesgo | K4: KPI / evidencia de finalización | L4: Criterio Go/No-Go | M4: Estado | N4: S1 | O4: S2 | P4: S3 | Q4: S4 | R4: S5 | S4: S6 | T4: S7 | U4: S8 | V4: S9 | W4: S10 | X4: S11 | Y4: S12 | Z4: S13 | AA4: S14 | AB4: S15 | AC4: S16 | AD4: S17 | AE4: S18 | AF4: S19 | AG4: S20 | AH4: S21 | AI4: S22 | AJ4: S23 | AK4: S24 | AL4: S25 | AM4: S26
A5: 0.1 | B5: F0 Viabilidad Cuba | C5: Contratar abogado cubano autorizado (bufete habilitado para extranjeros) y abogado español de comercio exterior | D5: Promotor | E5: D01 | F5: 1 | G5: 2 | H5: =F5+G5-1 -> 2 | I5: 1500 | J5: Medio | K5: Cartas de encargo firmadas | L5: — | M5: Ejecutable ahora | N5: =IF(AND(1>=$F5,1<=$H5),1,"") -> 1 | O5: =IF(AND(2>=$F5,2<=$H5),1,"") -> 1 | P5: =IF(AND(3>=$F5,3<=$H5),1,"") | Q5: =IF(AND(4>=$F5,4<=$H5),1,"") | R5: =IF(AND(5>=$F5,5<=$H5),1,"") | S5: =IF(AND(6>=$F5,6<=$H5),1,"") | T5: =IF(AND(7>=$F5,7<=$H5),1,"") | U5: =IF(AND(8>=$F5,8<=$H5),1,"") | V5: =IF(AND(9>=$F5,9<=$H5),1,"") | W5: =IF(AND(10>=$F5,10<=$H5),1,"") | X5: =IF(AND(11>=$F5,11<=$H5),1,"") | Y5: =IF(AND(12>=$F5,12<=$H5),1,"") | Z5: =IF(AND(13>=$F5,13<=$H5),1,"") | AA5: =IF(AND(14>=$F5,14<=$H5),1,"") | AB5: =IF(AND(15>=$F5,15<=$H5),1,"") | AC5: =IF(AND(16>=$F5,16<=$H5),1,"") | AD5: =IF(AND(17>=$F5,17<=$H5),1,"") | AE5: =IF(AND(18>=$F5,18<=$H5),1,"") | AF5: =IF(AND(19>=$F5,19<=$H5),1,"") | AG5: =IF(AND(20>=$F5,20<=$H5),1,"") | AH5: =IF(AND(21>=$F5,21<=$H5),1,"") | AI5: =IF(AND(22>=$F5,22<=$H5),1,"") | AJ5: =IF(AND(23>=$F5,23<=$H5),1,"") | AK5: =IF(AND(24>=$F5,24<=$H5),1,"") | AL5: =IF(AND(25>=$F5,25<=$H5),1,"") | AM5: =IF(AND(26>=$F5,26<=$H5),1,"")
A6: 0.2 | B6: F0 Viabilidad Cuba | C6: Obtener del torcedor la identidad completa de la empresa fabricante/exportadora (Cuestionario torcedor) | D6: Promotor | E6: — | F6: 1 | G6: 2 | H6: =F6+G6-1 -> 2 | I6: 0 | J6: Alto | K6: Razón social, NIT, objeto social, contacto oficial | L6: Sin identidad verificable → NO-GO | M6: Ejecutable ahora | N6: =IF(AND(1>=$F6,1<=$H6),1,"") -> 1 | O6: =IF(AND(2>=$F6,2<=$H6),1,"") -> 1 | P6: =IF(AND(3>=$F6,3<=$H6),1,"") | Q6: =IF(AND(4>=$F6,4<=$H6),1,"") | R6: =IF(AND(5>=$F6,5<=$H6),1,"") | S6: =IF(AND(6>=$F6,6<=$H6),1,"") | T6: =IF(AND(7>=$F6,7<=$H6),1,"") | U6: =IF(AND(8>=$F6,8<=$H6),1,"") | V6: =IF(AND(9>=$F6,9<=$H6),1,"") | W6: =IF(AND(10>=$F6,10<=$H6),1,"") | X6: =IF(AND(11>=$F6,11<=$H6),1,"") | Y6: =IF(AND(12>=$F6,12<=$H6),1,"") | Z6: =IF(AND(13>=$F6,13<=$H6),1,"") | AA6: =IF(AND(14>=$F6,14<=$H6),1,"") | AB6: =IF(AND(15>=$F6,15<=$H6),1,"") | AC6: =IF(AND(16>=$F6,16<=$H6),1,"") | AD6: =IF(AND(17>=$F6,17<=$H6),1,"") | AE6: =IF(AND(18>=$F6,18<=$H6),1,"") | AF6: =IF(AND(19>=$F6,19<=$H6),1,"") | AG6: =IF(AND(20>=$F6,20<=$H6),1,"") | AH6: =IF(AND(21>=$F6,21<=$H6),1,"") | AI6: =IF(AND(22>=$F6,22<=$H6),1,"") | AJ6: =IF(AND(23>=$F6,23<=$H6),1,"") | AK6: =IF(AND(24>=$F6,24<=$H6),1,"") | AL6: =IF(AND(25>=$F6,25<=$H6),1,"") | AM6: =IF(AND(26>=$F6,26<=$H6),1,"")
A7: 0.3 | B7: F0 Viabilidad Cuba | C7: Enviar 'Solicitud de confirmación de capacidad legal de exportación' a la empresa y, en su caso, a Habanos S.A. | D7: Abogado cubano | E7: 0.1, 0.2 | F7: 3 | G7: 4 | H7: =F7+G7-1 -> 6 | I7: 0 | J7: Alto | K7: Respuesta escrita | L7: Negativa o silencio > 8 semanas → NO-GO A | M7: Bloqueada | N7: =IF(AND(1>=$F7,1<=$H7),1,"") | O7: =IF(AND(2>=$F7,2<=$H7),1,"") | P7: =IF(AND(3>=$F7,3<=$H7),1,"") -> 1 | Q7: =IF(AND(4>=$F7,4<=$H7),1,"") -> 1 | R7: =IF(AND(5>=$F7,5<=$H7),1,"") -> 1 | S7: =IF(AND(6>=$F7,6<=$H7),1,"") -> 1 | T7: =IF(AND(7>=$F7,7<=$H7),1,"") | U7: =IF(AND(8>=$F7,8<=$H7),1,"") | V7: =IF(AND(9>=$F7,9<=$H7),1,"") | W7: =IF(AND(10>=$F7,10<=$H7),1,"") | X7: =IF(AND(11>=$F7,11<=$H7),1,"") | Y7: =IF(AND(12>=$F7,12<=$H7),1,"") | Z7: =IF(AND(13>=$F7,13<=$H7),1,"") | AA7: =IF(AND(14>=$F7,14<=$H7),1,"") | AB7: =IF(AND(15>=$F7,15<=$H7),1,"") | AC7: =IF(AND(16>=$F7,16<=$H7),1,"") | AD7: =IF(AND(17>=$F7,17<=$H7),1,"") | AE7: =IF(AND(18>=$F7,18<=$H7),1,"") | AF7: =IF(AND(19>=$F7,19<=$H7),1,"") | AG7: =IF(AND(20>=$F7,20<=$H7),1,"") | AH7: =IF(AND(21>=$F7,21<=$H7),1,"") | AI7: =IF(AND(22>=$F7,22<=$H7),1,"") | AJ7: =IF(AND(23>=$F7,23<=$H7),1,"") | AK7: =IF(AND(24>=$F7,24<=$H7),1,"") | AL7: =IF(AND(25>=$F7,25<=$H7),1,"") | AM7: =IF(AND(26>=$F7,26<=$H7),1,"")
A8: 0.4 | B8: F0 Viabilidad Cuba | C8: Due diligence documental de la fábrica (Cuestionario DD) y verificación en Gaceta Oficial de licencias | D8: Abogado cubano | E8: 0.3 | F8: 5 | G8: 5 | H8: =F8+G8-1 -> 9 | I8: 3500 | J8: Alto | K8: Informe jurídico Cuba | L8: Condiciones C1 y C2 | M8: Bloqueada | N8: =IF(AND(1>=$F8,1<=$H8),1,"") | O8: =IF(AND(2>=$F8,2<=$H8),1,"") | P8: =IF(AND(3>=$F8,3<=$H8),1,"") | Q8: =IF(AND(4>=$F8,4<=$H8),1,"") | R8: =IF(AND(5>=$F8,5<=$H8),1,"") -> 1 | S8: =IF(AND(6>=$F8,6<=$H8),1,"") -> 1 | T8: =IF(AND(7>=$F8,7<=$H8),1,"") -> 1 | U8: =IF(AND(8>=$F8,8<=$H8),1,"") -> 1 | V8: =IF(AND(9>=$F8,9<=$H8),1,"") -> 1 | W8: =IF(AND(10>=$F8,10<=$H8),1,"") | X8: =IF(AND(11>=$F8,11<=$H8),1,"") | Y8: =IF(AND(12>=$F8,12<=$H8),1,"") | Z8: =IF(AND(13>=$F8,13<=$H8),1,"") | AA8: =IF(AND(14>=$F8,14<=$H8),1,"") | AB8: =IF(AND(15>=$F8,15<=$H8),1,"") | AC8: =IF(AND(16>=$F8,16<=$H8),1,"") | AD8: =IF(AND(17>=$F8,17<=$H8),1,"") | AE8: =IF(AND(18>=$F8,18<=$H8),1,"") | AF8: =IF(AND(19>=$F8,19<=$H8),1,"") | AG8: =IF(AND(20>=$F8,20<=$H8),1,"") | AH8: =IF(AND(21>=$F8,21<=$H8),1,"") | AI8: =IF(AND(22>=$F8,22<=$H8),1,"") | AJ8: =IF(AND(23>=$F8,23<=$H8),1,"") | AK8: =IF(AND(24>=$F8,24<=$H8),1,"") | AL8: =IF(AND(25>=$F8,25<=$H8),1,"") | AM8: =IF(AND(26>=$F8,26<=$H8),1,"")
A9: 0.5 | B9: F0 Viabilidad Cuba | C9: Consulta a MINCEX sobre si un operador privado o cooperativa puede exportar tabaco torcido tras DL 133/2026 y Res. MINCEX 2026 | D9: Abogado cubano | E9: 0.1 | F9: 3 | G9: 6 | H9: =F9+G9-1 -> 8 | I9: 1000 | J9: Alto | K9: Respuesta / dictamen | L9: Confirma o descarta vías alternativas | M9: Bloqueada | N9: =IF(AND(1>=$F9,1<=$H9),1,"") | O9: =IF(AND(2>=$F9,2<=$H9),1,"") | P9: =IF(AND(3>=$F9,3<=$H9),1,"") -> 1 | Q9: =IF(AND(4>=$F9,4<=$H9),1,"") -> 1 | R9: =IF(AND(5>=$F9,5<=$H9),1,"") -> 1 | S9: =IF(AND(6>=$F9,6<=$H9),1,"") -> 1 | T9: =IF(AND(7>=$F9,7<=$H9),1,"") -> 1 | U9: =IF(AND(8>=$F9,8<=$H9),1,"") -> 1 | V9: =IF(AND(9>=$F9,9<=$H9),1,"") | W9: =IF(AND(10>=$F9,10<=$H9),1,"") | X9: =IF(AND(11>=$F9,11<=$H9),1,"") | Y9: =IF(AND(12>=$F9,12<=$H9),1,"") | Z9: =IF(AND(13>=$F9,13<=$H9),1,"") | AA9: =IF(AND(14>=$F9,14<=$H9),1,"") | AB9: =IF(AND(15>=$F9,15<=$H9),1,"") | AC9: =IF(AND(16>=$F9,16<=$H9),1,"") | AD9: =IF(AND(17>=$F9,17<=$H9),1,"") | AE9: =IF(AND(18>=$F9,18<=$H9),1,"") | AF9: =IF(AND(19>=$F9,19<=$H9),1,"") | AG9: =IF(AND(20>=$F9,20<=$H9),1,"") | AH9: =IF(AND(21>=$F9,21<=$H9),1,"") | AI9: =IF(AND(22>=$F9,22<=$H9),1,"") | AJ9: =IF(AND(23>=$F9,23<=$H9),1,"") | AK9: =IF(AND(24>=$F9,24<=$H9),1,"") | AL9: =IF(AND(25>=$F9,25<=$H9),1,"") | AM9: =IF(AND(26>=$F9,26<=$H9),1,"")
A10: 0.6 | B10: F0 Viabilidad Cuba | C10: Dictamen sobre propiedad de la marca y uso de 'Hecho en Cuba' / DO Habanos | D10: Abogado cubano + agente marcas | E10: 0.4 | F10: 8 | G10: 3 | H10: =F10+G10-1 -> 10 | I10: 1500 | J10: Alto | K10: Dictamen escrito | L10: Condición C2 | M10: Bloqueada | N10: =IF(AND(1>=$F10,1<=$H10),1,"") | O10: =IF(AND(2>=$F10,2<=$H10),1,"") | P10: =IF(AND(3>=$F10,3<=$H10),1,"") | Q10: =IF(AND(4>=$F10,4<=$H10),1,"") | R10: =IF(AND(5>=$F10,5<=$H10),1,"") | S10: =IF(AND(6>=$F10,6<=$H10),1,"") | T10: =IF(AND(7>=$F10,7<=$H10),1,"") | U10: =IF(AND(8>=$F10,8<=$H10),1,"") -> 1 | V10: =IF(AND(9>=$F10,9<=$H10),1,"") -> 1 | W10: =IF(AND(10>=$F10,10<=$H10),1,"") -> 1 | X10: =IF(AND(11>=$F10,11<=$H10),1,"") | Y10: =IF(AND(12>=$F10,12<=$H10),1,"") | Z10: =IF(AND(13>=$F10,13<=$H10),1,"") | AA10: =IF(AND(14>=$F10,14<=$H10),1,"") | AB10: =IF(AND(15>=$F10,15<=$H10),1,"") | AC10: =IF(AND(16>=$F10,16<=$H10),1,"") | AD10: =IF(AND(17>=$F10,17<=$H10),1,"") | AE10: =IF(AND(18>=$F10,18<=$H10),1,"") | AF10: =IF(AND(19>=$F10,19<=$H10),1,"") | AG10: =IF(AND(20>=$F10,20<=$H10),1,"") | AH10: =IF(AND(21>=$F10,21<=$H10),1,"") | AI10: =IF(AND(22>=$F10,22<=$H10),1,"") | AJ10: =IF(AND(23>=$F10,23<=$H10),1,"") | AK10: =IF(AND(24>=$F10,24<=$H10),1,"") | AL10: =IF(AND(25>=$F10,25<=$H10),1,"") | AM10: =IF(AND(26>=$F10,26<=$H10),1,"")
A11: 0.9 | B11: F0 Viabilidad Cuba | C11: Arnaldo: consentimiento escrito al uso de su nombre/firma, autorización de su empleador, firmas escaneadas y retrato opcional | D11: Promotor + abogado cubano | E11: 0.2 | F11: 1 | G11: 3 | H11: =F11+G11-1 -> 3 | I11: 0 | J11: Alto | K11: Consentimiento firmado + materiales | L11: Sin consentimiento → usar reserva FOLIO | M11: Ejecutable ahora | N11: =IF(AND(1>=$F11,1<=$H11),1,"") -> 1 | O11: =IF(AND(2>=$F11,2<=$H11),1,"") -> 1 | P11: =IF(AND(3>=$F11,3<=$H11),1,"") -> 1 | Q11: =IF(AND(4>=$F11,4<=$H11),1,"") | R11: =IF(AND(5>=$F11,5<=$H11),1,"") | S11: =IF(AND(6>=$F11,6<=$H11),1,"") | T11: =IF(AND(7>=$F11,7<=$H11),1,"") | U11: =IF(AND(8>=$F11,8<=$H11),1,"") | V11: =IF(AND(9>=$F11,9<=$H11),1,"") | W11: =IF(AND(10>=$F11,10<=$H11),1,"") | X11: =IF(AND(11>=$F11,11<=$H11),1,"") | Y11: =IF(AND(12>=$F11,12<=$H11),1,"") | Z11: =IF(AND(13>=$F11,13<=$H11),1,"") | AA11: =IF(AND(14>=$F11,14<=$H11),1,"") | AB11: =IF(AND(15>=$F11,15<=$H11),1,"") | AC11: =IF(AND(16>=$F11,16<=$H11),1,"") | AD11: =IF(AND(17>=$F11,17<=$H11),1,"") | AE11: =IF(AND(18>=$F11,18<=$H11),1,"") | AF11: =IF(AND(19>=$F11,19<=$H11),1,"") | AG11: =IF(AND(20>=$F11,20<=$H11),1,"") | AH11: =IF(AND(21>=$F11,21<=$H11),1,"") | AI11: =IF(AND(22>=$F11,22<=$H11),1,"") | AJ11: =IF(AND(23>=$F11,23<=$H11),1,"") | AK11: =IF(AND(24>=$F11,24<=$H11),1,"") | AL11: =IF(AND(25>=$F11,25<=$H11),1,"") | AM11: =IF(AND(26>=$F11,26<=$H11),1,"")
A12: 2.6 | B12: F2 Marca y producto | C12: Brief creativo a 3 estudios de packaging premium y selección | D12: Promotor | E12: 0.9 | F12: 2 | G12: 4 | H12: =F12+G12-1 -> 5 | I12: 0 | J12: Medio | K12: 3 presupuestos | L12: Encargo ≤ 15 k€ | M12: Ejecutable ahora | N12: =IF(AND(1>=$F12,1<=$H12),1,"") | O12: =IF(AND(2>=$F12,2<=$H12),1,"") -> 1 | P12: =IF(AND(3>=$F12,3<=$H12),1,"") -> 1 | Q12: =IF(AND(4>=$F12,4<=$H12),1,"") -> 1 | R12: =IF(AND(5>=$F12,5<=$H12),1,"") -> 1 | S12: =IF(AND(6>=$F12,6<=$H12),1,"") | T12: =IF(AND(7>=$F12,7<=$H12),1,"") | U12: =IF(AND(8>=$F12,8<=$H12),1,"") | V12: =IF(AND(9>=$F12,9<=$H12),1,"") | W12: =IF(AND(10>=$F12,10<=$H12),1,"") | X12: =IF(AND(11>=$F12,11<=$H12),1,"") | Y12: =IF(AND(12>=$F12,12<=$H12),1,"") | Z12: =IF(AND(13>=$F12,13<=$H12),1,"") | AA12: =IF(AND(14>=$F12,14<=$H12),1,"") | AB12: =IF(AND(15>=$F12,15<=$H12),1,"") | AC12: =IF(AND(16>=$F12,16<=$H12),1,"") | AD12: =IF(AND(17>=$F12,17<=$H12),1,"") | AE12: =IF(AND(18>=$F12,18<=$H12),1,"") | AF12: =IF(AND(19>=$F12,19<=$H12),1,"") | AG12: =IF(AND(20>=$F12,20<=$H12),1,"") | AH12: =IF(AND(21>=$F12,21<=$H12),1,"") | AI12: =IF(AND(22>=$F12,22<=$H12),1,"") | AJ12: =IF(AND(23>=$F12,23<=$H12),1,"") | AK12: =IF(AND(24>=$F12,24<=$H12),1,"") | AL12: =IF(AND(25>=$F12,25<=$H12),1,"") | AM12: =IF(AND(26>=$F12,26<=$H12),1,"")
A13: 0.7 | B13: F0 Viabilidad Cuba | C13: Rechazo formal de la oferta Behike 56 (plantilla en 08_COMMUNICATIONS) | D13: Promotor | E13: — | F13: 1 | G13: 1 | H13: =F13+G13-1 -> 1 | I13: 0 | J13: Alto | K13: Correo enviado/archivado | L13: — | M13: Ejecutable ahora (requiere aprobación) | N13: =IF(AND(1>=$F13,1<=$H13),1,"") -> 1 | O13: =IF(AND(2>=$F13,2<=$H13),1,"") | P13: =IF(AND(3>=$F13,3<=$H13),1,"") | Q13: =IF(AND(4>=$F13,4<=$H13),1,"") | R13: =IF(AND(5>=$F13,5<=$H13),1,"") | S13: =IF(AND(6>=$F13,6<=$H13),1,"") | T13: =IF(AND(7>=$F13,7<=$H13),1,"") | U13: =IF(AND(8>=$F13,8<=$H13),1,"") | V13: =IF(AND(9>=$F13,9<=$H13),1,"") | W13: =IF(AND(10>=$F13,10<=$H13),1,"") | X13: =IF(AND(11>=$F13,11<=$H13),1,"") | Y13: =IF(AND(12>=$F13,12<=$H13),1,"") | Z13: =IF(AND(13>=$F13,13<=$H13),1,"") | AA13: =IF(AND(14>=$F13,14<=$H13),1,"") | AB13: =IF(AND(15>=$F13,15<=$H13),1,"") | AC13: =IF(AND(16>=$F13,16<=$H13),1,"") | AD13: =IF(AND(17>=$F13,17<=$H13),1,"") | AE13: =IF(AND(18>=$F13,18<=$H13),1,"") | AF13: =IF(AND(19>=$F13,19<=$H13),1,"") | AG13: =IF(AND(20>=$F13,20<=$H13),1,"") | AH13: =IF(AND(21>=$F13,21<=$H13),1,"") | AI13: =IF(AND(22>=$F13,22<=$H13),1,"") | AJ13: =IF(AND(23>=$F13,23<=$H13),1,"") | AK13: =IF(AND(24>=$F13,24<=$H13),1,"") | AL13: =IF(AND(25>=$F13,25<=$H13),1,"") | AM13: =IF(AND(26>=$F13,26<=$H13),1,"")
A14: 0.8 | B14: F0 Viabilidad Cuba | C14: Comité de decisión Fase 0 | D14: Promotor | E14: 0.3–0.6 | F14: 11 | G14: 1 | H14: =F14+G14-1 -> 11 | I14: 0 | J14: — | K14: Acta con decisión | L14: Go si C1+C2; si no, activar plan alternativo | M14: Bloqueada | N14: =IF(AND(1>=$F14,1<=$H14),1,"") | O14: =IF(AND(2>=$F14,2<=$H14),1,"") | P14: =IF(AND(3>=$F14,3<=$H14),1,"") | Q14: =IF(AND(4>=$F14,4<=$H14),1,"") | R14: =IF(AND(5>=$F14,5<=$H14),1,"") | S14: =IF(AND(6>=$F14,6<=$H14),1,"") | T14: =IF(AND(7>=$F14,7<=$H14),1,"") | U14: =IF(AND(8>=$F14,8<=$H14),1,"") | V14: =IF(AND(9>=$F14,9<=$H14),1,"") | W14: =IF(AND(10>=$F14,10<=$H14),1,"") | X14: =IF(AND(11>=$F14,11<=$H14),1,"") -> 1 | Y14: =IF(AND(12>=$F14,12<=$H14),1,"") | Z14: =IF(AND(13>=$F14,13<=$H14),1,"") | AA14: =IF(AND(14>=$F14,14<=$H14),1,"") | AB14: =IF(AND(15>=$F14,15<=$H14),1,"") | AC14: =IF(AND(16>=$F14,16<=$H14),1,"") | AD14: =IF(AND(17>=$F14,17<=$H14),1,"") | AE14: =IF(AND(18>=$F14,18<=$H14),1,"") | AF14: =IF(AND(19>=$F14,19<=$H14),1,"") | AG14: =IF(AND(20>=$F14,20<=$H14),1,"") | AH14: =IF(AND(21>=$F14,21<=$H14),1,"") | AI14: =IF(AND(22>=$F14,22<=$H14),1,"") | AJ14: =IF(AND(23>=$F14,23<=$H14),1,"") | AK14: =IF(AND(24>=$F14,24<=$H14),1,"") | AL14: =IF(AND(25>=$F14,25<=$H14),1,"") | AM14: =IF(AND(26>=$F14,26<=$H14),1,"")
A15: 1.1 | B15: F1 España y estructura | C15: Dictamen fiscal España–Andorra (residencia, dirección efectiva, retribución) | D15: Asesor fiscal | E15: D06 | F15: 2 | G15: 4 | H15: =F15+G15-1 -> 5 | I15: 1500 | J15: Medio | K15: Dictamen | L15: Estructura elegida | M15: Ejecutable ahora | N15: =IF(AND(1>=$F15,1<=$H15),1,"") | O15: =IF(AND(2>=$F15,2<=$H15),1,"") -> 1 | P15: =IF(AND(3>=$F15,3<=$H15),1,"") -> 1 | Q15: =IF(AND(4>=$F15,4<=$H15),1,"") -> 1 | R15: =IF(AND(5>=$F15,5<=$H15),1,"") -> 1 | S15: =IF(AND(6>=$F15,6<=$H15),1,"") | T15: =IF(AND(7>=$F15,7<=$H15),1,"") | U15: =IF(AND(8>=$F15,8<=$H15),1,"") | V15: =IF(AND(9>=$F15,9<=$H15),1,"") | W15: =IF(AND(10>=$F15,10<=$H15),1,"") | X15: =IF(AND(11>=$F15,11<=$H15),1,"") | Y15: =IF(AND(12>=$F15,12<=$H15),1,"") | Z15: =IF(AND(13>=$F15,13<=$H15),1,"") | AA15: =IF(AND(14>=$F15,14<=$H15),1,"") | AB15: =IF(AND(15>=$F15,15<=$H15),1,"") | AC15: =IF(AND(16>=$F15,16<=$H15),1,"") | AD15: =IF(AND(17>=$F15,17<=$H15),1,"") | AE15: =IF(AND(18>=$F15,18<=$H15),1,"") | AF15: =IF(AND(19>=$F15,19<=$H15),1,"") | AG15: =IF(AND(20>=$F15,20<=$H15),1,"") | AH15: =IF(AND(21>=$F15,21<=$H15),1,"") | AI15: =IF(AND(22>=$F15,22<=$H15),1,"") | AJ15: =IF(AND(23>=$F15,23<=$H15),1,"") | AK15: =IF(AND(24>=$F15,24<=$H15),1,"") | AL15: =IF(AND(25>=$F15,25<=$H15),1,"") | AM15: =IF(AND(26>=$F15,26<=$H15),1,"")
A16: 1.2 | B16: F1 España y estructura | C16: Verificar con CMT requisitos de habilitación como fabricante/titular de marca y como importador | D16: Asesor regulatorio | E16: — | F16: 2 | G16: 3 | H16: =F16+G16-1 -> 4 | I16: 500 | J16: Bajo | K16: Correo/consulta del CMT | L16: — | M16: Ejecutable ahora | N16: =IF(AND(1>=$F16,1<=$H16),1,"") | O16: =IF(AND(2>=$F16,2<=$H16),1,"") -> 1 | P16: =IF(AND(3>=$F16,3<=$H16),1,"") -> 1 | Q16: =IF(AND(4>=$F16,4<=$H16),1,"") -> 1 | R16: =IF(AND(5>=$F16,5<=$H16),1,"") | S16: =IF(AND(6>=$F16,6<=$H16),1,"") | T16: =IF(AND(7>=$F16,7<=$H16),1,"") | U16: =IF(AND(8>=$F16,8<=$H16),1,"") | V16: =IF(AND(9>=$F16,9<=$H16),1,"") | W16: =IF(AND(10>=$F16,10<=$H16),1,"") | X16: =IF(AND(11>=$F16,11<=$H16),1,"") | Y16: =IF(AND(12>=$F16,12<=$H16),1,"") | Z16: =IF(AND(13>=$F16,13<=$H16),1,"") | AA16: =IF(AND(14>=$F16,14<=$H16),1,"") | AB16: =IF(AND(15>=$F16,15<=$H16),1,"") | AC16: =IF(AND(16>=$F16,16<=$H16),1,"") | AD16: =IF(AND(17>=$F16,17<=$H16),1,"") | AE16: =IF(AND(18>=$F16,18<=$H16),1,"") | AF16: =IF(AND(19>=$F16,19<=$H16),1,"") | AG16: =IF(AND(20>=$F16,20<=$H16),1,"") | AH16: =IF(AND(21>=$F16,21<=$H16),1,"") | AI16: =IF(AND(22>=$F16,22<=$H16),1,"") | AJ16: =IF(AND(23>=$F16,23<=$H16),1,"") | AK16: =IF(AND(24>=$F16,24<=$H16),1,"") | AL16: =IF(AND(25>=$F16,25<=$H16),1,"") | AM16: =IF(AND(26>=$F16,26<=$H16),1,"")
... A39: 6.2 | B39: F6 Primera operación | C39: Importación, control en destino, primeras ventas (fuera del horizonte de 180 días) | D39: Operador logístico | E39: 6.1 | F39: 26 | G39: 1 | H39: =F39+G39-1 -> 26 | I39: 0 | J39: Alto | K39: DUA + PVP en BOE | L39: — | M39: Bloqueada | N39: =IF(AND(1>=$F39,1<=$H39),1,"") | O39: =IF(AND(2>=$F39,2<=$H39),1,"") | P39: =IF(AND(3>=$F39,3<=$H39),1,"") | Q39: =IF(AND(4>=$F39,4<=$H39),1,"") | R39: =IF(AND(5>=$F39,5<=$H39),1,"") | S39: =IF(AND(6>=$F39,6<=$H39),1,"") | T39: =IF(AND(7>=$F39,7<=$H39),1,"") | U39: =IF(AND(8>=$F39,8<=$H39),1,"") | V39: =IF(AND(9>=$F39,9<=$H39),1,"") | W39: =IF(AND(10>=$F39,10<=$H39),1,"") | X39: =IF(AND(11>=$F39,11<=$H39),1,"") | Y39: =IF(AND(12>=$F39,12<=$H39),1,"") | Z39: =IF(AND(13>=$F39,13<=$H39),1,"") | AA39: =IF(AND(14>=$F39,14<=$H39),1,"") | AB39: =IF(AND(15>=$F39,15<=$H39),1,"") | AC39: =IF(AND(16>=$F39,16<=$H39),1,"") | AD39: =IF(AND(17>=$F39,17<=$H39),1,"") | AE39: =IF(AND(18>=$F39,18<=$H39),1,"") | AF39: =IF(AND(19>=$F39,19<=$H39),1,"") | AG39: =IF(AND(20>=$F39,20<=$H39),1,"") | AH39: =IF(AND(21>=$F39,21<=$H39),1,"") | AI39: =IF(AND(22>=$F39,22<=$H39),1,"") | AJ39: =IF(AND(23>=$F39,23<=$H39),1,"") | AK39: =IF(AND(24>=$F39,24<=$H39),1,"") | AL39: =IF(AND(25>=$F39,25<=$H39),1,"") | AM39: =IF(AND(26>=$F39,26<=$H39),1,"") -> 1
H41: Coste total estimado | I41: =SUM(I5:I39) -> 25100

Sheet Vistas 30-60-90-180
A1: Resumen por horizonte (calculado desde el plan)
A4: Horizonte | B4: Semana fin | C4: Tareas que terminan | D4: de ellas ejecutables ahora | E4: Bloqueadas | F4: Coste acumulado (€)
A5: 30 días | B5: 4 | C5: =COUNTIF('Plan 180 días'!$H$5:$H$39,"<="&B5) -> 7 | D5: =COUNTIFS('Plan 180 días'!$H$5:$H$39,"<="&B5,'Plan 180 días'!$M$5:$M$39,"Ejecutable*") -> 7 | E5: =COUNTIFS('Plan 180 días'!$H$5:$H$39,"<="&B5,'Plan 180 días'!$M$5:$M$39,"Bloq*") -> 0 | F5: =SUMIF('Plan 180 días'!$H$5:$H$39,"<="&B5,'Plan 180 días'!$I$5:$I$39) -> 2000
A6: 60 días | B6: 9 | C6: =COUNTIF('Plan 180 días'!$H$5:$H$39,"<="&B6) -> 15 | D6: =COUNTIFS('Plan 180 días'!$H$5:$H$39,"<="&B6,'Plan 180 días'!$M$5:$M$39,"Ejecutable*") -> 12 | E6: =COUNTIFS('Plan 180 días'!$H$5:$H$39,"<="&B6,'Plan 180 días'!$M$5:$M$39,"Bloq*") -> 3 | F6: =SUMIF('Plan 180 días'!$H$5:$H$39,"<="&B6,'Plan 180 días'!$I$5:$I$39) -> 10000
A7: 90 días | B7: 13 | C7: =COUNTIF('Plan 180 días'!$H$5:$H$39,"<="&B7) -> 20 | D7: =COUNTIFS('Plan 180 días'!$H$5:$H$39,"<="&B7,'Plan 180 días'!$M$5:$M$39,"Ejecutable*") -> 14 | E7: =COUNTIFS('Plan 180 días'!$H$5:$H$39,"<="&B7,'Plan 180 días'!$M$5:$M$39,"Bloq*") -> 6 | F7: =SUMIF('Plan 180 días'!$H$5:$H$39,"<="&B7,'Plan 180 días'!$I$5:$I$39) -> 12100
A8: 180 días | B8: 26 | C8: =COUNTIF('Plan 180 días'!$H$5:$H$39,"<="&B8) -> 35 | D8: =COUNTIFS('Plan 180 días'!$H$5:$H$39,"<="&B8,'Plan 180 días'!$M$5:$M$39,"Ejecutable*") -> 14 | E8: =COUNTIFS('Plan 180 días'!$H$5:$H$39,"<="&B8,'Plan 180 días'!$M$5:$M$39,"Bloq*") -> 21 | F8: =SUMIF('Plan 180 días'!$H$5:$H$39,"<="&B8,'Plan 180 días'!$I$5:$I$39) -> 25100
A11: Qué se hace en cada horizonte
A12: Horizonte | B12: Contenido
A13: 0–30 días | B13: Contratar abogados (0.1), identidad de la fábrica (0.2), rechazo Behike (0.7), dictamen fiscal arrancado (1.1), consultas CMT/TARIC/BOE (1.2–1.4), banco (1.5), informe de marcas (2.1), mapa de expendedurías y fabricantes B3 (5.1, 5.4).
A14: 31–60 días | B14: Respuesta de capacidad legal (0.3), consulta MINCEX (0.5), DD documental en curso (0.4), solicitud EUIPO si informe favorable (2.2).
A15: 61–90 días | B15: Dictamen de marca y DO (0.6), comité Fase 0 (0.8). Si NO-GO: activar vía B3 o marca en origen alternativo. Si GO: SL, cotización FOB, ficha técnica.
A16: 91–180 días | B16: Prototipos y catas, term sheet y contrato, habilitaciones CMT, EU-CEG, trazabilidad, PVP en BOE, cartas de interés y distribuidor. Pedido piloto sólo con 8/8 condiciones.
